Workbook
Name cellLeft: #REF!
Name VALUEVX: LAMBDA(42.314159)

Sheet Septiembre
E1: CONTROL DE CITAS | AN1: Fecha | AO1: Consultorio | AP1: Estado | AQ1: Paciente | AR1: Precio | AS1: Tipo | AT1: Forma1 | AU1: Monto1 | AV1: Forma2 | AW1: Monto2 | AX1: Empleado
E2: Centro Médico Comunitario OscaryAnny | M2: $ USD: | N2: =IFERROR(__xludf.DUMMYFUNCTION("IMPORTXML(""https://www.bcv.org.ve/"", ""//*[@id='dolar']//strong"", ""es_VE"")"),888.8909) -> 888.8909
M3: Fecha Valor: | N3: =IFERROR(__xludf.DUMMYFUNCTION("IMPORTXML(""https://www.bcv.org.ve/"", ""(//span[@class='date-display-single'])[1]"", ""es_VE"")"),46324) -> 46324
A4: 46266 | AE4: TOTAL DEL MES
A5: Hora | B5: Name | C5: Consultorio N° 1 | G5: Consultorio N° 2 | K5: Consultorio N° 3 | S5: Consultorio N° 1 | W5: Consultorio N° 2 | AA5: Consultorio N° 3 | AE5: Doctor | AG5: Cantidad citas | AH5: Citas pagadas | AI5: Total | AJ5: Monto Cobrado | AK5: Monto ADH | AL5: Monto Médico | AN5: Fecha | AO5: Consultorio | AP5: Estado | AQ5: Paciente | AR5: Precio | AS5: Tipo | AT5: Forma 1 | AU5: Monto 1 | AV5: Forma 2 | AW5: Monto 2 | AX5: Empleado | AY5: Doctor | BA5: CONSULTA BENEFICIO DE EMPLEADO DEL MES | BF5: CONSULTAS 50% DESC./ FAMILIAR DIRECTO DEL MES | BL5: CONSULTA BENEFICIO DE PARTICIPANTES ADH DEL MES
A6: =Q12 -> 0.33333333 | E6: Representante: | F6: =IF(D6<>"", VLOOKUP(D6,'Base de Datos'!$A$2:$D1268,2,FALSE()),"") | I6: Representante: | J6: =IF(H6<>"", VLOOKUP(H6,'Base de Datos'!$A$2:$D1268,2,FALSE()),"") | M6: Representante: | N6: =IF(L6<>"", VLOOKUP(L6,'Base de Datos'!$A$2:$D1268,2,FALSE()),"") | T6: Precio: | X6: Precio: | AB6: Precio: | AE6: Dra. Rosanny García | AG6: =COUNTIFS(AP:AP, "💲", AY:AY, AE6) + COUNTIFS(AP:AP, "📦", AY:AY, AE6) + COUNTIFS(AP:AP, "✅", AY:AY, AE6) -> 1 | AH6: =COUNTIFS(AP:AP, "💲", AY:AY, AE6) + COUNTIFS(AP:AP, "📦", AY:AY, AE6) -> 1 | AI6: =SUMIFS(AR:AR, AY:AY, AE6, AP:AP, "💲") + SUMIFS(AR:AR, AY:AY, AE6, AP:AP, "📦") -> 50 | AJ6: =( SUMIFS(AR:AR, AY:AY, INDIRECT("AE" & ROW()), AP:AP, "💲") + SUMIFS(AR:AR, AY:AY, INDIRECT("AE" & ROW()), AP:AP, "📦") ) - ( SUMIFS(AR:AR, AY:AY, INDIRECT("AE" & ROW()), AP:AP, "💲", AS:AS, "Participante") + SUMIFS(AR:AR, AY:AY, INDIRECT("AE" & ROW()), AP:AP, "📦", AS:AS, "Participante") ) - ( SUMIFS(AR:AR, AY:AY, INDIRECT("AE" & ROW()), AP:AP, "💲", AS:AS, "Empleado") + SUMIFS(AR:AR, AY:AY, INDIRECT("AE" & ROW()), AP:AP, "📦", AS:AS, "Empleado") ) - ( ( SUMIFS(AR:AR, AY:AY, INDIRECT("AE" & ROW()), AP:AP, "💲", AS:AS, "Familiar") + SUMIFS(AR:AR, AY:AY, INDIRECT("AE" & ROW()), AP:AP, "📦", AS:AS, "Familiar") ) / 2 ) - ( ( SUMIFS(AR:AR, AY:AY, INDIRECT("AE" & ROW()), AP:AP, "💲", AS:AS, "Exonerado ADH") + SUMIFS(AR:AR, AY:AY, INDIRECT("AE" & ROW()), AP:AP, "📦", AS:AS, "Exonerado ADH") ) / 2 ) - ( ( SUMIFS(AR:AR, AY:AY, INDIRECT("AE" & ROW()), AP:AP, "💲", AS:AS, "Exonerado Doctor") + SUMIFS(AR:AR, AY:AY, INDIRECT("AE" & ROW()), AP:AP, "📦", AS:AS, "Exonerado Doctor") ) / 2 ) -> 0 | AK6: =( SUMIFS(AR:AR, AY:AY, INDIRECT("AE" & ROW()), AP:AP, "💲") + SUMIFS(AR:AR, AY:AY, INDIRECT("AE" & ROW()), AP:AP, "📦") ) - ( SUMIFS(AR:AR, AY:AY, INDIRECT("AE" & ROW()), AP:AP, "💲", AS:AS, "Familiar") + SUMIFS(AR:AR, AY:AY, INDIRECT("AE" & ROW()), AP:AP, "📦", AS:AS, "Familiar") ) - ( SUMIFS(AR:AR, AY:AY, INDIRECT("AE" & ROW()), AP:AP, "💲", AS:AS, "Participante") + SUMIFS(AR:AR, AY:AY, INDIRECT("AE" & ROW()), AP:AP, "📦", AS:AS, "Participante") ) - ( SUMIFS(AR:AR, AY:AY, INDIRECT("AE" & ROW()), AP:AP, "💲", AS:AS, "Empleado") + SUMIFS(AR:AR, AY:AY, INDIRECT("AE" & ROW()), AP:AP, "📦", AS:AS, "Empleado") ) - ( SUMIFS(AR:AR, AY:AY, INDIRECT("AE" & ROW()), AP:AP, "💲", AS:AS, "Exonerado ADH") + SUMIFS(AR:AR, AY:AY, INDIRECT("AE" & ROW()), AP:AP, "📦", AS:AS, "Exonerado ADH") ) - (( SUMIFS(AR:AR, AY:AY, INDIRECT("AE" & ROW()), AP:AP, "💲", AS:AS, "Exonerado Doctor") + SUMIFS(AR:AR, AY:AY, INDIRECT("AE" & ROW()), AP:AP, "📦", AS:AS, "Exonerado Doctor") ) / 2 )- ( ( SUMIFS(AR:AR, AY:AY, INDIRECT("AE" & ROW()), AP:AP, "💲", AS:AS, "") + SUMIFS(AR:AR, AY:AY, INDIRECT("AE" & ROW()), AP:AP, "📦", AS:AS, "") ) / 2 ) -> 0 | AL6: =( SUMIFS(AR:AR, AY:AY, INDIRECT("AE" & ROW()), AP:AP, "💲") + SUMIFS(AR:AR, AY:AY, INDIRECT("AE" & ROW()), AP:AP, "📦") ) - (( SUMIFS(AR:AR, AY:AY, INDIRECT("AE" & ROW()), AP:AP, "💲", AS:AS, "Familiar") + SUMIFS(AR:AR, AY:AY, INDIRECT("AE" & ROW()), AP:AP, "📦", AS:AS, "Familiar") ) / 2 ) - (( SUMIFS(AR:AR, AY:AY, INDIRECT("AE" & ROW()), AP:AP, "💲", AS:AS, "Participante") + SUMIFS(AR:AR, AY:AY, INDIRECT("AE" & ROW()), AP:AP, "📦", AS:AS, "Participante") ) / 2 ) - (( SUMIFS(AR:AR, AY:AY, INDIRECT("AE" & ROW()), AP:AP, "💲", AS:AS, "Empleado") + SUMIFS(AR:AR, AY:AY, INDIRECT("AE" & ROW()), AP:AP, "📦", AS:AS, "Empleado") ) / 2 ) - (( SUMIFS(AR:AR, AY:AY, INDIRECT("AE" & ROW()), AP:AP, "💲", AS:AS, "Exonerado ADH") + SUMIFS(AR:AR, AY:AY, INDIRECT("AE" & ROW()), AP:AP, "📦", AS:AS, "Exonerado ADH") ) / 2 ) - ( SUMIFS(AR:AR, AY:AY, INDIRECT("AE" & ROW()), AP:AP, "💲", AS:AS, "Exonerado Doctor") + SUMIFS(AR:AR, AY:AY, INDIRECT("AE" & ROW()), AP:AP, "📦", AS:AS, "Exonerado Doctor") )- ( ( SUMIFS(AR:AR, AY:AY, INDIRECT("AE" & ROW()), AP:AP, "💲", AS:AS, "") + SUMIFS(AR:AR, AY:AY, INDIRECT("AE" & ROW()), AP:AP, "📦", AS:AS, "") ) / 2 ) -> 25 | AN6: =A4 -> 46266 | AO6: =C5 -> Consultorio N° 1 | AP6: =C6 -> 0 | AQ6: =D6 -> 0 | AR6: =U6 -> 0 | AS6: =S6 -> 0 | AT6: =S7 -> 0 | AU6: =U7 -> 0 | AV6: =S8 -> 0 | AW6: =U8 -> 0 | AX6: =U9 -> 0 | AY6: =F9 -> 0 | BA6: Nombre y Apellido | BB6: Fecha | BC6: Monto | BD6: Doctor | BF6: Nombre y Apellido | BG6: Personal ADH | BH6: Fecha | BI6: Monto | BJ6: Doctor | BL6: Nombre y Apellido | BM6: Fecha | BN6: Monto
E7: Teléfono: | F7: =IF(D6<>"", VLOOKUP(D6,'Base de Datos'!$A$2:$D1268,3,FALSE()),"") | I7: Teléfono: | J7: =IF(H6<>"", VLOOKUP(H6,'Base de Datos'!$A$2:$D1268,3,FALSE()),"") | M7: Teléfono: | N7: =IF(L6<>"", VLOOKUP(L6,'Base de Datos'!$A$2:$D1268,3,FALSE()),"") | AE7: Dra. Maribel Guilarte | AG7: =COUNTIFS(AP:AP, "💲", AY:AY, AE7) + COUNTIFS(AP:AP, "📦", AY:AY, AE7) + COUNTIFS(AP:AP, "✅", AY:AY, AE7) -> 1 | AH7: =COUNTIFS(AP:AP, "💲", AY:AY, AE7) + COUNTIFS(AP:AP, "📦", AY:AY, AE7) -> 1 | AI7: =SUMIFS(AR:AR, AY:AY, AE7, AP:AP, "💲") + SUMIFS(AR:AR, AY:AY, AE7, AP:AP, "📦") -> 50 | AJ7: =( SUMIFS(AR:AR, AY:AY, INDIRECT("AE" & ROW()), AP:AP, "💲") + SUMIFS(AR:AR, AY:AY, INDIRECT("AE" & ROW()), AP:AP, "📦") ) - ( SUMIFS(AR:AR, AY:AY, INDIRECT("AE" & ROW()), AP:AP, "💲", AS:AS, "Participante") + SUMIFS(AR:AR, AY:AY, INDIRECT("AE" & ROW()), AP:AP, "📦", AS:AS, "Participante") ) - ( SUMIFS(AR:AR, AY:AY, INDIRECT("AE" & ROW()), AP:AP, "💲", AS:AS, "Empleado") + SUMIFS(AR:AR, AY:AY, INDIRECT("AE" & ROW()), AP:AP, "📦", AS:AS, "Empleado") ) - ( ( SUMIFS(AR:AR, AY:AY, INDIRECT("AE" & ROW()), AP:AP, "💲", AS:AS, "Familiar") + SUMIFS(AR:AR, AY:AY, INDIRECT("AE" & ROW()), AP:AP, "📦", AS:AS, "Familiar") ) / 2 ) - ( ( SUMIFS(AR:AR, AY:AY, INDIRECT("AE" & ROW()), AP:AP, "💲", AS:AS, "Exonerado ADH") + SUMIFS(AR:AR, AY:AY, INDIRECT("AE" & ROW()), AP:AP, "📦", AS:AS, "Exonerado ADH") ) / 2 ) - ( ( SUMIFS(AR:AR, AY:AY, INDIRECT("AE" & ROW()), AP:AP, "💲", AS:AS, "Exonerado Doctor") + SUMIFS(AR:AR, AY:AY, INDIRECT("AE" & ROW()), AP:AP, "📦", AS:AS, "Exonerado Doctor") ) / 2 ) -> 0 | AK7: =( SUMIFS(AR:AR, AY:AY, INDIRECT("AE" & ROW()), AP:AP, "💲") + SUMIFS(AR:AR, AY:AY, INDIRECT("AE" & ROW()), AP:AP, "📦") ) - ( SUMIFS(AR:AR, AY:AY, INDIRECT("AE" & ROW()), AP:AP, "💲", AS:AS, "Familiar") + SUMIFS(AR:AR, AY:AY, INDIRECT("AE" & ROW()), AP:AP, "📦", AS:AS, "Familiar") ) - ( SUMIFS(AR:AR, AY:AY, INDIRECT("AE" & ROW()), AP:AP, "💲", AS:AS, "Participante") + SUMIFS(AR:AR, AY:AY, INDIRECT("AE" & ROW()), AP:AP, "📦", AS:AS, "Participante") ) - ( SUMIFS(AR:AR, AY:AY, INDIRECT("AE" & ROW()), AP:AP, "💲", AS:AS, "Empleado") + SUMIFS(AR:AR, AY:AY, INDIRECT("AE" & ROW()), AP:AP, "📦", AS:AS, "Empleado") ) - ( SUMIFS(AR:AR, AY:AY, INDIRECT("AE" & ROW()), AP:AP, "💲", AS:AS, "Exonerado ADH") + SUMIFS(AR:AR, AY:AY, INDIRECT("AE" & ROW()), AP:AP, "📦", AS:AS, "Exonerado ADH") ) - (( SUMIFS(AR:AR, AY:AY, INDIRECT("AE" & ROW()), AP:AP, "💲", AS:AS, "Exonerado Doctor") + SUMIFS(AR:AR, AY:AY, INDIRECT("AE" & ROW()), AP:AP, "📦", AS:AS, "Exonerado Doctor") ) / 2 )- ( ( SUMIFS(AR:AR, AY:AY, INDIRECT("AE" & ROW()), AP:AP, "💲", AS:AS, "") + SUMIFS(AR:AR, AY:AY, INDIRECT("AE" & ROW()), AP:AP, "📦", AS:AS, "") ) / 2 ) -> 0 | AL7: =( SUMIFS(AR:AR, AY:AY, INDIRECT("AE" & ROW()), AP:AP, "💲") + SUMIFS(AR:AR, AY:AY, INDIRECT("AE" & ROW()), AP:AP, "📦") ) - (( SUMIFS(AR:AR, AY:AY, INDIRECT("AE" & ROW()), AP:AP, "💲", AS:AS, "Familiar") + SUMIFS(AR:AR, AY:AY, INDIRECT("AE" & ROW()), AP:AP, "📦", AS:AS, "Familiar") ) / 2 ) - (( SUMIFS(AR:AR, AY:AY, INDIRECT("AE" & ROW()), AP:AP, "💲", AS:AS, "Participante") + SUMIFS(AR:AR, AY:AY, INDIRECT("AE" & ROW()), AP:AP, "📦", AS:AS, "Participante") ) / 2 ) - (( SUMIFS(AR:AR, AY:AY, INDIRECT("AE" & ROW()), AP:AP, "💲", AS:AS, "Empleado") + SUMIFS(AR:AR, AY:AY, INDIRECT("AE" & ROW()), AP:AP, "📦", AS:AS, "Empleado") ) / 2 ) - (( SUMIFS(AR:AR, AY:AY, INDIRECT("AE" & ROW()), AP:AP, "💲", AS:AS, "Exonerado ADH") + SUMIFS(AR:AR, AY:AY, INDIRECT("AE" & ROW()), AP:AP, "📦", AS:AS, "Exonerado ADH") ) / 2 ) - ( SUMIFS(AR:AR, AY:AY, INDIRECT("AE" & ROW()), AP:AP, "💲", AS:AS, "Exonerado Doctor") + SUMIFS(AR:AR, AY:AY, INDIRECT("AE" & ROW()), AP:AP, "📦", AS:AS, "Exonerado Doctor") )- ( ( SUMIFS(AR:AR, AY:AY, INDIRECT("AE" & ROW()), AP:AP, "💲", AS:AS, "") + SUMIFS(AR:AR, AY:AY, INDIRECT("AE" & ROW()), AP:AP, "📦", AS:AS, "") ) / 2 ) -> 25 | AN7: =A4 -> 46266 | AO7: =C5 -> Consultorio N° 1 | AP7: =C10 -> 0 | AQ7: =D10 -> 0 | AR7: =U10 -> 0 | AS7: =S10 -> 0 | AT7: =S11 -> 0 | AU7: =U11 -> 0 | AV7: =S12 -> 0 | AW7: =U12 -> 0 | AX7: =U13 -> 0 | AY7: =F13 -> 0 | BA7: =IFERROR(__xludf.DUMMYFUNCTION("QUERY(AN:AY, ""SELECT AQ, AN, AR, AY WHERE AS = 'Empleado' AND (AP = '💲' OR AP = '📦') ORDER BY AN"", )"),"Silvia D´Angelo") -> Silvia D´Angelo | BB7: =IFERROR(__xludf.DUMMYFUNCTION("""COMPUTED_VALUE"""),46273) -> 46273 | BC7: =IFERROR(__xludf.DUMMYFUNCTION("""COMPUTED_VALUE"""),50) -> 50 | BD7: =IFERROR(__xludf.DUMMYFUNCTION("""COMPUTED_VALUE"""),"Dra. Mónica Porras") -> Dra. Mónica Porras | BF7: =IFERROR(__xludf.DUMMYFUNCTION("QUERY(AN:AY, ""SELECT AQ, AX, AN, AR, AY WHERE AS = 'Familiar' AND (AP = '💲' OR AP = '📦') ORDER BY AN"", )"),"Carla Segura") -> Carla Segura | BH7: =IFERROR(__xludf.DUMMYFUNCTION("""COMPUTED_VALUE"""),46280) -> 46280 | BI7: =IFERROR(__xludf.DUMMYFUNCTION("""COMPUTED_VALUE"""),50) -> 50 | BJ7: =IFERROR(__xludf.DUMMYFUNCTION("""COMPUTED_VALUE"""),"Dra. Mónica Porras") -> Dra. Mónica Porras | BL7: =IFERROR(__xludf.DUMMYFUNCTION("QUERY(AN:AY, ""SELECT AQ, AN, AR WHERE AS = 'Participante' AND (AP = '💲' OR AP = '📦') ORDER BY AN"", )"),"Moises Rodriguez") -> Moises Rodriguez | BM7: =IFERROR(__xludf.DUMMYFUNCTION("""COMPUTED_VALUE"""),46272) -> 46272 | BN7: =IFERROR(__xludf.DUMMYFUNCTION("""COMPUTED_VALUE"""),50) -> 50
E8: Cedula: | F8: =IF(D6<>"", VLOOKUP(D6,'Base de Datos'!$A$2:$D1268,4,FALSE()),"") | I8: Cedula: | J8: =IF(H6<>"", VLOOKUP(H6,'Base de Datos'!$A$2:$D1268,4,FALSE()),"") | M8: Cedula: | N8: =IF(L6<>"", VLOOKUP(L6,'Base de Datos'!$A$2:$D1268,4,FALSE()),"") | AE8: Dra. Lyl Belisario | AG8: =COUNTIFS(AP:AP, "💲", AY:AY, AE8) + COUNTIFS(AP:AP, "📦", AY:AY, AE8) + COUNTIFS(AP:AP, "✅", AY:AY, AE8) -> 0 | AH8: =COUNTIFS(AP:AP, "💲", AY:AY, AE8) + COUNTIFS(AP:AP, "📦", AY:AY, AE8) -> 0 | AI8: =SUMIFS(AR:AR, AY:AY, AE8, AP:AP, "💲") + SUMIFS(AR:AR, AY:AY, AE8, AP:AP, "📦") -> 0 | AJ8: =( SUMIFS(AR:AR, AY:AY, INDIRECT("AE" & ROW()), AP:AP, "💲") + SUMIFS(AR:AR, AY:AY, INDIRECT("AE" & ROW()), AP:AP, "📦") ) - ( SUMIFS(AR:AR, AY:AY, INDIRECT("AE" & ROW()), AP:AP, "💲", AS:AS, "Participante") + SUMIFS(AR:AR, AY:AY, INDIRECT("AE" & ROW()), AP:AP, "📦", AS:AS, "Participante") ) - ( SUMIFS(AR:AR, AY:AY, INDIRECT("AE" & ROW()), AP:AP, "💲", AS:AS, "Empleado") + SUMIFS(AR:AR, AY:AY, INDIRECT("AE" & ROW()), AP:AP, "📦", AS:AS, "Empleado") ) - ( ( SUMIFS(AR:AR, AY:AY, INDIRECT("AE" & ROW()), AP:AP, "💲", AS:AS, "Familiar") + SUMIFS(AR:AR, AY:AY, INDIRECT("AE" & ROW()), AP:AP, "📦", AS:AS, "Familiar") ) / 2 ) - ( ( SUMIFS(AR:AR, AY:AY, INDIRECT("AE" & ROW()), AP:AP, "💲", AS:AS, "Exonerado ADH") + SUMIFS(AR:AR, AY:AY, INDIRECT("AE" & ROW()), AP:AP, "📦", AS:AS, "Exonerado ADH") ) / 2 ) - ( ( SUMIFS(AR:AR, AY:AY, INDIRECT("AE" & ROW()), AP:AP, "💲", AS:AS, "Exonerado Doctor") + SUMIFS(AR:AR, AY:AY, INDIRECT("AE" & ROW()), AP:AP, "📦", AS:AS, "Exonerado Doctor") ) / 2 ) -> 0 | AK8: =( SUMIFS(AR:AR, AY:AY, INDIRECT("AE" & ROW()), AP:AP, "💲") + SUMIFS(AR:AR, AY:AY, INDIRECT("AE" & ROW()), AP:AP, "📦") ) - ( SUMIFS(AR:AR, AY:AY, INDIRECT("AE" & ROW()), AP:AP, "💲", AS:AS, "Familiar") + SUMIFS(AR:AR, AY:AY, INDIRECT("AE" & ROW()), AP:AP, "📦", AS:AS, "Familiar") ) - ( SUMIFS(AR:AR, AY:AY, INDIRECT("AE" & ROW()), AP:AP, "💲", AS:AS, "Participante") + SUMIFS(AR:AR, AY:AY, INDIRECT("AE" & ROW()), AP:AP, "📦", AS:AS, "Participante") ) - ( SUMIFS(AR:AR, AY:AY, INDIRECT("AE" & ROW()), AP:AP, "💲", AS:AS, "Empleado") + SUMIFS(AR:AR, AY:AY, INDIRECT("AE" & ROW()), AP:AP, "📦", AS:AS, "Empleado") ) - ( SUMIFS(AR:AR, AY:AY, INDIRECT("AE" & ROW()), AP:AP, "💲", AS:AS, "Exonerado ADH") + SUMIFS(AR:AR, AY:AY, INDIRECT("AE" & ROW()), AP:AP, "📦", AS:AS, "Exonerado ADH") ) - (( SUMIFS(AR:AR, AY:AY, INDIRECT("AE" & ROW()), AP:AP, "💲", AS:AS, "Exonerado Doctor") + SUMIFS(AR:AR, AY:AY, INDIRECT("AE" & ROW()), AP:AP, "📦", AS:AS, "Exonerado Doctor") ) / 2 )- ( ( SUMIFS(AR:AR, AY:AY, INDIRECT("AE" & ROW()), AP:AP, "💲", AS:AS, "") + SUMIFS(AR:AR, AY:AY, INDIRECT("AE" & ROW()), AP:AP, "📦", AS:AS, "") ) / 2 ) -> 0 | AL8: =( SUMIFS(AR:AR, AY:AY, INDIRECT("AE" & ROW()), AP:AP, "💲") + SUMIFS(AR:AR, AY:AY, INDIRECT("AE" & ROW()), AP:AP, "📦") ) - (( SUMIFS(AR:AR, AY:AY, INDIRECT("AE" & ROW()), AP:AP, "💲", AS:AS, "Familiar") + SUMIFS(AR:AR, AY:AY, INDIRECT("AE" & ROW()), AP:AP, "📦", AS:AS, "Familiar") ) / 2 ) - (( SUMIFS(AR:AR, AY:AY, INDIRECT("AE" & ROW()), AP:AP, "💲", AS:AS, "Participante") + SUMIFS(AR:AR, AY:AY, INDIRECT("AE" & ROW()), AP:AP, "📦", AS:AS, "Participante") ) / 2 ) - (( SUMIFS(AR:AR, AY:AY, INDIRECT("AE" & ROW()), AP:AP, "💲", AS:AS, "Empleado") + SUMIFS(AR:AR, AY:AY, INDIRECT("AE" & ROW()), AP:AP, "📦", AS:AS, "Empleado") ) / 2 ) - (( SUMIFS(AR:AR, AY:AY, INDIRECT("AE" & ROW()), AP:AP, "💲", AS:AS, "Exonerado ADH") + SUMIFS(AR:AR, AY:AY, INDIRECT("AE" & ROW()), AP:AP, "📦", AS:AS, "Exonerado ADH") ) / 2 ) - ( SUMIFS(AR:AR, AY:AY, INDIRECT("AE" & ROW()), AP:AP, "💲", AS:AS, "Exonerado Doctor") + SUMIFS(AR:AR, AY:AY, INDIRECT("AE" & ROW()), AP:AP, "📦", AS:AS, "Exonerado Doctor") )- ( ( SUMIFS(AR:AR, AY:AY, INDIRECT("AE" & ROW()), AP:AP, "💲", AS:AS, "") + SUMIFS(AR:AR, AY:AY, INDIRECT("AE" & ROW()), AP:AP, "📦", AS:AS, "") ) / 2 ) -> 0 | AN8: =A4 -> 46266 | AO8: =C5 -> Consultorio N° 1 | AP8: =C14 -> 0 | AQ8: =D14 -> 0 | AR8: =U14 -> 0 | AS8: =S14 -> 0 | AT8: =S15 -> 0 | AU8: =U15 -> 0 | AV8: =S16 -> 0 | AW8: =U16 -> 0 | AX8: =U17 -> 0 | AY8: =F17 -> 0 | BA8: =IFERROR(__xludf.DUMMYFUNCTION("""COMPUTED_VALUE"""),"Gabriela Guerra") -> Gabriela Guerra | BB8: =IFERROR(__xludf.DUMMYFUNCTION("""COMPUTED_VALUE"""),46274) -> 46274 | BC8: =IFERROR(__xludf.DUMMYFUNCTION("""COMPUTED_VALUE"""),50) -> 50 | BD8: =IFERROR(__xludf.DUMMYFUNCTION("""COMPUTED_VALUE"""),"Dra. Ma.Auxliliadora Aguilera") -> Dra. Ma.Auxliliadora Aguilera | BF8: =IFERROR(__xludf.DUMMYFUNCTION("""COMPUTED_VALUE"""),"Jorgelina Alvarez") -> Jorgelina Alvarez | BH8: =IFERROR(__xludf.DUMMYFUNCTION("""COMPUTED_VALUE"""),46289) -> 46289 | BI8: =IFERROR(__xludf.DUMMYFUNCTION("""COMPUTED_VALUE"""),50) -> 50 | BJ8: =IFERROR(__xludf.DUMMYFUNCTION("""COMPUTED_VALUE"""),"Dr. Jorge Valeri") -> Dr. Jorge Valeri | BL8: =IFERROR(__xludf.DUMMYFUNCTION("""COMPUTED_VALUE"""),"Juan Andres Figueira") -> Juan Andres Figueira | BM8: =IFERROR(__xludf.DUMMYFUNCTION("""COMPUTED_VALUE"""),46280) -> 46280 | BN8: =IFERROR(__xludf.DUMMYFUNCTION("""COMPUTED_VALUE"""),50) -> 50
E9: Doctor: | I9: Doctor: | M9: Doctor: | S9: =IF(OR(S6="Empleado",S6="Familiar"),"Nombre del Empleado","N° Factura") -> N° Factura | W9: =IF(OR(W6="Empleado",W6="Familiar"),"Nombre del Empleado","N° Factura") -> N° Factura | AA9: =IF(OR(AA6="Empleado",AA6="Familiar"),"Nombre del Empleado","N° Factura") -> N° Factura | AE9: Dra. Ma.Auxliliadora Aguilera | AG9: =COUNTIFS(AP:AP, "💲", AY:AY, AE9) + COUNTIFS(AP:AP, "📦", AY:AY, AE9) + COUNTIFS(AP:AP, "✅", AY:AY, AE9) -> 2 | AH9: =COUNTIFS(AP:AP, "💲", AY:AY, AE9) + COUNTIFS(AP:AP, "📦", AY:AY, AE9) -> 2 | AI9: =SUMIFS(AR:AR, AY:AY, AE9, AP:AP, "💲") + SUMIFS(AR:AR, AY:AY, AE9, AP:AP, "📦") -> 100 | AJ9: =( SUMIFS(AR:AR, AY:AY, INDIRECT("AE" & ROW()), AP:AP, "💲") + SUMIFS(AR:AR, AY:AY, INDIRECT("AE" & ROW()), AP:AP, "📦") ) - ( SUMIFS(AR:AR, AY:AY, INDIRECT("AE" & ROW()), AP:AP, "💲", AS:AS, "Participante") + SUMIFS(AR:AR, AY:AY, INDIRECT("AE" & ROW()), AP:AP, "📦", AS:AS, "Participante") ) - ( SUMIFS(AR:AR, AY:AY, INDIRECT("AE" & ROW()), AP:AP, "💲", AS:AS, "Empleado") + SUMIFS(AR:AR, AY:AY, INDIRECT("AE" & ROW()), AP:AP, "📦", AS:AS, "Empleado") ) - ( ( SUMIFS(AR:AR, AY:AY, INDIRECT("AE" & ROW()), AP:AP, "💲", AS:AS, "Familiar") + SUMIFS(AR:AR, AY:AY, INDIRECT("AE" & ROW()), AP:AP, "📦", AS:AS, "Familiar") ) / 2 ) - ( ( SUMIFS(AR:AR, AY:AY, INDIRECT("AE" & ROW()), AP:AP, "💲", AS:AS, "Exonerado ADH") + SUMIFS(AR:AR, AY:AY, INDIRECT("AE" & ROW()), AP:AP, "📦", AS:AS, "Exonerado ADH") ) / 2 ) - ( ( SUMIFS(AR:AR, AY:AY, INDIRECT("AE" & ROW()), AP:AP, "💲", AS:AS, "Exonerado Doctor") + SUMIFS(AR:AR, AY:AY, INDIRECT("AE" & ROW()), AP:AP, "📦", AS:AS, "Exonerado Doctor") ) / 2 ) -> 25 | AK9: =( SUMIFS(AR:AR, AY:AY, INDIRECT("AE" & ROW()), AP:AP, "💲") + SUMIFS(AR:AR, AY:AY, INDIRECT("AE" & ROW()), AP:AP, "📦") ) - ( SUMIFS(AR:AR, AY:AY, INDIRECT("AE" & ROW()), AP:AP, "💲", AS:AS, "Familiar") + SUMIFS(AR:AR, AY:AY, INDIRECT("AE" & ROW()), AP:AP, "📦", AS:AS, "Familiar") ) - ( SUMIFS(AR:AR, AY:AY, INDIRECT("AE" & ROW()), AP:AP, "💲", AS:AS, "Participante") + SUMIFS(AR:AR, AY:AY, INDIRECT("AE" & ROW()), AP:AP, "📦", AS:AS, "Participante") ) - ( SUMIFS(AR:AR, AY:AY, INDIRECT("AE" & ROW()), AP:AP, "💲", AS:AS, "Empleado") + SUMIFS(AR:AR, AY:AY, INDIRECT("AE" & ROW()), AP:AP, "📦", AS:AS, "Empleado") ) - ( SUMIFS(AR:AR, AY:AY, INDIRECT("AE" & ROW()), AP:AP, "💲", AS:AS, "Exonerado ADH") + SUMIFS(AR:AR, AY:AY, INDIRECT("AE" & ROW()), AP:AP, "📦", AS:AS, "Exonerado ADH") ) - (( SUMIFS(AR:AR, AY:AY, INDIRECT("AE" & ROW()), AP:AP, "💲", AS:AS, "Exonerado Doctor") + SUMIFS(AR:AR, AY:AY, INDIRECT("AE" & ROW()), AP:AP, "📦", AS:AS, "Exonerado Doctor") ) / 2 )- ( ( SUMIFS(AR:AR, AY:AY, INDIRECT("AE" & ROW()), AP:AP, "💲", AS:AS, "") + SUMIFS(AR:AR, AY:AY, INDIRECT("AE" & ROW()), AP:AP, "📦", AS:AS, "") ) / 2 ) -> 0 | AL9: =( SUMIFS(AR:AR, AY:AY, INDIRECT("AE" & ROW()), AP:AP, "💲") + SUMIFS(AR:AR, AY:AY, INDIRECT("AE" & ROW()), AP:AP, "📦") ) - (( SUMIFS(AR:AR, AY:AY, INDIRECT("AE" & ROW()), AP:AP, "💲", AS:AS, "Familiar") + SUMIFS(AR:AR, AY:AY, INDIRECT("AE" & ROW()), AP:AP, "📦", AS:AS, "Familiar") ) / 2 ) - (( SUMIFS(AR:AR, AY:AY, INDIRECT("AE" & ROW()), AP:AP, "💲", AS:AS, "Participante") + SUMIFS(AR:AR, AY:AY, INDIRECT("AE" & ROW()), AP:AP, "📦", AS:AS, "Participante") ) / 2 ) - (( SUMIFS(AR:AR, AY:AY, INDIRECT("AE" & ROW()), AP:AP, "💲", AS:AS, "Empleado") + SUMIFS(AR:AR, AY:AY, INDIRECT("AE" & ROW()), AP:AP, "📦", AS:AS, "Empleado") ) / 2 ) - (( SUMIFS(AR:AR, AY:AY, INDIRECT("AE" & ROW()), AP:AP, "💲", AS:AS, "Exonerado ADH") + SUMIFS(AR:AR, AY:AY, INDIRECT("AE" & ROW()), AP:AP, "📦", AS:AS, "Exonerado ADH") ) / 2 ) - ( SUMIFS(AR:AR, AY:AY, INDIRECT("AE" & ROW()), AP:AP, "💲", AS:AS, "Exonerado Doctor") + SUMIFS(AR:AR, AY:AY, INDIRECT("AE" & ROW()), AP:AP, "📦", AS:AS, "Exonerado Doctor") )- ( ( SUMIFS(AR:AR, AY:AY, INDIRECT("AE" & ROW()), AP:AP, "💲", AS:AS, "") + SUMIFS(AR:AR, AY:AY, INDIRECT("AE" & ROW()), AP:AP, "📦", AS:AS, "") ) / 2 ) -> 50 | AN9: =A4 -> 46266 | AO9: =C5 -> Consultorio N° 1 | AP9: =C18 -> 0 | AQ9: =D18 -> 0 | AR9: =U18 -> 0 | AS9: =S18 -> 0 | AT9: =S19 -> 0 | AU9: =U19 -> 0 | AV9: =S20 -> 0 | AW9: =U20 -> 0 | AX9: =U21 -> 0 | AY9: =F21 -> 0 | BA9: =IFERROR(__xludf.DUMMYFUNCTION("""COMPUTED_VALUE"""),"Jorgelina Alvarez") -> Jorgelina Alvarez | BB9: =IFERROR(__xludf.DUMMYFUNCTION("""COMPUTED_VALUE"""),46274) -> 46274 | BC9: =IFERROR(__xludf.DUMMYFUNCTION("""COMPUTED_VALUE"""),50) -> 50 | BD9: =IFERROR(__xludf.DUMMYFUNCTION("""COMPUTED_VALUE"""),"Dra. Gabriela Berbis") -> Dra. Gabriela Berbis | BF9: =IFERROR(__xludf.DUMMYFUNCTION("""COMPUTED_VALUE"""),"Leonardo Aular") -> Leonardo Aular | BH9: =IFERROR(__xludf.DUMMYFUNCTION("""COMPUTED_VALUE"""),46293) -> 46293 | BI9: =IFERROR(__xludf.DUMMYFUNCTION("""COMPUTED_VALUE"""),50) -> 50 | BJ9: =IFERROR(__xludf.DUMMYFUNCTION("""COMPUTED_VALUE"""),"Luzmir Fagúndez") -> Luzmir Fagúndez | BL9: =IFERROR(__xludf.DUMMYFUNCTION("""COMPUTED_VALUE"""),"Juan Carlos Keklikian") -> Juan Carlos Keklikian | BM9: =IFERROR(__xludf.DUMMYFUNCTION("""COMPUTED_VALUE"""),46282) -> 46282 | BN9: =IFERROR(__xludf.DUMMYFUNCTION("""COMPUTED_VALUE"""),50) -> 50
A10: =A6+$Q$13/1440 -> 0.375 | E10: Representante: | F10: =IF(D10<>"", VLOOKUP(D10,'Base de Datos'!$A$2:$D1268,2,FALSE()),"") | I10: Representante: | J10: =IF(H10<>"", VLOOKUP(H10,'Base de Datos'!$A$2:$D1268,2,FALSE()),"") | M10: Representante: | N10: =IF(L10<>"", VLOOKUP(L10,'Base de Datos'!$A$2:$D1268,2,FALSE()),"") | O10: $ USD: | Q10: =$N$2 -> 888.8909 | T10: Precio: | X10: Precio: | AB10: Precio: | AE10: Dr. Jorge Valeri | AG10: =COUNTIFS(AP:AP, "💲", AY:AY, AE10) + COUNTIFS(AP:AP, "📦", AY:AY, AE10) + COUNTIFS(AP:AP, "✅", AY:AY, AE10) -> 11 | AH10: =COUNTIFS(AP:AP, "💲", AY:AY, AE10) + COUNTIFS(AP:AP, "📦", AY:AY, AE10) -> 11 | AI10: =SUMIFS(AR:AR, AY:AY, AE10, AP:AP, "💲") + SUMIFS(AR:AR, AY:AY, AE10, AP:AP, "📦") -> 550 | AJ10: =( SUMIFS(AR:AR, AY:AY, INDIRECT("AE" & ROW()), AP:AP, "💲") + SUMIFS(AR:AR, AY:AY, INDIRECT("AE" & ROW()), AP:AP, "📦") ) - ( SUMIFS(AR:AR, AY:AY, INDIRECT("AE" & ROW()), AP:AP, "💲", AS:AS, "Participante") + SUMIFS(AR:AR, AY:AY, INDIRECT("AE" & ROW()), AP:AP, "📦", AS:AS, "Participante") ) - ( SUMIFS(AR:AR, AY:AY, INDIRECT("AE" & ROW()), AP:AP, "💲", AS:AS, "Empleado") + SUMIFS(AR:AR, AY:AY, INDIRECT("AE" & ROW()), AP:AP, "📦", AS:AS, "Empleado") ) - ( ( SUMIFS(AR:AR, AY:AY, INDIRECT("AE" & ROW()), AP:AP, "💲", AS:AS, "Familiar") + SUMIFS(AR:AR, AY:AY, INDIRECT("AE" & ROW()), AP:AP, "📦", AS:AS, "Familiar") ) / 2 ) - ( ( SUMIFS(AR:AR, AY:AY, INDIRECT("AE" & ROW()), AP:AP, "💲", AS:AS, "Exonerado ADH") + SUMIFS(AR:AR, AY:AY, INDIRECT("AE" & ROW()), AP:AP, "📦", AS:AS, "Exonerado ADH") ) / 2 ) - ( ( SUMIFS(AR:AR, AY:AY, INDIRECT("AE" & ROW()), AP:AP, "💲", AS:AS, "Exonerado Doctor") + SUMIFS(AR:AR, AY:AY, INDIRECT("AE" & ROW()), AP:AP, "📦", AS:AS, "Exonerado Doctor") ) / 2 ) -> 425 | AK10: =( SUMIFS(AR:AR, AY:AY, INDIRECT("AE" & ROW()), AP:AP, "💲") + SUMIFS(AR:AR, AY:AY, INDIRECT("AE" & ROW()), AP:AP, "📦") ) - ( SUMIFS(AR:AR, AY:AY, INDIRECT("AE" & ROW()), AP:AP, "💲", AS:AS, "Familiar") + SUMIFS(AR:AR, AY:AY, INDIRECT("AE" & ROW()), AP:AP, "📦", AS:AS, "Familiar") ) - ( SUMIFS(AR:AR, AY:AY, INDIRECT("AE" & ROW()), AP:AP, "💲", AS:AS, "Participante") + SUMIFS(AR:AR, AY:AY, INDIRECT("AE" & ROW()), AP:AP, "📦", AS:AS, "Participante") ) - ( SUMIFS(AR:AR, AY:AY, INDIRECT("AE" & ROW()), AP:AP, "💲", AS:AS, "Empleado") + SUMIFS(AR:AR, AY:AY, INDIRECT("AE" & ROW()), AP:AP, "📦", AS:AS, "Empleado") ) - ( SUMIFS(AR:AR, AY:AY, INDIRECT("AE" & ROW()), AP:AP, "💲", AS:AS, "Exonerado ADH") + SUMIFS(AR:AR, AY:AY, INDIRECT("AE" & ROW()), AP:AP, "📦", AS:AS, "Exonerado ADH") ) - (( SUMIFS(AR:AR, AY:AY, INDIRECT("AE" & ROW()), AP:AP, "💲", AS:AS, "Exonerado Doctor") + SUMIFS(AR:AR, AY:AY, INDIRECT("AE" & ROW()), AP:AP, "📦", AS:AS, "Exonerado Doctor") ) / 2 )- ( ( SUMIFS(AR:AR, AY:AY, INDIRECT("AE" & ROW()), AP:AP, "💲", AS:AS, "") + SUMIFS(AR:AR, AY:AY, INDIRECT("AE" & ROW()), AP:AP, "📦", AS:AS, "") ) / 2 ) -> 400 | AL10: =( SUMIFS(AR:AR, AY:AY, INDIRECT("AE" & ROW()), AP:AP, "💲") + SUMIFS(AR:AR, AY:AY, INDIRECT("AE" & ROW()), AP:AP, "📦") ) - (( SUMIFS(AR:AR, AY:AY, INDIRECT("AE" & ROW()), AP:AP, "💲", AS:AS, "Familiar") + SUMIFS(AR:AR, AY:AY, INDIRECT("AE" & ROW()), AP:AP, "📦", AS:AS, "Familiar") ) / 2 ) - (( SUMIFS(AR:AR, AY:AY, INDIRECT("AE" & ROW()), AP:AP, "💲", AS:AS, "Participante") + SUMIFS(AR:AR, AY:AY, INDIRECT("AE" & ROW()), AP:AP, "📦", AS:AS, "Participante") ) / 2 ) - (( SUMIFS(AR:AR, AY:AY, INDIRECT("AE" & ROW()), AP:AP, "💲", AS:AS, "Empleado") + SUMIFS(AR:AR, AY:AY, INDIRECT("AE" & ROW()), AP:AP, "📦", AS:AS, "Empleado") ) / 2 ) - (( SUMIFS(AR:AR, AY:AY, INDIRECT("AE" & ROW()), AP:AP, "💲", AS:AS, "Exonerado ADH") + SUMIFS(AR:AR, AY:AY, INDIRECT("AE" & ROW()), AP:AP, "📦", AS:AS, "Exonerado ADH") ) / 2 ) - ( SUMIFS(AR:AR, AY:AY, INDIRECT("AE" & ROW()), AP:AP, "💲", AS:AS, "Exonerado Doctor") + SUMIFS(AR:AR, AY:AY, INDIRECT("AE" & ROW()), AP:AP, "📦", AS:AS, "Exonerado Doctor") )- ( ( SUMIFS(AR:AR, AY:AY, INDIRECT("AE" & ROW()), AP:AP, "💲", AS:AS, "") + SUMIFS(AR:AR, AY:AY, INDIRECT("AE" & ROW()), AP:AP, "📦", AS:AS, "") ) / 2 ) -> 475 | AN10: =A4 -> 46266 | AO10: =C5 -> Consultorio N° 1 | AP10: =C22 -> 0 | AQ10: =D22 -> 0 | AR10: =U22 -> 0 | AS10: =S22 -> 0 | AT10: =S23 -> 0 | AU10: =U23 -> 0 | AV10: =S24 -> 0 | AW10: =U24 -> 0 | AX10: =U25 -> 0 | AY10: =F25 -> 0 | BA10: =IFERROR(__xludf.DUMMYFUNCTION("""COMPUTED_VALUE"""),"Dariela Cáceres") -> Dariela Cáceres | BB10: =IFERROR(__xludf.DUMMYFUNCTION("""COMPUTED_VALUE"""),46276) -> 46276 | BC10: =IFERROR(__xludf.DUMMYFUNCTION("""COMPUTED_VALUE"""),50) -> 50 | BD10: =IFERROR(__xludf.DUMMYFUNCTION("""COMPUTED_VALUE"""),"Odo. Geraldine Cabrera") -> Odo. Geraldine Cabrera | BL10: =IFERROR(__xludf.DUMMYFUNCTION("""COMPUTED_VALUE"""),"Ignacio Escorcia") -> Ignacio Escorcia | BM10: =IFERROR(__xludf.DUMMYFUNCTION("""COMPUTED_VALUE"""),46282) -> 46282 | BN10: =IFERROR(__xludf.DUMMYFUNCTION("""COMPUTED_VALUE"""),50) -> 50
E11: Teléfono: | F11: =IF(D10<>"", VLOOKUP(D10,'Base de Datos'!$A$2:$D1268,3,FALSE()),"") | I11: Teléfono: | J11: =IF(H10<>"", VLOOKUP(H10,'Base de Datos'!$A$2:$D1268,3,FALSE()),"") | M11: Teléfono: | N11: =IF(L10<>"", VLOOKUP(L10,'Base de Datos'!$A$2:$D1268,3,FALSE()),"") | AE11: Dr. José Francisco Cordero | AG11: =COUNTIFS(AP:AP, "💲", AY:AY, AE11) + COUNTIFS(AP:AP, "📦", AY:AY, AE11) + COUNTIFS(AP:AP, "✅", AY:AY, AE11) -> 0 | AH11: =COUNTIFS(AP:AP, "💲", AY:AY, AE11) + COUNTIFS(AP:AP, "📦", AY:AY, AE11) -> 0 | AI11: =SUMIFS(AR:AR, AY:AY, AE11, AP:AP, "💲") + SUMIFS(AR:AR, AY:AY, AE11, AP:AP, "📦") -> 0 | AJ11: =( SUMIFS(AR:AR, AY:AY, INDIRECT("AE" & ROW()), AP:AP, "💲") + SUMIFS(AR:AR, AY:AY, INDIRECT("AE" & ROW()), AP:AP, "📦") ) - ( SUMIFS(AR:AR, AY:AY, INDIRECT("AE" & ROW()), AP:AP, "💲", AS:AS, "Participante") + SUMIFS(AR:AR, AY:AY, INDIRECT("AE" & ROW()), AP:AP, "📦", AS:AS, "Participante") ) - ( SUMIFS(AR:AR, AY:AY, INDIRECT("AE" & ROW()), AP:AP, "💲", AS:AS, "Empleado") + SUMIFS(AR:AR, AY:AY, INDIRECT("AE" & ROW()), AP:AP, "📦", AS:AS, "Empleado") ) - ( ( SUMIFS(AR:AR, AY:AY, INDIRECT("AE" & ROW()), AP:AP, "💲", AS:AS, "Familiar") + SUMIFS(AR:AR, AY:AY, INDIRECT("AE" & ROW()), AP:AP, "📦", AS:AS, "Familiar") ) / 2 ) - ( ( SUMIFS(AR:AR, AY:AY, INDIRECT("AE" & ROW()), AP:AP, "💲", AS:AS, "Exonerado ADH") + SUMIFS(AR:AR, AY:AY, INDIRECT("AE" & ROW()), AP:AP, "📦", AS:AS, "Exonerado ADH") ) / 2 ) - ( ( SUMIFS(AR:AR, AY:AY, INDIRECT("AE" & ROW()), AP:AP, "💲", AS:AS, "Exonerado Doctor") + SUMIFS(AR:AR, AY:AY, INDIRECT("AE" & ROW()), AP:AP, "📦", AS:AS, "Exonerado Doctor") ) / 2 ) -> 0 | AK11: =( SUMIFS(AR:AR, AY:AY, INDIRECT("AE" & ROW()), AP:AP, "💲") + SUMIFS(AR:AR, AY:AY, INDIRECT("AE" & ROW()), AP:AP, "📦") ) - ( SUMIFS(AR:AR, AY:AY, INDIRECT("AE" & ROW()), AP:AP, "💲", AS:AS, "Familiar") + SUMIFS(AR:AR, AY:AY, INDIRECT("AE" & ROW()), AP:AP, "📦", AS:AS, "Familiar") ) - ( SUMIFS(AR:AR, AY:AY, INDIRECT("AE" & ROW()), AP:AP, "💲", AS:AS, "Participante") + SUMIFS(AR:AR, AY:AY, INDIRECT("AE" & ROW()), AP:AP, "📦", AS:AS, "Participante") ) - ( SUMIFS(AR:AR, AY:AY, INDIRECT("AE" & ROW()), AP:AP, "💲", AS:AS, "Empleado") + SUMIFS(AR:AR, AY:AY, INDIRECT("AE" & ROW()), AP:AP, "📦", AS:AS, "Empleado") ) - ( SUMIFS(AR:AR, AY:AY, INDIRECT("AE" & ROW()), AP:AP, "💲", AS:AS, "Exonerado ADH") + SUMIFS(AR:AR, AY:AY, INDIRECT("AE" & ROW()), AP:AP, "📦", AS:AS, "Exonerado ADH") ) - (( SUMIFS(AR:AR, AY:AY, INDIRECT("AE" & ROW()), AP:AP, "💲", AS:AS, "Exonerado Doctor") + SUMIFS(AR:AR, AY:AY, INDIRECT("AE" & ROW()), AP:AP, "📦", AS:AS, "Exonerado Doctor") ) / 2 )- ( ( SUMIFS(AR:AR, AY:AY, INDIRECT("AE" & ROW()), AP:AP, "💲", AS:AS, "") + SUMIFS(AR:AR, AY:AY, INDIRECT("AE" & ROW()), AP:AP, "📦", AS:AS, "") ) / 2 ) -> 0 | AL11: =( SUMIFS(AR:AR, AY:AY, INDIRECT("AE" & ROW()), AP:AP, "💲") + SUMIFS(AR:AR, AY:AY, INDIRECT("AE" & ROW()), AP:AP, "📦") ) - (( SUMIFS(AR:AR, AY:AY, INDIRECT("AE" & ROW()), AP:AP, "💲", AS:AS, "Familiar") + SUMIFS(AR:AR, AY:AY, INDIRECT("AE" & ROW()), AP:AP, "📦", AS:AS, "Familiar") ) / 2 ) - (( SUMIFS(AR:AR, AY:AY, INDIRECT("AE" & ROW()), AP:AP, "💲", AS:AS, "Participante") + SUMIFS(AR:AR, AY:AY, INDIRECT("AE" & ROW()), AP:AP, "📦", AS:AS, "Participante") ) / 2 ) - (( SUMIFS(AR:AR, AY:AY, INDIRECT("AE" & ROW()), AP:AP, "💲", AS:AS, "Empleado") + SUMIFS(AR:AR, AY:AY, INDIRECT("AE" & ROW()), AP:AP, "📦", AS:AS, "Empleado") ) / 2 ) - (( SUMIFS(AR:AR, AY:AY, INDIRECT("AE" & ROW()), AP:AP, "💲", AS:AS, "Exonerado ADH") + SUMIFS(AR:AR, AY:AY, INDIRECT("AE" & ROW()), AP:AP, "📦", AS:AS, "Exonerado ADH") ) / 2 ) - ( SUMIFS(AR:AR, AY:AY, INDIRECT("AE" & ROW()), AP:AP, "💲", AS:AS, "Exonerado Doctor") + SUMIFS(AR:AR, AY:AY, INDIRECT("AE" & ROW()), AP:AP, "📦", AS:AS, "Exonerado Doctor") )- ( ( SUMIFS(AR:AR, AY:AY, INDIRECT("AE" & ROW()), AP:AP, "💲", AS:AS, "") + SUMIFS(AR:AR, AY:AY, INDIRECT("AE" & ROW()), AP:AP, "📦", AS:AS, "") ) / 2 ) -> 0 | AN11: =A4 -> 46266 | AO11: =C5 -> Consultorio N° 1 | AP11: =C26 -> 0 | AQ11: =D26 -> 0 | AR11: =U26 -> 0 | AS11: =S26 -> 0 | AT11: =S27 -> 0 | AU11: =U27 -> 0 | AV11: =S28 -> 0 | AW11: =U28 -> 0 | AX11: =U29 -> 0 | AY11: =F29 -> 0 | BA11: =IFERROR(__xludf.DUMMYFUNCTION("""COMPUTED_VALUE"""),"Marly Bracamontes") -> Marly Bracamontes | BB11: =IFERROR(__xludf.DUMMYFUNCTION("""COMPUTED_VALUE"""),46276) -> 46276 | BC11: =IFERROR(__xludf.DUMMYFUNCTION("""COMPUTED_VALUE"""),50) -> 50 | BD11: =IFERROR(__xludf.DUMMYFUNCTION("""COMPUTED_VALUE"""),"Odo. Geraldine Cabrera") -> Odo. Geraldine Cabrera | BL11: =IFERROR(__xludf.DUMMYFUNCTION("""COMPUTED_VALUE"""),"Luis Daniel La Cruz") -> Luis Daniel La Cruz | BM11: =IFERROR(__xludf.DUMMYFUNCTION("""COMPUTED_VALUE"""),46289) -> 46289 | BN11: =IFERROR(__xludf.DUMMYFUNCTION("""COMPUTED_VALUE"""),50) -> 50
E12: Cedula: | F12: =IF(D10<>"", VLOOKUP(D10,'Base de Datos'!$A$2:$D1268,4,FALSE()),"") | I12: Cedula: | J12: =IF(H10<>"", VLOOKUP(H10,'Base de Datos'!$A$2:$D1268,4,FALSE()),"") | M12: Cedula: | N12: =IF(L10<>"", VLOOKUP(L10,'Base de Datos'!$A$2:$D1268,4,FALSE()),"") | P12: Hora de inicio | Q12: 0.33333333 | AE12: Dra. Mónica Porras | AG12: =COUNTIFS(AP:AP, "💲", AY:AY, AE12) + COUNTIFS(AP:AP, "📦", AY:AY, AE12) + COUNTIFS(AP:AP, "✅", AY:AY, AE12) -> 3 | AH12: =COUNTIFS(AP:AP, "💲", AY:AY, AE12) + COUNTIFS(AP:AP, "📦", AY:AY, AE12) -> 3 | AI12: =SUMIFS(AR:AR, AY:AY, AE12, AP:AP, "💲") + SUMIFS(AR:AR, AY:AY, AE12, AP:AP, "📦") -> 150 | AJ12: =( SUMIFS(AR:AR, AY:AY, INDIRECT("AE" & ROW()), AP:AP, "💲") + SUMIFS(AR:AR, AY:AY, INDIRECT("AE" & ROW()), AP:AP, "📦") ) - ( SUMIFS(AR:AR, AY:AY, INDIRECT("AE" & ROW()), AP:AP, "💲", AS:AS, "Participante") + SUMIFS(AR:AR, AY:AY, INDIRECT("AE" & ROW()), AP:AP, "📦", AS:AS, "Participante") ) - ( SUMIFS(AR:AR, AY:AY, INDIRECT("AE" & ROW()), AP:AP, "💲", AS:AS, "Empleado") + SUMIFS(AR:AR, AY:AY, INDIRECT("AE" & ROW()), AP:AP, "📦", AS:AS, "Empleado") ) - ( ( SUMIFS(AR:AR, AY:AY, INDIRECT("AE" & ROW()), AP:AP, "💲", AS:AS, "Familiar") + SUMIFS(AR:AR, AY:AY, INDIRECT("AE" & ROW()), AP:AP, "📦", AS:AS, "Familiar") ) / 2 ) - ( ( SUMIFS(AR:AR, AY:AY, INDIRECT("AE" & ROW()), AP:AP, "💲", AS:AS, "Exonerado ADH") + SUMIFS(AR:AR, AY:AY, INDIRECT("AE" & ROW()), AP:AP, "📦", AS:AS, "Exonerado ADH") ) / 2 ) - ( ( SUMIFS(AR:AR, AY:AY, INDIRECT("AE" & ROW()), AP:AP, "💲", AS:AS, "Exonerado Doctor") + SUMIFS(AR:AR, AY:AY, INDIRECT("AE" & ROW()), AP:AP, "📦", AS:AS, "Exonerado Doctor") ) / 2 ) -> 75 | AK12: =( SUMIFS(AR:AR, AY:AY, INDIRECT("AE" & ROW()), AP:AP, "💲") + SUMIFS(AR:AR, AY:AY, INDIRECT("AE" & ROW()), AP:AP, "📦") ) - ( SUMIFS(AR:AR, AY:AY, INDIRECT("AE" & ROW()), AP:AP, "💲", AS:AS, "Familiar") + SUMIFS(AR:AR, AY:AY, INDIRECT("AE" & ROW()), AP:AP, "📦", AS:AS, "Familiar") ) - ( SUMIFS(AR:AR, AY:AY, INDIRECT("AE" & ROW()), AP:AP, "💲", AS:AS, "Participante") + SUMIFS(AR:AR, AY:AY, INDIRECT("AE" & ROW()), AP:AP, "📦", AS:AS, "Participante") ) - ( SUMIFS(AR:AR, AY:AY, INDIRECT("AE" & ROW()), AP:AP, "💲", AS:AS, "Empleado") + SUMIFS(AR:AR, AY:AY, INDIRECT("AE" & ROW()), AP:AP, "📦", AS:AS, "Empleado") ) - ( SUMIFS(AR:AR, AY:AY, INDIRECT("AE" & ROW()), AP:AP, "💲", AS:AS, "Exonerado ADH") + SUMIFS(AR:AR, AY:AY, INDIRECT("AE" & ROW()), AP:AP, "📦", AS:AS, "Exonerado ADH") ) - (( SUMIFS(AR:AR, AY:AY, INDIRECT("AE" & ROW()), AP:AP, "💲", AS:AS, "Exonerado Doctor") + SUMIFS(AR:AR, AY:AY, INDIRECT("AE" & ROW()), AP:AP, "📦", AS:AS, "Exonerado Doctor") ) / 2 )- ( ( SUMIFS(AR:AR, AY:AY, INDIRECT("AE" & ROW()), AP:AP, "💲", AS:AS, "") + SUMIFS(AR:AR, AY:AY, INDIRECT("AE" & ROW()), AP:AP, "📦", AS:AS, "") ) / 2 ) -> 50 | AL12: =( SUMIFS(AR:AR, AY:AY, INDIRECT("AE" & ROW()), AP:AP, "💲") + SUMIFS(AR:AR, AY:AY, INDIRECT("AE" & ROW()), AP:AP, "📦") ) - (( SUMIFS(AR:AR, AY:AY, INDIRECT("AE" & ROW()), AP:AP, "💲", AS:AS, "Familiar") + SUMIFS(AR:AR, AY:AY, INDIRECT("AE" & ROW()), AP:AP, "📦", AS:AS, "Familiar") ) / 2 ) - (( SUMIFS(AR:AR, AY:AY, INDIRECT("AE" & ROW()), AP:AP, "💲", AS:AS, "Participante") + SUMIFS(AR:AR, AY:AY, INDIRECT("AE" & ROW()), AP:AP, "📦", AS:AS, "Participante") ) / 2 ) - (( SUMIFS(AR:AR, AY:AY, INDIRECT("AE" & ROW()), AP:AP, "💲", AS:AS, "Empleado") + SUMIFS(AR:AR, AY:AY, INDIRECT("AE" & ROW()), AP:AP, "📦", AS:AS, "Empleado") ) / 2 ) - (( SUMIFS(AR:AR, AY:AY, INDIRECT("AE" & ROW()), AP:AP, "💲", AS:AS, "Exonerado ADH") + SUMIFS(AR:AR, AY:AY, INDIRECT("AE" & ROW()), AP:AP, "📦", AS:AS, "Exonerado ADH") ) / 2 ) - ( SUMIFS(AR:AR, AY:AY, INDIRECT("AE" & ROW()), AP:AP, "💲", AS:AS, "Exonerado Doctor") + SUMIFS(AR:AR, AY:AY, INDIRECT("AE" & ROW()), AP:AP, "📦", AS:AS, "Exonerado Doctor") )- ( ( SUMIFS(AR:AR, AY:AY, INDIRECT("AE" & ROW()), AP:AP, "💲", AS:AS, "") + SUMIFS(AR:AR, AY:AY, INDIRECT("AE" & ROW()), AP:AP, "📦", AS:AS, "") ) / 2 ) -> 100 | AN12: =A4 -> 46266 | AO12: =C5 -> Consultorio N° 1 | AP12: =C30 -> 0 | AQ12: =D30 -> 0 | AR12: =U30 -> 0 | AS12: =S30 -> 0 | AT12: =S31 -> 0 | AU12: =U31 -> 0 | AV12: =S32 -> 0 | AW12: =U32 -> 0 | AX12: =U33 -> 0 | AY12: =F33 -> 0 | BA12: =IFERROR(__xludf.DUMMYFUNCTION("""COMPUTED_VALUE"""),"Johanna Lopez") -> Johanna Lopez | BB12: =IFERROR(__xludf.DUMMYFUNCTION("""COMPUTED_VALUE"""),46289) -> 46289 | BC12: =IFERROR(__xludf.DUMMYFUNCTION("""COMPUTED_VALUE"""),50) -> 50 | BD12: =IFERROR(__xludf.DUMMYFUNCTION("""COMPUTED_VALUE"""),"Dra. Conchita Sánchez") -> Dra. Conchita Sánchez
E13: Doctor: | I13: Doctor: | M13: Doctor: | P13: Intervalo | Q13: 60 | S13: =IF(OR(S10="Empleado",S10="Familiar"),"Nombre del Empleado","N° Factura") -> N° Factura | W13: =IF(OR(W10="Empleado",W10="Familiar"),"Nombre del Empleado","N° Factura") -> N° Factura | AA13: =IF(OR(AA10="Empleado",AA10="Familiar"),"Nombre del Empleado","N° Factura") -> N° Factura | AE13: Dra. Conchita Sánchez | AG13: =COUNTIFS(AP:AP, "💲", AY:AY, AE13) + COUNTIFS(AP:AP, "📦", AY:AY, AE13) + COUNTIFS(AP:AP, "✅", AY:AY, AE13) -> 3 | AH13: =COUNTIFS(AP:AP, "💲", AY:AY, AE13) + COUNTIFS(AP:AP, "📦", AY:AY, AE13) -> 3 | AI13: =SUMIFS(AR:AR, AY:AY, AE13, AP:AP, "💲") + SUMIFS(AR:AR, AY:AY, AE13, AP:AP, "📦") -> 150 | AJ13: =( SUMIFS(AR:AR, AY:AY, INDIRECT("AE" & ROW()), AP:AP, "💲") + SUMIFS(AR:AR, AY:AY, INDIRECT("AE" & ROW()), AP:AP, "📦") ) - ( SUMIFS(AR:AR, AY:AY, INDIRECT("AE" & ROW()), AP:AP, "💲", AS:AS, "Participante") + SUMIFS(AR:AR, AY:AY, INDIRECT("AE" & ROW()), AP:AP, "📦", AS:AS, "Participante") ) - ( SUMIFS(AR:AR, AY:AY, INDIRECT("AE" & ROW()), AP:AP, "💲", AS:AS, "Empleado") + SUMIFS(AR:AR, AY:AY, INDIRECT("AE" & ROW()), AP:AP, "📦", AS:AS, "Empleado") ) - ( ( SUMIFS(AR:AR, AY:AY, INDIRECT("AE" & ROW()), AP:AP, "💲", AS:AS, "Familiar") + SUMIFS(AR:AR, AY:AY, INDIRECT("AE" & ROW()), AP:AP, "📦", AS:AS, "Familiar") ) / 2 ) - ( ( SUMIFS(AR:AR, AY:AY, INDIRECT("AE" & ROW()), AP:AP, "💲", AS:AS, "Exonerado ADH") + SUMIFS(AR:AR, AY:AY, INDIRECT("AE" & ROW()), AP:AP, "📦", AS:AS, "Exonerado ADH") ) / 2 ) - ( ( SUMIFS(AR:AR, AY:AY, INDIRECT("AE" & ROW()), AP:AP, "💲", AS:AS, "Exonerado Doctor") + SUMIFS(AR:AR, AY:AY, INDIRECT("AE" & ROW()), AP:AP, "📦", AS:AS, "Exonerado Doctor") ) / 2 ) -> 50 | AK13: =( SUMIFS(AR:AR, AY:AY, INDIRECT("AE" & ROW()), AP:AP, "💲") + SUMIFS(AR:AR, AY:AY, INDIRECT("AE" & ROW()), AP:AP, "📦") ) - ( SUMIFS(AR:AR, AY:AY, INDIRECT("AE" & ROW()), AP:AP, "💲", AS:AS, "Familiar") + SUMIFS(AR:AR, AY:AY, INDIRECT("AE" & ROW()), AP:AP, "📦", AS:AS, "Familiar") ) - ( SUMIFS(AR:AR, AY:AY, INDIRECT("AE" & ROW()), AP:AP, "💲", AS:AS, "Participante") + SUMIFS(AR:AR, AY:AY, INDIRECT("AE" & ROW()), AP:AP, "📦", AS:AS, "Participante") ) - ( SUMIFS(AR:AR, AY:AY, INDIRECT("AE" & ROW()), AP:AP, "💲", AS:AS, "Empleado") + SUMIFS(AR:AR, AY:AY, INDIRECT("AE" & ROW()), AP:AP, "📦", AS:AS, "Empleado") ) - ( SUMIFS(AR:AR, AY:AY, INDIRECT("AE" & ROW()), AP:AP, "💲", AS:AS, "Exonerado ADH") + SUMIFS(AR:AR, AY:AY, INDIRECT("AE" & ROW()), AP:AP, "📦", AS:AS, "Exonerado ADH") ) - (( SUMIFS(AR:AR, AY:AY, INDIRECT("AE" & ROW()), AP:AP, "💲", AS:AS, "Exonerado Doctor") + SUMIFS(AR:AR, AY:AY, INDIRECT("AE" & ROW()), AP:AP, "📦", AS:AS, "Exonerado Doctor") ) / 2 )- ( ( SUMIFS(AR:AR, AY:AY, INDIRECT("AE" & ROW()), AP:AP, "💲", AS:AS, "") + SUMIFS(AR:AR, AY:AY, INDIRECT("AE" & ROW()), AP:AP, "📦", AS:AS, "") ) / 2 ) -> 50 | AL13: =( SUMIFS(AR:AR, AY:AY, INDIRECT("AE" & ROW()), AP:AP, "💲") + SUMIFS(AR:AR, AY:AY, INDIRECT("AE" & ROW()), AP:AP, "📦") ) - (( SUMIFS(AR:AR, AY:AY, INDIRECT("AE" & ROW()), AP:AP, "💲", AS:AS, "Familiar") + SUMIFS(AR:AR, AY:AY, INDIRECT("AE" & ROW()), AP:AP, "📦", AS:AS, "Familiar") ) / 2 ) - (( SUMIFS(AR:AR, AY:AY, INDIRECT("AE" & ROW()), AP:AP, "💲", AS:AS, "Participante") + SUMIFS(AR:AR, AY:AY, INDIRECT("AE" & ROW()), AP:AP, "📦", AS:AS, "Participante") ) / 2 ) - (( SUMIFS(AR:AR, AY:AY, INDIRECT("AE" & ROW()), AP:AP, "💲", AS:AS, "Empleado") + SUMIFS(AR:AR, AY:AY, INDIRECT("AE" & ROW()), AP:AP, "📦", AS:AS, "Empleado") ) / 2 ) - (( SUMIFS(AR:AR, AY:AY, INDIRECT("AE" & ROW()), AP:AP, "💲", AS:AS, "Exonerado ADH") + SUMIFS(AR:AR, AY:AY, INDIRECT("AE" & ROW()), AP:AP, "📦", AS:AS, "Exonerado ADH") ) / 2 ) - ( SUMIFS(AR:AR, AY:AY, INDIRECT("AE" & ROW()), AP:AP, "💲", AS:AS, "Exonerado Doctor") + SUMIFS(AR:AR, AY:AY, INDIRECT("AE" & ROW()), AP:AP, "📦", AS:AS, "Exonerado Doctor") )- ( ( SUMIFS(AR:AR, AY:AY, INDIRECT("AE" & ROW()), AP:AP, "💲", AS:AS, "") + SUMIFS(AR:AR, AY:AY, INDIRECT("AE" & ROW()), AP:AP, "📦", AS:AS, "") ) / 2 ) -> 100 | AN13: =A4 -> 46266 | AO13: =C5 -> Consultorio N° 1 | AP13: =C34 -> 0 | AQ13: =D34 -> 0 | AR13: =U34 -> 0 | AS13: =S34 -> 0 | AT13: =S35 -> 0 | AU13: =U35 -> 0 | AV13: =S36 -> 0 | AW13: =U36 -> 0 | AX13: =U37 -> 0 | AY13: =F37 -> 0 | BA13: =IFERROR(__xludf.DUMMYFUNCTION("""COMPUTED_VALUE"""),"Maria Carmela Hernandez") -> Maria Carmela Hernandez | BB13: =IFERROR(__xludf.DUMMYFUNCTION("""COMPUTED_VALUE"""),46290) -> 46290 | BC13: =IFERROR(__xludf.DUMMYFUNCTION("""COMPUTED_VALUE"""),50) -> 50 | BD13: =IFERROR(__xludf.DUMMYFUNCTION("""COMPUTED_VALUE"""),"Odo. Geraldine Cabrera") -> Odo. Geraldine Cabrera
A14: =A10+$Q$13/1440 -> 0.41666667 | E14: Representante: | F14: =IF(D14<>"", VLOOKUP(D14,'Base de Datos'!$A$2:$D1268,2,FALSE()),"") | G14: 🚫 | H14: Yolimar Sofia Sayago Mosqueda | I14: Representante: | J14: =IF(H14<>"", VLOOKUP(H14,'Base de Datos'!$A$2:$D1268,2,FALSE()),"") -> Yolimar Sofia Sayago Mosqueda | M14: Representante: | N14: =IF(L14<>"", VLOOKUP(L14,'Base de Datos'!$A$2:$D1268,2,FALSE()),"") | T14: Precio: | X14: Precio: | AB14: Precio: | AE14: Dr. Carlos Eduardo Márquez | AG14: =COUNTIFS(AP:AP, "💲", AY:AY, AE14) + COUNTIFS(AP:AP, "📦", AY:AY, AE14) + COUNTIFS(AP:AP, "✅", AY:AY, AE14) -> 0 | AH14: =COUNTIFS(AP:AP, "💲", AY:AY, AE14) + COUNTIFS(AP:AP, "📦", AY:AY, AE14) -> 0 | AI14: =SUMIFS(AR:AR, AY:AY, AE14, AP:AP, "💲") + SUMIFS(AR:AR, AY:AY, AE14, AP:AP, "📦") -> 0 | AJ14: =( SUMIFS(AR:AR, AY:AY, INDIRECT("AE" & ROW()), AP:AP, "💲") + SUMIFS(AR:AR, AY:AY, INDIRECT("AE" & ROW()), AP:AP, "📦") ) - ( SUMIFS(AR:AR, AY:AY, INDIRECT("AE" & ROW()), AP:AP, "💲", AS:AS, "Participante") + SUMIFS(AR:AR, AY:AY, INDIRECT("AE" & ROW()), AP:AP, "📦", AS:AS, "Participante") ) - ( SUMIFS(AR:AR, AY:AY, INDIRECT("AE" & ROW()), AP:AP, "💲", AS:AS, "Empleado") + SUMIFS(AR:AR, AY:AY, INDIRECT("AE" & ROW()), AP:AP, "📦", AS:AS, "Empleado") ) - ( ( SUMIFS(AR:AR, AY:AY, INDIRECT("AE" & ROW()), AP:AP, "💲", AS:AS, "Familiar") + SUMIFS(AR:AR, AY:AY, INDIRECT("AE" & ROW()), AP:AP, "📦", AS:AS, "Familiar") ) / 2 ) - ( ( SUMIFS(AR:AR, AY:AY, INDIRECT("AE" & ROW()), AP:AP, "💲", AS:AS, "Exonerado ADH") + SUMIFS(AR:AR, AY:AY, INDIRECT("AE" & ROW()), AP:AP, "📦", AS:AS, "Exonerado ADH") ) / 2 ) - ( ( SUMIFS(AR:AR, AY:AY, INDIRECT("AE" & ROW()), AP:AP, "💲", AS:AS, "Exonerado Doctor") + SUMIFS(AR:AR, AY:AY, INDIRECT("AE" & ROW()), AP:AP, "📦", AS:AS, "Exonerado Doctor") ) / 2 ) -> 0 | AK14: =( SUMIFS(AR:AR, AY:AY, INDIRECT("AE" & ROW()), AP:AP, "💲") + SUMIFS(AR:AR, AY:AY, INDIRECT("AE" & ROW()), AP:AP, "📦") ) - ( SUMIFS(AR:AR, AY:AY, INDIRECT("AE" & ROW()), AP:AP, "💲", AS:AS, "Familiar") + SUMIFS(AR:AR, AY:AY, INDIRECT("AE" & ROW()), AP:AP, "📦", AS:AS, "Familiar") ) - ( SUMIFS(AR:AR, AY:AY, INDIRECT("AE" & ROW()), AP:AP, "💲", AS:AS, "Participante") + SUMIFS(AR:AR, AY:AY, INDIRECT("AE" & ROW()), AP:AP, "📦", AS:AS, "Participante") ) - ( SUMIFS(AR:AR, AY:AY, INDIRECT("AE" & ROW()), AP:AP, "💲", AS:AS, "Empleado") + SUMIFS(AR:AR, AY:AY, INDIRECT("AE" & ROW()), AP:AP, "📦", AS:AS, "Empleado") ) - ( SUMIFS(AR:AR, AY:AY, INDIRECT("AE" & ROW()), AP:AP, "💲", AS:AS, "Exonerado ADH") + SUMIFS(AR:AR, AY:AY, INDIRECT("AE" & ROW()), AP:AP, "📦", AS:AS, "Exonerado ADH") ) - (( SUMIFS(AR:AR, AY:AY, INDIRECT("AE" & ROW()), AP:AP, "💲", AS:AS, "Exonerado Doctor") + SUMIFS(AR:AR, AY:AY, INDIRECT("AE" & ROW()), AP:AP, "📦", AS:AS, "Exonerado Doctor") ) / 2 )- ( ( SUMIFS(AR:AR, AY:AY, INDIRECT("AE" & ROW()), AP:AP, "💲", AS:AS, "") + SUMIFS(AR:AR, AY:AY, INDIRECT("AE" & ROW()), AP:AP, "📦", AS:AS, "") ) / 2 ) -> 0 | AL14: =( SUMIFS(AR:AR, AY:AY, INDIRECT("AE" & ROW()), AP:AP, "💲") + SUMIFS(AR:AR, AY:AY, INDIRECT("AE" & ROW()), AP:AP, "📦") ) - (( SUMIFS(AR:AR, AY:AY, INDIRECT("AE" & ROW()), AP:AP, "💲", AS:AS, "Familiar") + SUMIFS(AR:AR, AY:AY, INDIRECT("AE" & ROW()), AP:AP, "📦", AS:AS, "Familiar") ) / 2 ) - (( SUMIFS(AR:AR, AY:AY, INDIRECT("AE" & ROW()), AP:AP, "💲", AS:AS, "Participante") + SUMIFS(AR:AR, AY:AY, INDIRECT("AE" & ROW()), AP:AP, "📦", AS:AS, "Participante") ) / 2 ) - (( SUMIFS(AR:AR, AY:AY, INDIRECT("AE" & ROW()), AP:AP, "💲", AS:AS, "Empleado") + SUMIFS(AR:AR, AY:AY, INDIRECT("AE" & ROW()), AP:AP, "📦", AS:AS, "Empleado") ) / 2 ) - (( SUMIFS(AR:AR, AY:AY, INDIRECT("AE" & ROW()), AP:AP, "💲", AS:AS, "Exonerado ADH") + SUMIFS(AR:AR, AY:AY, INDIRECT("AE" & ROW()), AP:AP, "📦", AS:AS, "Exonerado ADH") ) / 2 ) - ( SUMIFS(AR:AR, AY:AY, INDIRECT("AE" & ROW()), AP:AP, "💲", AS:AS, "Exonerado Doctor") + SUMIFS(AR:AR, AY:AY, INDIRECT("AE" & ROW()), AP:AP, "📦", AS:AS, "Exonerado Doctor") )- ( ( SUMIFS(AR:AR, AY:AY, INDIRECT("AE" & ROW()), AP:AP, "💲", AS:AS, "") + SUMIFS(AR:AR, AY:AY, INDIRECT("AE" & ROW()), AP:AP, "📦", AS:AS, "") ) / 2 ) -> 0 | AN14: =A4 -> 46266 | AO14: =C5 -> Consultorio N° 1 | AP14: =C38 -> 0 | AQ14: =D38 -> 0 | AR14: =U38 -> 0 | AS14: =S38 -> 0 | AT14: =S39 -> 0 | AU14: =U39 -> 0 | AV14: =S40 -> 0 | AW14: =U40 -> 0 | AX14: =U41 -> 0 | AY14: =F41 -> 0 | BF14: CLIENTES POR PUBLICIDAD DEL MES
E15: Teléfono: | F15: =IF(D14<>"", VLOOKUP(D14,'Base de Datos'!$A$2:$D1268,3,FALSE()),"") | I15: Teléfono: | J15: =IF(H14<>"", VLOOKUP(H14,'Base de Datos'!$A$2:$D1268,3,FALSE()),"") -> 0 | M15: Teléfono: | N15: =IF(L14<>"", VLOOKUP(L14,'Base de Datos'!$A$2:$D1268,3,FALSE()),"") | P15: LEYENDA | AE15: Odo. Geraldine Cabrera | AG15: =COUNTIFS(AP:AP, "💲", AY:AY, AE15) + COUNTIFS(AP:AP, "📦", AY:AY, AE15) + COUNTIFS(AP:AP, "✅", AY:AY, AE15) -> 9 | AH15: =COUNTIFS(AP:AP, "💲", AY:AY, AE15) + COUNTIFS(AP:AP, "📦", AY:AY, AE15) -> 8 | AI15: =SUMIFS(AR:AR, AY:AY, AE15, AP:AP, "💲") + SUMIFS(AR:AR, AY:AY, AE15, AP:AP, "📦") -> 500 | AJ15: =( SUMIFS(AR:AR, AY:AY, INDIRECT("AE" & ROW()), AP:AP, "💲") + SUMIFS(AR:AR, AY:AY, INDIRECT("AE" & ROW()), AP:AP, "📦") ) - ( SUMIFS(AR:AR, AY:AY, INDIRECT("AE" & ROW()), AP:AP, "💲", AS:AS, "Participante") + SUMIFS(AR:AR, AY:AY, INDIRECT("AE" & ROW()), AP:AP, "📦", AS:AS, "Participante") ) - ( SUMIFS(AR:AR, AY:AY, INDIRECT("AE" & ROW()), AP:AP, "💲", AS:AS, "Empleado") + SUMIFS(AR:AR, AY:AY, INDIRECT("AE" & ROW()), AP:AP, "📦", AS:AS, "Empleado") ) - ( ( SUMIFS(AR:AR, AY:AY, INDIRECT("AE" & ROW()), AP:AP, "💲", AS:AS, "Familiar") + SUMIFS(AR:AR, AY:AY, INDIRECT("AE" & ROW()), AP:AP, "📦", AS:AS, "Familiar") ) / 2 ) - ( ( SUMIFS(AR:AR, AY:AY, INDIRECT("AE" & ROW()), AP:AP, "💲", AS:AS, "Exonerado ADH") + SUMIFS(AR:AR, AY:AY, INDIRECT("AE" & ROW()), AP:AP, "📦", AS:AS, "Exonerado ADH") ) / 2 ) - ( ( SUMIFS(AR:AR, AY:AY, INDIRECT("AE" & ROW()), AP:AP, "💲", AS:AS, "Exonerado Doctor") + SUMIFS(AR:AR, AY:AY, INDIRECT("AE" & ROW()), AP:AP, "📦", AS:AS, "Exonerado Doctor") ) / 2 ) -> 350 | AK15: =( SUMIFS(AR:AR, AY:AY, INDIRECT("AE" & ROW()), AP:AP, "💲") + SUMIFS(AR:AR, AY:AY, INDIRECT("AE" & ROW()), AP:AP, "📦") ) - ( SUMIFS(AR:AR, AY:AY, INDIRECT("AE" & ROW()), AP:AP, "💲", AS:AS, "Familiar") + SUMIFS(AR:AR, AY:AY, INDIRECT("AE" & ROW()), AP:AP, "📦", AS:AS, "Familiar") ) - ( SUMIFS(AR:AR, AY:AY, INDIRECT("AE" & ROW()), AP:AP, "💲", AS:AS, "Participante") + SUMIFS(AR:AR, AY:AY, INDIRECT("AE" & ROW()), AP:AP, "📦", AS:AS, "Participante") ) - ( SUMIFS(AR:AR, AY:AY, INDIRECT("AE" & ROW()), AP:AP, "💲", AS:AS, "Empleado") + SUMIFS(AR:AR, AY:AY, INDIRECT("AE" & ROW()), AP:AP, "📦", AS:AS, "Empleado") ) - ( SUMIFS(AR:AR, AY:AY, INDIRECT("AE" & ROW()), AP:AP, "💲", AS:AS, "Exonerado ADH") + SUMIFS(AR:AR, AY:AY, INDIRECT("AE" & ROW()), AP:AP, "📦", AS:AS, "Exonerado ADH") ) - (( SUMIFS(AR:AR, AY:AY, INDIRECT("AE" & ROW()), AP:AP, "💲", AS:AS, "Exonerado Doctor") + SUMIFS(AR:AR, AY:AY, INDIRECT("AE" & ROW()), AP:AP, "📦", AS:AS, "Exonerado Doctor") ) / 2 )- ( ( SUMIFS(AR:AR, AY:AY, INDIRECT("AE" & ROW()), AP:AP, "💲", AS:AS, "") + SUMIFS(AR:AR, AY:AY, INDIRECT("AE" & ROW()), AP:AP, "📦", AS:AS, "") ) / 2 ) -> 350 | AL15: =( SUMIFS(AR:AR, AY:AY, INDIRECT("AE" & ROW()), AP:AP, "💲") + SUMIFS(AR:AR, AY:AY, INDIRECT("AE" & ROW()), AP:AP, "📦") ) - (( SUMIFS(AR:AR, AY:AY, INDIRECT("AE" & ROW()), AP:AP, "💲", AS:AS, "Familiar") + SUMIFS(AR:AR, AY:AY, INDIRECT("AE" & ROW()), AP:AP, "📦", AS:AS, "Familiar") ) / 2 ) - (( SUMIFS(AR:AR, AY:AY, INDIRECT("AE" & ROW()), AP:AP, "💲", AS:AS, "Participante") + SUMIFS(AR:AR, AY:AY, INDIRECT("AE" & ROW()), AP:AP, "📦", AS:AS, "Participante") ) / 2 ) - (( SUMIFS(AR:AR, AY:AY, INDIRECT("AE" & ROW()), AP:AP, "💲", AS:AS, "Empleado") + SUMIFS(AR:AR, AY:AY, INDIRECT("AE" & ROW()), AP:AP, "📦", AS:AS, "Empleado") ) / 2 ) - (( SUMIFS(AR:AR, AY:AY, INDIRECT("AE" & ROW()), AP:AP, "💲", AS:AS, "Exonerado ADH") + SUMIFS(AR:AR, AY:AY, INDIRECT("AE" & ROW()), AP:AP, "📦", AS:AS, "Exonerado ADH") ) / 2 ) - ( SUMIFS(AR:AR, AY:AY, INDIRECT("AE" & ROW()), AP:AP, "💲", AS:AS, "Exonerado Doctor") + SUMIFS(AR:AR, AY:AY, INDIRECT("AE" & ROW()), AP:AP, "📦", AS:AS, "Exonerado Doctor") )- ( ( SUMIFS(AR:AR, AY:AY, INDIRECT("AE" & ROW()), AP:AP, "💲", AS:AS, "") + SUMIFS(AR:AR, AY:AY, INDIRECT("AE" & ROW()), AP:AP, "📦", AS:AS, "") ) / 2 ) -> 425 | AN15: =A4 -> 46266 | AO15: =C5 -> Consultorio N° 1 | AP15: =C42 -> 0 | AQ15: =D42 -> 0 | AR15: =U42 -> 0 | AS15: =S42 -> 0 | AT15: =S43 -> 0 | AU15: =U43 -> 0 | AV15: =S44 -> 0 | AW15: =U44 -> 0 | AX15: =U45 -> 0 | AY15: =F45 -> 0 | BF15: Nombre y Apellido | BG15: Personal ADH | BH15: Fecha | BI15: Monto | BJ15: Doctor
E16: Cedula: | F16: =IF(D14<>"", VLOOKUP(D14,'Base de Datos'!$A$2:$D1268,4,FALSE()),"") | I16: Cedula: | J16: =IF(H14<>"", VLOOKUP(H14,'Base de Datos'!$A$2:$D1268,4,FALSE()),"") -> V-10870603 | M16: Cedula: | N16: =IF(L14<>"", VLOOKUP(L14,'Base de Datos'!$A$2:$D1268,4,FALSE()),"") | P16: 📌 | Q16: Agendada | AE16: Luzmir Fagúndez | AG16: =COUNTIFS(AP:AP, "💲", AY:AY, AE16) + COUNTIFS(AP:AP, "📦", AY:AY, AE16) + COUNTIFS(AP:AP, "✅", AY:AY, AE16) -> 6 | AH16: =COUNTIFS(AP:AP, "💲", AY:AY, AE16) + COUNTIFS(AP:AP, "📦", AY:AY, AE16) -> 6 | AI16: =SUMIFS(AR:AR, AY:AY, AE16, AP:AP, "💲") + SUMIFS(AR:AR, AY:AY, AE16, AP:AP, "📦") -> 460 | AJ16: =( SUMIFS(AR:AR, AY:AY, INDIRECT("AE" & ROW()), AP:AP, "💲") + SUMIFS(AR:AR, AY:AY, INDIRECT("AE" & ROW()), AP:AP, "📦") ) - ( SUMIFS(AR:AR, AY:AY, INDIRECT("AE" & ROW()), AP:AP, "💲", AS:AS, "Participante") + SUMIFS(AR:AR, AY:AY, INDIRECT("AE" & ROW()), AP:AP, "📦", AS:AS, "Participante") ) - ( SUMIFS(AR:AR, AY:AY, INDIRECT("AE" & ROW()), AP:AP, "💲", AS:AS, "Empleado") + SUMIFS(AR:AR, AY:AY, INDIRECT("AE" & ROW()), AP:AP, "📦", AS:AS, "Empleado") ) - ( ( SUMIFS(AR:AR, AY:AY, INDIRECT("AE" & ROW()), AP:AP, "💲", AS:AS, "Familiar") + SUMIFS(AR:AR, AY:AY, INDIRECT("AE" & ROW()), AP:AP, "📦", AS:AS, "Familiar") ) / 2 ) - ( ( SUMIFS(AR:AR, AY:AY, INDIRECT("AE" & ROW()), AP:AP, "💲", AS:AS, "Exonerado ADH") + SUMIFS(AR:AR, AY:AY, INDIRECT("AE" & ROW()), AP:AP, "📦", AS:AS, "Exonerado ADH") ) / 2 ) - ( ( SUMIFS(AR:AR, AY:AY, INDIRECT("AE" & ROW()), AP:AP, "💲", AS:AS, "Exonerado Doctor") + SUMIFS(AR:AR, AY:AY, INDIRECT("AE" & ROW()), AP:AP, "📦", AS:AS, "Exonerado Doctor") ) / 2 ) -> 435 | AK16: =( SUMIFS(AR:AR, AY:AY, INDIRECT("AE" & ROW()), AP:AP, "💲") + SUMIFS(AR:AR, AY:AY, INDIRECT("AE" & ROW()), AP:AP, "📦") ) - ( SUMIFS(AR:AR, AY:AY, INDIRECT("AE" & ROW()), AP:AP, "💲", AS:AS, "Familiar") + SUMIFS(AR:AR, AY:AY, INDIRECT("AE" & ROW()), AP:AP, "📦", AS:AS, "Familiar") ) - ( SUMIFS(AR:AR, AY:AY, INDIRECT("AE" & ROW()), AP:AP, "💲", AS:AS, "Participante") + SUMIFS(AR:AR, AY:AY, INDIRECT("AE" & ROW()), AP:AP, "📦", AS:AS, "Participante") ) - ( SUMIFS(AR:AR, AY:AY, INDIRECT("AE" & ROW()), AP:AP, "💲", AS:AS, "Empleado") + SUMIFS(AR:AR, AY:AY, INDIRECT("AE" & ROW()), AP:AP, "📦", AS:AS, "Empleado") ) - ( SUMIFS(AR:AR, AY:AY, INDIRECT("AE" & ROW()), AP:AP, "💲", AS:AS, "Exonerado ADH") + SUMIFS(AR:AR, AY:AY, INDIRECT("AE" & ROW()), AP:AP, "📦", AS:AS, "Exonerado ADH") ) - (( SUMIFS(AR:AR, AY:AY, INDIRECT("AE" & ROW()), AP:AP, "💲", AS:AS, "Exonerado Doctor") + SUMIFS(AR:AR, AY:AY, INDIRECT("AE" & ROW()), AP:AP, "📦", AS:AS, "Exonerado Doctor") ) / 2 )- ( ( SUMIFS(AR:AR, AY:AY, INDIRECT("AE" & ROW()), AP:AP, "💲", AS:AS, "") + SUMIFS(AR:AR, AY:AY, INDIRECT("AE" & ROW()), AP:AP, "📦", AS:AS, "") ) / 2 ) -> 410 | AL16: =( SUMIFS(AR:AR, AY:AY, INDIRECT("AE" & ROW()), AP:AP, "💲") + SUMIFS(AR:AR, AY:AY, INDIRECT("AE" & ROW()), AP:AP, "📦") ) - (( SUMIFS(AR:AR, AY:AY, INDIRECT("AE" & ROW()), AP:AP, "💲", AS:AS, "Familiar") + SUMIFS(AR:AR, AY:AY, INDIRECT("AE" & ROW()), AP:AP, "📦", AS:AS, "Familiar") ) / 2 ) - (( SUMIFS(AR:AR, AY:AY, INDIRECT("AE" & ROW()), AP:AP, "💲", AS:AS, "Participante") + SUMIFS(AR:AR, AY:AY, INDIRECT("AE" & ROW()), AP:AP, "📦", AS:AS, "Participante") ) / 2 ) - (( SUMIFS(AR:AR, AY:AY, INDIRECT("AE" & ROW()), AP:AP, "💲", AS:AS, "Empleado") + SUMIFS(AR:AR, AY:AY, INDIRECT("AE" & ROW()), AP:AP, "📦", AS:AS, "Empleado") ) / 2 ) - (( SUMIFS(AR:AR, AY:AY, INDIRECT("AE" & ROW()), AP:AP, "💲", AS:AS, "Exonerado ADH") + SUMIFS(AR:AR, AY:AY, INDIRECT("AE" & ROW()), AP:AP, "📦", AS:AS, "Exonerado ADH") ) / 2 ) - ( SUMIFS(AR:AR, AY:AY, INDIRECT("AE" & ROW()), AP:AP, "💲", AS:AS, "Exonerado Doctor") + SUMIFS(AR:AR, AY:AY, INDIRECT("AE" & ROW()), AP:AP, "📦", AS:AS, "Exonerado Doctor") )- ( ( SUMIFS(AR:AR, AY:AY, INDIRECT("AE" & ROW()), AP:AP, "💲", AS:AS, "") + SUMIFS(AR:AR, AY:AY, INDIRECT("AE" & ROW()), AP:AP, "📦", AS:AS, "") ) / 2 ) -> 435 | AN16: =A4 -> 46266 | AO16: Consultorio N° 1 | AP16: =C46 -> 0 | AQ16: =D46 -> 0 | AR16: =U46 -> 0 | AS16: =S46 -> 0 | AT16: =S47 -> 0 | AU16: =U47 -> 0 | AV16: =S48 -> 0 | AW16: =U48 -> 0 | AX16: =U49 -> 0 | AY16: =F49 -> 0 | BF16: =IFERROR(__xludf.DUMMYFUNCTION("QUERY(AN:AY, ""SELECT AQ, AX, AN, AR, AY WHERE AS = 'Publicidad' AND (AP = '💲' OR AP = '📦') ORDER BY AN"", )"),"#N/A") -> #N/A
E17: Doctor: | I17: Doctor: | J17: Dra. Mónica Porras | M17: Doctor: | P17: 📞 | Q17: Sin confirmar | S17: =IF(OR(S14="Empleado",S14="Familiar"),"Nombre del Empleado","N° Factura") -> N° Factura | W17: =IF(OR(W14="Empleado",W14="Familiar"),"Nombre del Empleado","N° Factura") -> N° Factura | AA17: =IF(OR(AA14="Empleado",AA14="Familiar"),"Nombre del Empleado","N° Factura") -> N° Factura | AE17: Dra. Mariana Morales | AG17: =COUNTIFS(AP:AP, "💲", AY:AY, AE17) + COUNTIFS(AP:AP, "📦", AY:AY, AE17) + COUNTIFS(AP:AP, "✅", AY:AY, AE17) -> 0 | AH17: =COUNTIFS(AP:AP, "💲", AY:AY, AE17) + COUNTIFS(AP:AP, "📦", AY:AY, AE17) -> 0 | AI17: =SUMIFS(AR:AR, AY:AY, AE17, AP:AP, "💲") + SUMIFS(AR:AR, AY:AY, AE17, AP:AP, "📦") -> 0 | AJ17: =( SUMIFS(AR:AR, AY:AY, INDIRECT("AE" & ROW()), AP:AP, "💲") + SUMIFS(AR:AR, AY:AY, INDIRECT("AE" & ROW()), AP:AP, "📦") ) - ( SUMIFS(AR:AR, AY:AY, INDIRECT("AE" & ROW()), AP:AP, "💲", AS:AS, "Participante") + SUMIFS(AR:AR, AY:AY, INDIRECT("AE" & ROW()), AP:AP, "📦", AS:AS, "Participante") ) - ( SUMIFS(AR:AR, AY:AY, INDIRECT("AE" & ROW()), AP:AP, "💲", AS:AS, "Empleado") + SUMIFS(AR:AR, AY:AY, INDIRECT("AE" & ROW()), AP:AP, "📦", AS:AS, "Empleado") ) - ( ( SUMIFS(AR:AR, AY:AY, INDIRECT("AE" & ROW()), AP:AP, "💲", AS:AS, "Familiar") + SUMIFS(AR:AR, AY:AY, INDIRECT("AE" & ROW()), AP:AP, "📦", AS:AS, "Familiar") ) / 2 ) - ( ( SUMIFS(AR:AR, AY:AY, INDIRECT("AE" & ROW()), AP:AP, "💲", AS:AS, "Exonerado ADH") + SUMIFS(AR:AR, AY:AY, INDIRECT("AE" & ROW()), AP:AP, "📦", AS:AS, "Exonerado ADH") ) / 2 ) - ( ( SUMIFS(AR:AR, AY:AY, INDIRECT("AE" & ROW()), AP:AP, "💲", AS:AS, "Exonerado Doctor") + SUMIFS(AR:AR, AY:AY, INDIRECT("AE" & ROW()), AP:AP, "📦", AS:AS, "Exonerado Doctor") ) / 2 ) -> 0 | AK17: =( SUMIFS(AR:AR, AY:AY, INDIRECT("AE" & ROW()), AP:AP, "💲") + SUMIFS(AR:AR, AY:AY, INDIRECT("AE" & ROW()), AP:AP, "📦") ) - ( SUMIFS(AR:AR, AY:AY, INDIRECT("AE" & ROW()), AP:AP, "💲", AS:AS, "Familiar") + SUMIFS(AR:AR, AY:AY, INDIRECT("AE" & ROW()), AP:AP, "📦", AS:AS, "Familiar") ) - ( SUMIFS(AR:AR, AY:AY, INDIRECT("AE" & ROW()), AP:AP, "💲", AS:AS, "Participante") + SUMIFS(AR:AR, AY:AY, INDIRECT("AE" & ROW()), AP:AP, "📦", AS:AS, "Participante") ) - ( SUMIFS(AR:AR, AY:AY, INDIRECT("AE" & ROW()), AP:AP, "💲", AS:AS, "Empleado") + SUMIFS(AR:AR, AY:AY, INDIRECT("AE" & ROW()), AP:AP, "📦", AS:AS, "Empleado") ) - ( SUMIFS(AR:AR, AY:AY, INDIRECT("AE" & ROW()), AP:AP, "💲", AS:AS, "Exonerado ADH") + SUMIFS(AR:AR, AY:AY, INDIRECT("AE" & ROW()), AP:AP, "📦", AS:AS, "Exonerado ADH") ) - (( SUMIFS(AR:AR, AY:AY, INDIRECT("AE" & ROW()), AP:AP, "💲", AS:AS, "Exonerado Doctor") + SUMIFS(AR:AR, AY:AY, INDIRECT("AE" & ROW()), AP:AP, "📦", AS:AS, "Exonerado Doctor") ) / 2 )- ( ( SUMIFS(AR:AR, AY:AY, INDIRECT("AE" & ROW()), AP:AP, "💲", AS:AS, "") + SUMIFS(AR:AR, AY:AY, INDIRECT("AE" & ROW()), AP:AP, "📦", AS:AS, "") ) / 2 ) -> 0 | AL17: =( SUMIFS(AR:AR, AY:AY, INDIRECT("AE" & ROW()), AP:AP, "💲") + SUMIFS(AR:AR, AY:AY, INDIRECT("AE" & ROW()), AP:AP, "📦") ) - (( SUMIFS(AR:AR, AY:AY, INDIRECT("AE" & ROW()), AP:AP, "💲", AS:AS, "Familiar") + SUMIFS(AR:AR, AY:AY, INDIRECT("AE" & ROW()), AP:AP, "📦", AS:AS, "Familiar") ) / 2 ) - (( SUMIFS(AR:AR, AY:AY, INDIRECT("AE" & ROW()), AP:AP, "💲", AS:AS, "Participante") + SUMIFS(AR:AR, AY:AY, INDIRECT("AE" & ROW()), AP:AP, "📦", AS:AS, "Participante") ) / 2 ) - (( SUMIFS(AR:AR, AY:AY, INDIRECT("AE" & ROW()), AP:AP, "💲", AS:AS, "Empleado") + SUMIFS(AR:AR, AY:AY, INDIRECT("AE" & ROW()), AP:AP, "📦", AS:AS, "Empleado") ) / 2 ) - (( SUMIFS(AR:AR, AY:AY, INDIRECT("AE" & ROW()), AP:AP, "💲", AS:AS, "Exonerado ADH") + SUMIFS(AR:AR, AY:AY, INDIRECT("AE" & ROW()), AP:AP, "📦", AS:AS, "Exonerado ADH") ) / 2 ) - ( SUMIFS(AR:AR, AY:AY, INDIRECT("AE" & ROW()), AP:AP, "💲", AS:AS, "Exonerado Doctor") + SUMIFS(AR:AR, AY:AY, INDIRECT("AE" & ROW()), AP:AP, "📦", AS:AS, "Exonerado Doctor") )- ( ( SUMIFS(AR:AR, AY:AY, INDIRECT("AE" & ROW()), AP:AP, "💲", AS:AS, "") + SUMIFS(AR:AR, AY:AY, INDIRECT("AE" & ROW()), AP:AP, "📦", AS:AS, "") ) / 2 ) -> 0 | AN17: =A4 -> 46266 | AO17: Consultorio N° 1 | AP17: =C50 -> 0 | AQ17: =D50 -> 0 | AR17: =U50 -> 0 | AS17: =S50 -> 0 | AT17: =S51 -> 0 | AU17: =U51 -> 0 | AV17: =S52 -> 0 | AW17: =U52 -> 0 | AX17: =U53 -> 0 | AY17: =F53 -> 0
A18: =A14+$Q$13/1440 -> 0.45833333 | E18: Representante: | F18: =IF(D18<>"", VLOOKUP(D18,'Base de Datos'!$A$2:$D1268,2,FALSE()),"") | I18: Representante: | J18: =IF(H18<>"", VLOOKUP(H18,'Base de Datos'!$A$2:$D1268,2,FALSE()),"") | M18: Representante: | N18: =IF(L18<>"", VLOOKUP(L18,'Base de Datos'!$A$2:$D1268,2,FALSE()),"") | P18: ✔️ | Q18: Confirmado | T18: Precio: | X18: Precio: | AB18: Precio: | AE18: Dra. Evelyn Tranchino | AG18: =COUNTIFS(AP:AP, "💲", AY:AY, AE18) + COUNTIFS(AP:AP, "📦", AY:AY, AE18) + COUNTIFS(AP:AP, "✅", AY:AY, AE18) -> 9 | AH18: =COUNTIFS(AP:AP, "💲", AY:AY, AE18) + COUNTIFS(AP:AP, "📦", AY:AY, AE18) -> 9 | AI18: =SUMIFS(AR:AR, AY:AY, AE18, AP:AP, "💲") + SUMIFS(AR:AR, AY:AY, AE18, AP:AP, "📦") -> 490 | AJ18: =( SUMIFS(AR:AR, AY:AY, INDIRECT("AE" & ROW()), AP:AP, "💲") + SUMIFS(AR:AR, AY:AY, INDIRECT("AE" & ROW()), AP:AP, "📦") ) - ( SUMIFS(AR:AR, AY:AY, INDIRECT("AE" & ROW()), AP:AP, "💲", AS:AS, "Participante") + SUMIFS(AR:AR, AY:AY, INDIRECT("AE" & ROW()), AP:AP, "📦", AS:AS, "Participante") ) - ( SUMIFS(AR:AR, AY:AY, INDIRECT("AE" & ROW()), AP:AP, "💲", AS:AS, "Empleado") + SUMIFS(AR:AR, AY:AY, INDIRECT("AE" & ROW()), AP:AP, "📦", AS:AS, "Empleado") ) - ( ( SUMIFS(AR:AR, AY:AY, INDIRECT("AE" & ROW()), AP:AP, "💲", AS:AS, "Familiar") + SUMIFS(AR:AR, AY:AY, INDIRECT("AE" & ROW()), AP:AP, "📦", AS:AS, "Familiar") ) / 2 ) - ( ( SUMIFS(AR:AR, AY:AY, INDIRECT("AE" & ROW()), AP:AP, "💲", AS:AS, "Exonerado ADH") + SUMIFS(AR:AR, AY:AY, INDIRECT("AE" & ROW()), AP:AP, "📦", AS:AS, "Exonerado ADH") ) / 2 ) - ( ( SUMIFS(AR:AR, AY:AY, INDIRECT("AE" & ROW()), AP:AP, "💲", AS:AS, "Exonerado Doctor") + SUMIFS(AR:AR, AY:AY, INDIRECT("AE" & ROW()), AP:AP, "📦", AS:AS, "Exonerado Doctor") ) / 2 ) -> 490 | AK18: =( SUMIFS(AR:AR, AY:AY, INDIRECT("AE" & ROW()), AP:AP, "💲") + SUMIFS(AR:AR, AY:AY, INDIRECT("AE" & ROW()), AP:AP, "📦") ) - ( SUMIFS(AR:AR, AY:AY, INDIRECT("AE" & ROW()), AP:AP, "💲", AS:AS, "Familiar") + SUMIFS(AR:AR, AY:AY, INDIRECT("AE" & ROW()), AP:AP, "📦", AS:AS, "Familiar") ) - ( SUMIFS(AR:AR, AY:AY, INDIRECT("AE" & ROW()), AP:AP, "💲", AS:AS, "Participante") + SUMIFS(AR:AR, AY:AY, INDIRECT("AE" & ROW()), AP:AP, "📦", AS:AS, "Participante") ) - ( SUMIFS(AR:AR, AY:AY, INDIRECT("AE" & ROW()), AP:AP, "💲", AS:AS, "Empleado") + SUMIFS(AR:AR, AY:AY, INDIRECT("AE" & ROW()), AP:AP, "📦", AS:AS, "Empleado") ) - ( SUMIFS(AR:AR, AY:AY, INDIRECT("AE" & ROW()), AP:AP, "💲", AS:AS, "Exonerado ADH") + SUMIFS(AR:AR, AY:AY, INDIRECT("AE" & ROW()), AP:AP, "📦", AS:AS, "Exonerado ADH") ) - (( SUMIFS(AR:AR, AY:AY, INDIRECT("AE" & ROW()), AP:AP, "💲", AS:AS, "Exonerado Doctor") + SUMIFS(AR:AR, AY:AY, INDIRECT("AE" & ROW()), AP:AP, "📦", AS:AS, "Exonerado Doctor") ) / 2 )- ( ( SUMIFS(AR:AR, AY:AY, INDIRECT("AE" & ROW()), AP:AP, "💲", AS:AS, "") + SUMIFS(AR:AR, AY:AY, INDIRECT("AE" & ROW()), AP:AP, "📦", AS:AS, "") ) / 2 ) -> 490 | AL18: =( SUMIFS(AR:AR, AY:AY, INDIRECT("AE" & ROW()), AP:AP, "💲") + SUMIFS(AR:AR, AY:AY, INDIRECT("AE" & ROW()), AP:AP, "📦") ) - (( SUMIFS(AR:AR, AY:AY, INDIRECT("AE" & ROW()), AP:AP, "💲", AS:AS, "Familiar") + SUMIFS(AR:AR, AY:AY, INDIRECT("AE" & ROW()), AP:AP, "📦", AS:AS, "Familiar") ) / 2 ) - (( SUMIFS(AR:AR, AY:AY, INDIRECT("AE" & ROW()), AP:AP, "💲", AS:AS, "Participante") + SUMIFS(AR:AR, AY:AY, INDIRECT("AE" & ROW()), AP:AP, "📦", AS:AS, "Participante") ) / 2 ) - (( SUMIFS(AR:AR, AY:AY, INDIRECT("AE" & ROW()), AP:AP, "💲", AS:AS, "Empleado") + SUMIFS(AR:AR, AY:AY, INDIRECT("AE" & ROW()), AP:AP, "📦", AS:AS, "Empleado") ) / 2 ) - (( SUMIFS(AR:AR, AY:AY, INDIRECT("AE" & ROW()), AP:AP, "💲", AS:AS, "Exonerado ADH") + SUMIFS(AR:AR, AY:AY, INDIRECT("AE" & ROW()), AP:AP, "📦", AS:AS, "Exonerado ADH") ) / 2 ) - ( SUMIFS(AR:AR, AY:AY, INDIRECT("AE" & ROW()), AP:AP, "💲", AS:AS, "Exonerado Doctor") + SUMIFS(AR:AR, AY:AY, INDIRECT("AE" & ROW()), AP:AP, "📦", AS:AS, "Exonerado Doctor") )- ( ( SUMIFS(AR:AR, AY:AY, INDIRECT("AE" & ROW()), AP:AP, "💲", AS:AS, "") + SUMIFS(AR:AR, AY:AY, INDIRECT("AE" & ROW()), AP:AP, "📦", AS:AS, "") ) / 2 ) -> 490 | AN18: =A4 -> 46266 | AO18: Consultorio N° 1 | AP18: =C54 -> 0 | AQ18: =D54 -> 0 | AR18: =U54 -> 0 | AS18: =S54 -> 0 | AT18: =S55 -> 0 | AU18: =U55 -> 0 | AV18: =S56 -> 0 | AW18: =U56 -> 0 | AX18: =U57 -> 0 | AY18: =F57 -> 0
E19: Teléfono: | F19: =IF(D18<>"", VLOOKUP(D18,'Base de Datos'!$A$2:$D1268,3,FALSE()),"") | I19: Teléfono: | J19: =IF(H18<>"", VLOOKUP(H18,'Base de Datos'!$A$2:$D1268,3,FALSE()),"") | M19: Teléfono: | N19: =IF(L18<>"", VLOOKUP(L18,'Base de Datos'!$A$2:$D1268,3,FALSE()),"") | P19: ✅ | Q19: Completado | AE19: Dra. Elisa Villasmil | AG19: =COUNTIFS(AP:AP, "💲", AY:AY, AE19) + COUNTIFS(AP:AP, "📦", AY:AY, AE19) + COUNTIFS(AP:AP, "✅", AY:AY, AE19) -> 0 | AH19: =COUNTIFS(AP:AP, "💲", AY:AY, AE19) + COUNTIFS(AP:AP, "📦", AY:AY, AE19) -> 0 | AI19: =SUMIFS(AR:AR, AY:AY, AE19, AP:AP, "💲") + SUMIFS(AR:AR, AY:AY, AE19, AP:AP, "📦") -> 0 | AJ19: =( SUMIFS(AR:AR, AY:AY, INDIRECT("AE" & ROW()), AP:AP, "💲") + SUMIFS(AR:AR, AY:AY, INDIRECT("AE" & ROW()), AP:AP, "📦") ) - ( SUMIFS(AR:AR, AY:AY, INDIRECT("AE" & ROW()), AP:AP, "💲", AS:AS, "Participante") + SUMIFS(AR:AR, AY:AY, INDIRECT("AE" & ROW()), AP:AP, "📦", AS:AS, "Participante") ) - ( SUMIFS(AR:AR, AY:AY, INDIRECT("AE" & ROW()), AP:AP, "💲", AS:AS, "Empleado") + SUMIFS(AR:AR, AY:AY, INDIRECT("AE" & ROW()), AP:AP, "📦", AS:AS, "Empleado") ) - ( ( SUMIFS(AR:AR, AY:AY, INDIRECT("AE" & ROW()), AP:AP, "💲", AS:AS, "Familiar") + SUMIFS(AR:AR, AY:AY, INDIRECT("AE" & ROW()), AP:AP, "📦", AS:AS, "Familiar") ) / 2 ) - ( ( SUMIFS(AR:AR, AY:AY, INDIRECT("AE" & ROW()), AP:AP, "💲", AS:AS, "Exonerado ADH") + SUMIFS(AR:AR, AY:AY, INDIRECT("AE" & ROW()), AP:AP, "📦", AS:AS, "Exonerado ADH") ) / 2 ) - ( ( SUMIFS(AR:AR, AY:AY, INDIRECT("AE" & ROW()), AP:AP, "💲", AS:AS, "Exonerado Doctor") + SUMIFS(AR:AR, AY:AY, INDIRECT("AE" & ROW()), AP:AP, "📦", AS:AS, "Exonerado Doctor") ) / 2 ) -> 0 | AK19: =( SUMIFS(AR:AR, AY:AY, INDIRECT("AE" & ROW()), AP:AP, "💲") + SUMIFS(AR:AR, AY:AY, INDIRECT("AE" & ROW()), AP:AP, "📦") ) - ( SUMIFS(AR:AR, AY:AY, INDIRECT("AE" & ROW()), AP:AP, "💲", AS:AS, "Familiar") + SUMIFS(AR:AR, AY:AY, INDIRECT("AE" & ROW()), AP:AP, "📦", AS:AS, "Familiar") ) - ( SUMIFS(AR:AR, AY:AY, INDIRECT("AE" & ROW()), AP:AP, "💲", AS:AS, "Participante") + SUMIFS(AR:AR, AY:AY, INDIRECT("AE" & ROW()), AP:AP, "📦", AS:AS, "Participante") ) - ( SUMIFS(AR:AR, AY:AY, INDIRECT("AE" & ROW()), AP:AP, "💲", AS:AS, "Empleado") + SUMIFS(AR:AR, AY:AY, INDIRECT("AE" & ROW()), AP:AP, "📦", AS:AS, "Empleado") ) - ( SUMIFS(AR:AR, AY:AY, INDIRECT("AE" & ROW()), AP:AP, "💲", AS:AS, "Exonerado ADH") + SUMIFS(AR:AR, AY:AY, INDIRECT("AE" & ROW()), AP:AP, "📦", AS:AS, "Exonerado ADH") ) - (( SUMIFS(AR:AR, AY:AY, INDIRECT("AE" & ROW()), AP:AP, "💲", AS:AS, "Exonerado Doctor") + SUMIFS(AR:AR, AY:AY, INDIRECT("AE" & ROW()), AP:AP, "📦", AS:AS, "Exonerado Doctor") ) / 2 )- ( ( SUMIFS(AR:AR, AY:AY, INDIRECT("AE" & ROW()), AP:AP, "💲", AS:AS, "") + SUMIFS(AR:AR, AY:AY, INDIRECT("AE" & ROW()), AP:AP, "📦", AS:AS, "") ) / 2 ) -> 0 | AL19: =( SUMIFS(AR:AR, AY:AY, INDIRECT("AE" & ROW()), AP:AP, "💲") + SUMIFS(AR:AR, AY:AY, INDIRECT("AE" & ROW()), AP:AP, "📦") ) - (( SUMIFS(AR:AR, AY:AY, INDIRECT("AE" & ROW()), AP:AP, "💲", AS:AS, "Familiar") + SUMIFS(AR:AR, AY:AY, INDIRECT("AE" & ROW()), AP:AP, "📦", AS:AS, "Familiar") ) / 2 ) - (( SUMIFS(AR:AR, AY:AY, INDIRECT("AE" & ROW()), AP:AP, "💲", AS:AS, "Participante") + SUMIFS(AR:AR, AY:AY, INDIRECT("AE" & ROW()), AP:AP, "📦", AS:AS, "Participante") ) / 2 ) - (( SUMIFS(AR:AR, AY:AY, INDIRECT("AE" & ROW()), AP:AP, "💲", AS:AS, "Empleado") + SUMIFS(AR:AR, AY:AY, INDIRECT("AE" & ROW()), AP:AP, "📦", AS:AS, "Empleado") ) / 2 ) - (( SUMIFS(AR:AR, AY:AY, INDIRECT("AE" & ROW()), AP:AP, "💲", AS:AS, "Exonerado ADH") + SUMIFS(AR:AR, AY:AY, INDIRECT("AE" & ROW()), AP:AP, "📦", AS:AS, "Exonerado ADH") ) / 2 ) - ( SUMIFS(AR:AR, AY:AY, INDIRECT("AE" & ROW()), AP:AP, "💲", AS:AS, "Exonerado Doctor") + SUMIFS(AR:AR, AY:AY, INDIRECT("AE" & ROW()), AP:AP, "📦", AS:AS, "Exonerado Doctor") )- ( ( SUMIFS(AR:AR, AY:AY, INDIRECT("AE" & ROW()), AP:AP, "💲", AS:AS, "") + SUMIFS(AR:AR, AY:AY, INDIRECT("AE" & ROW()), AP:AP, "📦", AS:AS, "") ) / 2 ) -> 0 | AN19: =A4 -> 46266 | AO19: =G5 -> Consultorio N° 2 | AP19: =G6 -> 0 | AQ19: =H6 -> 0 | AR19: =Y6 -> 0 | AS19: =W6 -> 0 | AT19: =W7 -> 0 | AU19: =Y7 -> 0 | AV19: =W8 -> 0 | AW19: =Y8 -> 0 | AX19: =Y9 -> 0 | AY19: =J9 -> 0
E20: Cedula: | F20: =IF(D18<>"", VLOOKUP(D18,'Base de Datos'!$A$2:$D1268,4,FALSE()),"") | I20: Cedula: | J20: =IF(H18<>"", VLOOKUP(H18,'Base de Datos'!$A$2:$D1268,4,FALSE()),"") | M20: Cedula: | N20: =IF(L18<>"", VLOOKUP(L18,'Base de Datos'!$A$2:$D1268,4,FALSE()),"") | P20: 🚫 | Q20: No asistio | AE20: Dra. Elisa Izquierdo | AG20: =COUNTIFS(AP:AP, "💲", AY:AY, AE20) + COUNTIFS(AP:AP, "📦", AY:AY, AE20) + COUNTIFS(AP:AP, "✅", AY:AY, AE20) -> 0 | AH20: =COUNTIFS(AP:AP, "💲", AY:AY, AE20) + COUNTIFS(AP:AP, "📦", AY:AY, AE20) -> 0 | AI20: =SUMIFS(AR:AR, AY:AY, AE20, AP:AP, "💲") + SUMIFS(AR:AR, AY:AY, AE20, AP:AP, "📦") -> 0 | AJ20: =( SUMIFS(AR:AR, AY:AY, INDIRECT("AE" & ROW()), AP:AP, "💲") + SUMIFS(AR:AR, AY:AY, INDIRECT("AE" & ROW()), AP:AP, "📦") ) - ( SUMIFS(AR:AR, AY:AY, INDIRECT("AE" & ROW()), AP:AP, "💲", AS:AS, "Participante") + SUMIFS(AR:AR, AY:AY, INDIRECT("AE" & ROW()), AP:AP, "📦", AS:AS, "Participante") ) - ( SUMIFS(AR:AR, AY:AY, INDIRECT("AE" & ROW()), AP:AP, "💲", AS:AS, "Empleado") + SUMIFS(AR:AR, AY:AY, INDIRECT("AE" & ROW()), AP:AP, "📦", AS:AS, "Empleado") ) - ( ( SUMIFS(AR:AR, AY:AY, INDIRECT("AE" & ROW()), AP:AP, "💲", AS:AS, "Familiar") + SUMIFS(AR:AR, AY:AY, INDIRECT("AE" & ROW()), AP:AP, "📦", AS:AS, "Familiar") ) / 2 ) - ( ( SUMIFS(AR:AR, AY:AY, INDIRECT("AE" & ROW()), AP:AP, "💲", AS:AS, "Exonerado ADH") + SUMIFS(AR:AR, AY:AY, INDIRECT("AE" & ROW()), AP:AP, "📦", AS:AS, "Exonerado ADH") ) / 2 ) - ( ( SUMIFS(AR:AR, AY:AY, INDIRECT("AE" & ROW()), AP:AP, "💲", AS:AS, "Exonerado Doctor") + SUMIFS(AR:AR, AY:AY, INDIRECT("AE" & ROW()), AP:AP, "📦", AS:AS, "Exonerado Doctor") ) / 2 ) -> 0 | AK20: =( SUMIFS(AR:AR, AY:AY, INDIRECT("AE" & ROW()), AP:AP, "💲") + SUMIFS(AR:AR, AY:AY, INDIRECT("AE" & ROW()), AP:AP, "📦") ) - ( SUMIFS(AR:AR, AY:AY, INDIRECT("AE" & ROW()), AP:AP, "💲", AS:AS, "Familiar") + SUMIFS(AR:AR, AY:AY, INDIRECT("AE" & ROW()), AP:AP, "📦", AS:AS, "Familiar") ) - ( SUMIFS(AR:AR, AY:AY, INDIRECT("AE" & ROW()), AP:AP, "💲", AS:AS, "Participante") + SUMIFS(AR:AR, AY:AY, INDIRECT("AE" & ROW()), AP:AP, "📦", AS:AS, "Participante") ) - ( SUMIFS(AR:AR, AY:AY, INDIRECT("AE" & ROW()), AP:AP, "💲", AS:AS, "Empleado") + SUMIFS(AR:AR, AY:AY, INDIRECT("AE" & ROW()), AP:AP, "📦", AS:AS, "Empleado") ) - ( SUMIFS(AR:AR, AY:AY, INDIRECT("AE" & ROW()), AP:AP, "💲", AS:AS, "Exonerado ADH") + SUMIFS(AR:AR, AY:AY, INDIRECT("AE" & ROW()), AP:AP, "📦", AS:AS, "Exonerado ADH") ) - (( SUMIFS(AR:AR, AY:AY, INDIRECT("AE" & ROW()), AP:AP, "💲", AS:AS, "Exonerado Doctor") + SUMIFS(AR:AR, AY:AY, INDIRECT("AE" & ROW()), AP:AP, "📦", AS:AS, "Exonerado Doctor") ) / 2 )- ( ( SUMIFS(AR:AR, AY:AY, INDIRECT("AE" & ROW()), AP:AP, "💲", AS:AS, "") + SUMIFS(AR:AR, AY:AY, INDIRECT("AE" & ROW()), AP:AP, "📦", AS:AS, "") ) / 2 ) -> 0 | AL20: =( SUMIFS(AR:AR, AY:AY, INDIRECT("AE" & ROW()), AP:AP, "💲") + SUMIFS(AR:AR, AY:AY, INDIRECT("AE" & ROW()), AP:AP, "📦") ) - (( SUMIFS(AR:AR, AY:AY, INDIRECT("AE" & ROW()), AP:AP, "💲", AS:AS, "Familiar") + SUMIFS(AR:AR, AY:AY, INDIRECT("AE" & ROW()), AP:AP, "📦", AS:AS, "Familiar") ) / 2 ) - (( SUMIFS(AR:AR, AY:AY, INDIRECT("AE" & ROW()), AP:AP, "💲", AS:AS, "Participante") + SUMIFS(AR:AR, AY:AY, INDIRECT("AE" & ROW()), AP:AP, "📦", AS:AS, "Participante") ) / 2 ) - (( SUMIFS(AR:AR, AY:AY, INDIRECT("AE" & ROW()), AP:AP, "💲", AS:AS, "Empleado") + SUMIFS(AR:AR, AY:AY, INDIRECT("AE" & ROW()), AP:AP, "📦", AS:AS, "Empleado") ) / 2 ) - (( SUMIFS(AR:AR, AY:AY, INDIRECT("AE" & ROW()), AP:AP, "💲", AS:AS, "Exonerado ADH") + SUMIFS(AR:AR, AY:AY, INDIRECT("AE" & ROW()), AP:AP, "📦", AS:AS, "Exonerado ADH") ) / 2 ) - ( SUMIFS(AR:AR, AY:AY, INDIRECT("AE" & ROW()), AP:AP, "💲", AS:AS, "Exonerado Doctor") + SUMIFS(AR:AR, AY:AY, INDIRECT("AE" & ROW()), AP:AP, "📦", AS:AS, "Exonerado Doctor") )- ( ( SUMIFS(AR:AR, AY:AY, INDIRECT("AE" & ROW()), AP:AP, "💲", AS:AS, "") + SUMIFS(AR:AR, AY:AY, INDIRECT("AE" & ROW()), AP:AP, "📦", AS:AS, "") ) / 2 ) -> 0 | AN20: =A4 -> 46266 | AO20: =G5 -> Consultorio N° 2 | AP20: =G10 -> 0 | AQ20: =H10 -> 0 | AR20: =Y10 -> 0 | AS20: =W10 -> 0 | AT20: =W11 -> 0 | AU20: =Y11 -> 0 | AV20: =W12 -> 0 | AW20: =Y12 -> 0 | AX20: =Y13 -> 0 | AY20: =J13 -> 0
E21: Doctor: | I21: Doctor: | M21: Doctor: | P21: 💲 | Q21: Pagado | S21: =IF(OR(S18="Empleado",S18="Familiar"),"Nombre del Empleado","N° Factura") -> N° Factura | W21: =IF(OR(W18="Empleado",W18="Familiar"),"Nombre del Empleado","N° Factura") -> N° Factura | AA21: =IF(OR(AA18="Empleado",AA18="Familiar"),"Nombre del Empleado","N° Factura") -> N° Factura | AE21: Dra. Gabriela Berbis | AG21: =COUNTIFS(AP:AP, "💲", AY:AY, AE21) + COUNTIFS(AP:AP, "📦", AY:AY, AE21) + COUNTIFS(AP:AP, "✅", AY:AY, AE21) -> 1 | AH21: =COUNTIFS(AP:AP, "💲", AY:AY, AE21) + COUNTIFS(AP:AP, "📦", AY:AY, AE21) -> 1 | AI21: =SUMIFS(AR:AR, AY:AY, AE21, AP:AP, "💲") + SUMIFS(AR:AR, AY:AY, AE21, AP:AP, "📦") -> 50 | AJ21: =( SUMIFS(AR:AR, AY:AY, INDIRECT("AE" & ROW()), AP:AP, "💲") + SUMIFS(AR:AR, AY:AY, INDIRECT("AE" & ROW()), AP:AP, "📦") ) - ( SUMIFS(AR:AR, AY:AY, INDIRECT("AE" & ROW()), AP:AP, "💲", AS:AS, "Participante") + SUMIFS(AR:AR, AY:AY, INDIRECT("AE" & ROW()), AP:AP, "📦", AS:AS, "Participante") ) - ( SUMIFS(AR:AR, AY:AY, INDIRECT("AE" & ROW()), AP:AP, "💲", AS:AS, "Empleado") + SUMIFS(AR:AR, AY:AY, INDIRECT("AE" & ROW()), AP:AP, "📦", AS:AS, "Empleado") ) - ( ( SUMIFS(AR:AR, AY:AY, INDIRECT("AE" & ROW()), AP:AP, "💲", AS:AS, "Familiar") + SUMIFS(AR:AR, AY:AY, INDIRECT("AE" & ROW()), AP:AP, "📦", AS:AS, "Familiar") ) / 2 ) - ( ( SUMIFS(AR:AR, AY:AY, INDIRECT("AE" & ROW()), AP:AP, "💲", AS:AS, "Exonerado ADH") + SUMIFS(AR:AR, AY:AY, INDIRECT("AE" & ROW()), AP:AP, "📦", AS:AS, "Exonerado ADH") ) / 2 ) - ( ( SUMIFS(AR:AR, AY:AY, INDIRECT("AE" & ROW()), AP:AP, "💲", AS:AS, "Exonerado Doctor") + SUMIFS(AR:AR, AY:AY, INDIRECT("AE" & ROW()), AP:AP, "📦", AS:AS, "Exonerado Doctor") ) / 2 ) -> 0 | AK21: =( SUMIFS(AR:AR, AY:AY, INDIRECT("AE" & ROW()), AP:AP, "💲") + SUMIFS(AR:AR, AY:AY, INDIRECT("AE" & ROW()), AP:AP, "📦") ) - ( SUMIFS(AR:AR, AY:AY, INDIRECT("AE" & ROW()), AP:AP, "💲", AS:AS, "Familiar") + SUMIFS(AR:AR, AY:AY, INDIRECT("AE" & ROW()), AP:AP, "📦", AS:AS, "Familiar") ) - ( SUMIFS(AR:AR, AY:AY, INDIRECT("AE" & ROW()), AP:AP, "💲", AS:AS, "Participante") + SUMIFS(AR:AR, AY:AY, INDIRECT("AE" & ROW()), AP:AP, "📦", AS:AS, "Participante") ) - ( SUMIFS(AR:AR, AY:AY, INDIRECT("AE" & ROW()), AP:AP, "💲", AS:AS, "Empleado") + SUMIFS(AR:AR, AY:AY, INDIRECT("AE" & ROW()), AP:AP, "📦", AS:AS, "Empleado") ) - ( SUMIFS(AR:AR, AY:AY, INDIRECT("AE" & ROW()), AP:AP, "💲", AS:AS, "Exonerado ADH") + SUMIFS(AR:AR, AY:AY, INDIRECT("AE" & ROW()), AP:AP, "📦", AS:AS, "Exonerado ADH") ) - (( SUMIFS(AR:AR, AY:AY, INDIRECT("AE" & ROW()), AP:AP, "💲", AS:AS, "Exonerado Doctor") + SUMIFS(AR:AR, AY:AY, INDIRECT("AE" & ROW()), AP:AP, "📦", AS:AS, "Exonerado Doctor") ) / 2 )- ( ( SUMIFS(AR:AR, AY:AY, INDIRECT("AE" & ROW()), AP:AP, "💲", AS:AS, "") + SUMIFS(AR:AR, AY:AY, INDIRECT("AE" & ROW()), AP:AP, "📦", AS:AS, "") ) / 2 ) -> 0 | AL21: =( SUMIFS(AR:AR, AY:AY, INDIRECT("AE" & ROW()), AP:AP, "💲") + SUMIFS(AR:AR, AY:AY, INDIRECT("AE" & ROW()), AP:AP, "📦") ) - (( SUMIFS(AR:AR, AY:AY, INDIRECT("AE" & ROW()), AP:AP, "💲", AS:AS, "Familiar") + SUMIFS(AR:AR, AY:AY, INDIRECT("AE" & ROW()), AP:AP, "📦", AS:AS, "Familiar") ) / 2 ) - (( SUMIFS(AR:AR, AY:AY, INDIRECT("AE" & ROW()), AP:AP, "💲", AS:AS, "Participante") + SUMIFS(AR:AR, AY:AY, INDIRECT("AE" & ROW()), AP:AP, "📦", AS:AS, "Participante") ) / 2 ) - (( SUMIFS(AR:AR, AY:AY, INDIRECT("AE" & ROW()), AP:AP, "💲", AS:AS, "Empleado") + SUMIFS(AR:AR, AY:AY, INDIRECT("AE" & ROW()), AP:AP, "📦", AS:AS, "Empleado") ) / 2 ) - (( SUMIFS(AR:AR, AY:AY, INDIRECT("AE" & ROW()), AP:AP, "💲", AS:AS, "Exonerado ADH") + SUMIFS(AR:AR, AY:AY, INDIRECT("AE" & ROW()), AP:AP, "📦", AS:AS, "Exonerado ADH") ) / 2 ) - ( SUMIFS(AR:AR, AY:AY, INDIRECT("AE" & ROW()), AP:AP, "💲", AS:AS, "Exonerado Doctor") + SUMIFS(AR:AR, AY:AY, INDIRECT("AE" & ROW()), AP:AP, "📦", AS:AS, "Exonerado Doctor") )- ( ( SUMIFS(AR:AR, AY:AY, INDIRECT("AE" & ROW()), AP:AP, "💲", AS:AS, "") + SUMIFS(AR:AR, AY:AY, INDIRECT("AE" & ROW()), AP:AP, "📦", AS:AS, "") ) / 2 ) -> 25 | AN21: =A4 -> 46266 | AO21: =G5 -> Consultorio N° 2 | AP21: =G14 -> 🚫 | AQ21: =H14 -> Yolimar Sofia Sayago Mosqueda | AR21: =Y14 -> 0 | AS21: =W14 -> 0 | AT21: =W15 -> 0 | AU21: =Y15 -> 0 | AV21: =W16 -> 0 | AW21: =Y16 -> 0 | AX21: =Y17 -> 0 | AY21: =J17 -> Dra. Mónica Porras
A22: =A18+$Q$13/1440 -> 0.5 | E22: Representante: | F22: =IF(D22<>"", VLOOKUP(D22,'Base de Datos'!$A$2:$D1268,2,FALSE()),"") | I22: Representante: | J22: =IF(H22<>"", VLOOKUP(H22,'Base de Datos'!$A$2:$D1268,2,FALSE()),"") | M22: Representante: | N22: =IF(L22<>"", VLOOKUP(L22,'Base de Datos'!$A$2:$D1268,2,FALSE()),"") | P22: 📦 | Q22: Facturado | T22: Precio: | X22: Precio: | AB22: Precio: | AE22: Dra. Gerlly Mendoza | AG22: =COUNTIFS(AP:AP, "💲", AY:AY, AE22) + COUNTIFS(AP:AP, "📦", AY:AY, AE22) + COUNTIFS(AP:AP, "✅", AY:AY, AE22) -> 0 | AH22: =COUNTIFS(AP:AP, "💲", AY:AY, AE22) + COUNTIFS(AP:AP, "📦", AY:AY, AE22) -> 0 | AI22: =SUMIFS(AR:AR, AY:AY, AE22, AP:AP, "💲") + SUMIFS(AR:AR, AY:AY, AE22, AP:AP, "📦") -> 0 | AJ22: =( SUMIFS(AR:AR, AY:AY, INDIRECT("AE" & ROW()), AP:AP, "💲") + SUMIFS(AR:AR, AY:AY, INDIRECT("AE" & ROW()), AP:AP, "📦") ) - ( SUMIFS(AR:AR, AY:AY, INDIRECT("AE" & ROW()), AP:AP, "💲", AS:AS, "Participante") + SUMIFS(AR:AR, AY:AY, INDIRECT("AE" & ROW()), AP:AP, "📦", AS:AS, "Participante") ) - ( SUMIFS(AR:AR, AY:AY, INDIRECT("AE" & ROW()), AP:AP, "💲", AS:AS, "Empleado") + SUMIFS(AR:AR, AY:AY, INDIRECT("AE" & ROW()), AP:AP, "📦", AS:AS, "Empleado") ) - ( ( SUMIFS(AR:AR, AY:AY, INDIRECT("AE" & ROW()), AP:AP, "💲", AS:AS, "Familiar") + SUMIFS(AR:AR, AY:AY, INDIRECT("AE" & ROW()), AP:AP, "📦", AS:AS, "Familiar") ) / 2 ) - ( ( SUMIFS(AR:AR, AY:AY, INDIRECT("AE" & ROW()), AP:AP, "💲", AS:AS, "Exonerado ADH") + SUMIFS(AR:AR, AY:AY, INDIRECT("AE" & ROW()), AP:AP, "📦", AS:AS, "Exonerado ADH") ) / 2 ) - ( ( SUMIFS(AR:AR, AY:AY, INDIRECT("AE" & ROW()), AP:AP, "💲", AS:AS, "Exonerado Doctor") + SUMIFS(AR:AR, AY:AY, INDIRECT("AE" & ROW()), AP:AP, "📦", AS:AS, "Exonerado Doctor") ) / 2 ) -> 0 | AK22: =( SUMIFS(AR:AR, AY:AY, INDIRECT("AE" & ROW()), AP:AP, "💲") + SUMIFS(AR:AR, AY:AY, INDIRECT("AE" & ROW()), AP:AP, "📦") ) - ( SUMIFS(AR:AR, AY:AY, INDIRECT("AE" & ROW()), AP:AP, "💲", AS:AS, "Familiar") + SUMIFS(AR:AR, AY:AY, INDIRECT("AE" & ROW()), AP:AP, "📦", AS:AS, "Familiar") ) - ( SUMIFS(AR:AR, AY:AY, INDIRECT("AE" & ROW()), AP:AP, "💲", AS:AS, "Participante") + SUMIFS(AR:AR, AY:AY, INDIRECT("AE" & ROW()), AP:AP, "📦", AS:AS, "Participante") ) - ( SUMIFS(AR:AR, AY:AY, INDIRECT("AE" & ROW()), AP:AP, "💲", AS:AS, "Empleado") + SUMIFS(AR:AR, AY:AY, INDIRECT("AE" & ROW()), AP:AP, "📦", AS:AS, "Empleado") ) - ( SUMIFS(AR:AR, AY:AY, INDIRECT("AE" & ROW()), AP:AP, "💲", AS:AS, "Exonerado ADH") + SUMIFS(AR:AR, AY:AY, INDIRECT("AE" & ROW()), AP:AP, "📦", AS:AS, "Exonerado ADH") ) - (( SUMIFS(AR:AR, AY:AY, INDIRECT("AE" & ROW()), AP:AP, "💲", AS:AS, "Exonerado Doctor") + SUMIFS(AR:AR, AY:AY, INDIRECT("AE" & ROW()), AP:AP, "📦", AS:AS, "Exonerado Doctor") ) / 2 )- ( ( SUMIFS(AR:AR, AY:AY, INDIRECT("AE" & ROW()), AP:AP, "💲", AS:AS, "") + SUMIFS(AR:AR, AY:AY, INDIRECT("AE" & ROW()), AP:AP, "📦", AS:AS, "") ) / 2 ) -> 0 | AL22: =( SUMIFS(AR:AR, AY:AY, INDIRECT("AE" & ROW()), AP:AP, "💲") + SUMIFS(AR:AR, AY:AY, INDIRECT("AE" & ROW()), AP:AP, "📦") ) - (( SUMIFS(AR:AR, AY:AY, INDIRECT("AE" & ROW()), AP:AP, "💲", AS:AS, "Familiar") + SUMIFS(AR:AR, AY:AY, INDIRECT("AE" & ROW()), AP:AP, "📦", AS:AS, "Familiar") ) / 2 ) - (( SUMIFS(AR:AR, AY:AY, INDIRECT("AE" & ROW()), AP:AP, "💲", AS:AS, "Participante") + SUMIFS(AR:AR, AY:AY, INDIRECT("AE" & ROW()), AP:AP, "📦", AS:AS, "Participante") ) / 2 ) - (( SUMIFS(AR:AR, AY:AY, INDIRECT("AE" & ROW()), AP:AP, "💲", AS:AS, "Empleado") + SUMIFS(AR:AR, AY:AY, INDIRECT("AE" & ROW()), AP:AP, "📦", AS:AS, "Empleado") ) / 2 ) - (( SUMIFS(AR:AR, AY:AY, INDIRECT("AE" & ROW()), AP:AP, "💲", AS:AS, "Exonerado ADH") + SUMIFS(AR:AR, AY:AY, INDIRECT("AE" & ROW()), AP:AP, "📦", AS:AS, "Exonerado ADH") ) / 2 ) - ( SUMIFS(AR:AR, AY:AY, INDIRECT("AE" & ROW()), AP:AP, "💲", AS:AS, "Exonerado Doctor") + SUMIFS(AR:AR, AY:AY, INDIRECT("AE" & ROW()), AP:AP, "📦", AS:AS, "Exonerado Doctor") )- ( ( SUMIFS(AR:AR, AY:AY, INDIRECT("AE" & ROW()), AP:AP, "💲", AS:AS, "") + SUMIFS(AR:AR, AY:AY, INDIRECT("AE" & ROW()), AP:AP, "📦", AS:AS, "") ) / 2 ) -> 0 | AN22: =A4 -> 46266 | AO22: =G5 -> Consultorio N° 2 | AP22: =G18 -> 0 | AQ22: =H18 -> 0 | AR22: =Y18 -> 0 | AS22: =W18 -> 0 | AT22: =W19 -> 0 | AU22: =Y19 -> 0 | AV22: =W20 -> 0 | AW22: =Y20 -> 0 | AX22: =Y21 -> 0 | AY22: =J21 -> 0
E23: Teléfono: | F23: =IF(D22<>"", VLOOKUP(D22,'Base de Datos'!$A$2:$D1268,3,FALSE()),"") | I23: Teléfono: | J23: =IF(H22<>"", VLOOKUP(H22,'Base de Datos'!$A$2:$D1268,3,FALSE()),"") | M23: Teléfono: | N23: =IF(L22<>"", VLOOKUP(L22,'Base de Datos'!$A$2:$D1268,3,FALSE()),"") | AI23: =SUM(AI9:AI22) -> 2450 | AJ23: =SUM(AJ9:AJ22) -> 1850 | AK23: =SUM(AK9:AK22) -> 1750 | AL23: =SUM(AL9:AL22) -> 2100 | AN23: =A4 -> 46266 | AO23: =G5 -> Consultorio N° 2 | AP23: =G22 -> 0 | AQ23: =H22 -> 0 | AR23: =Y22 -> 0 | AS23: =W22 -> 0 | AT23: =W23 -> 0 | AU23: =Y23 -> 0 | AV23: =W24 -> 0 | AW23: =Y24 -> 0 | AX23: =Y25 -> 0 | AY23: =J25 -> 0
E24: Cedula: | F24: =IF(D22<>"", VLOOKUP(D22,'Base de Datos'!$A$2:$D1268,4,FALSE()),"") | I24: Cedula: | J24: =IF(H22<>"", VLOOKUP(H22,'Base de Datos'!$A$2:$D1268,4,FALSE()),"") | M24: Cedula: | N24: =IF(L22<>"", VLOOKUP(L22,'Base de Datos'!$A$2:$D1268,4,FALSE()),"") | AN24: =A4 -> 46266 | AO24: =G5 -> Consultorio N° 2 | AP24: =G26 -> 0 | AQ24: =H26 -> 0 | AR24: =Y26 -> 0 | AS24: =W26 -> 0 | AT24: =W27 -> 0 | AU24: =Y27 -> 0 | AV24: =W28 -> 0 | AW24: =Y28 -> 0 | AX24: =Y29 -> 0 | AY24: =J29 -> 0
E25: Doctor: | I25: Doctor: | M25: Doctor: | S25: =IF(OR(S22="Empleado",S22="Familiar"),"Nombre del Empleado","N° Factura") -> N° Factura | W25: =IF(OR(W22="Empleado",W22="Familiar"),"Nombre del Empleado","N° Factura") -> N° Factura | AA25: =IF(OR(AA22="Empleado",AA22="Familiar"),"Nombre del Empleado","N° Factura") -> N° Factura | AN25: =A4 -> 46266 | AO25: =G5 -> Consultorio N° 2 | AP25: =G30 -> 0 | AQ25: =H30 -> 0 | AR25: =Y30 -> 0 | AS25: =W30 -> 0 | AT25: =W31 -> 0 | AU25: =Y31 -> 0 | AV25: =W32 -> 0 | AW25: =Y32 -> 0 | AX25: =Y33 -> 0 | AY25: =J33 -> 0
A26: =A22+$Q$13/1440 -> 0.54166667 | E26: Representante: | F26: =IF(D26<>"", VLOOKUP(D26,'Base de Datos'!$A$2:$D1268,2,FALSE()),"") | I26: Representante: | J26: =IF(H26<>"", VLOOKUP(H26,'Base de Datos'!$A$2:$D1268,2,FALSE()),"") | M26: Representante: | N26: =IF(L26<>"", VLOOKUP(L26,'Base de Datos'!$A$2:$D1268,2,FALSE()),"") | T26: Precio: | X26: Precio: | AB26: Precio: | AN26: =A4 -> 46266 | AO26: =G5 -> Consultorio N° 2 | AP26: =G34 -> 0 | AQ26: =H34 -> 0 | AR26: =Y34 -> 0 | AS26: =W34 -> 0 | AT26: =W35 -> 0 | AU26: =Y35 -> 0 | AV26: =W36 -> 0 | AW26: =Y36 -> 0 | AX26: =Y37 -> 0 | AY26: =J37 -> 0
E27: Teléfono: | F27: =IF(D26<>"", VLOOKUP(D26,'Base de Datos'!$A$2:$D1268,3,FALSE()),"") | I27: Teléfono: | J27: =IF(H26<>"", VLOOKUP(H26,'Base de Datos'!$A$2:$D1268,3,FALSE()),"") | M27: Teléfono: | N27: =IF(L26<>"", VLOOKUP(L26,'Base de Datos'!$A$2:$D1268,3,FALSE()),"") | AN27: =A4 -> 46266 | AO27: =G5 -> Consultorio N° 2 | AP27: =G38 -> 0 | AQ27: =H38 -> 0 | AR27: =Y38 -> 0 | AS27: =W38 -> 0 | AT27: =W39 -> 0 | AU27: =Y39 -> 0 | AV27: =W40 -> 0 | AW27: =Y40 -> 0 | AX27: =Y41 -> 0 | AY27: =J41 -> 0
E28: Cedula: | F28: =IF(D26<>"", VLOOKUP(D26,'Base de Datos'!$A$2:$D1268,4,FALSE()),"") | I28: Cedula: | J28: =IF(H26<>"", VLOOKUP(H26,'Base de Datos'!$A$2:$D1268,4,FALSE()),"") | M28: Cedula: | N28: =IF(L26<>"", VLOOKUP(L26,'Base de Datos'!$A$2:$D1268,4,FALSE()),"") | AN28: =A4 -> 46266 | AO28: =G5 -> Consultorio N° 2 | AP28: =G42 -> 0 | AQ28: =H42 -> 0 | AR28: =Y42 -> 0 | AS28: =W42 -> 0 | AT28: =W43 -> 0 | AU28: =Y43 -> 0 | AV28: =W44 -> 0 | AW28: =Y44 -> 0 | AX28: =Y45 -> 0 | AY28: =J45 -> 0
E29: Doctor: | I29: Doctor: | M29: Doctor: | S29: =IF(OR(S26="Empleado",S26="Familiar"),"Nombre del Empleado","N° Factura") -> N° Factura | W29: =IF(OR(W26="Empleado",W26="Familiar"),"Nombre del Empleado","N° Factura") -> N° Factura | AA29: =IF(OR(AA26="Empleado",AA26="Familiar"),"Nombre del Empleado","N° Factura") -> N° Factura | AN29: =A4 -> 46266 | AO29: =K5 -> Consultorio N° 3 | AP29: =K6 -> 0 | AQ29: =L6 -> 0 | AR29: =AC6 -> 0 | AS29: =AA6 -> 0 | AT29: =AA7 -> 0 | AU29: =AC7 -> 0 | AV29: =AA8 -> 0 | AW29: =AC8 -> 0 | AX29: =AC9 -> 0 | AY29: =N9 -> 0
A30: =A26+$Q$13/1440 -> 0.58333333 | E30: Representante: | F30: =IF(D30<>"", VLOOKUP(D30,'Base de Datos'!$A$2:$D1268,2,FALSE()),"") | I30: Representante: | J30: =IF(H30<>"", VLOOKUP(H30,'Base de Datos'!$A$2:$D1268,2,FALSE()),"") | M30: Representante: | N30: =IF(L30<>"", VLOOKUP(L30,'Base de Datos'!$A$2:$D1268,2,FALSE()),"") | T30: Precio: | X30: Precio: | AB30: Precio: | AN30: =A4 -> 46266 | AO30: =K5 -> Consultorio N° 3 | AP30: =K10 -> 0 | AQ30: =L10 -> 0 | AR30: =AC10 -> 0 | AS30: =AA10 -> 0 | AT30: =AA11 -> 0 | AU30: =AC11 -> 0 | AV30: =AA12 -> 0 | AW30: =AC12 -> 0 | AX30: =AC13 -> 0 | AY30: =N13 -> 0
E31: Teléfono: | F31: =IF(D30<>"", VLOOKUP(D30,'Base de Datos'!$A$2:$D1268,3,FALSE()),"") | I31: Teléfono: | J31: =IF(H30<>"", VLOOKUP(H30,'Base de Datos'!$A$2:$D1268,3,FALSE()),"") | M31: Teléfono: | N31: =IF(L30<>"", VLOOKUP(L30,'Base de Datos'!$A$2:$D1268,3,FALSE()),"") | AN31: =A4 -> 46266 | AO31: =K5 -> Consultorio N° 3 | AP31: =K14 -> 0 | AQ31: =L14 -> 0 | AR31: =AC14 -> 0 | AS31: =AA14 -> 0 | AT31: =AA15 -> 0 | AU31: =AC15 -> 0 | AV31: =AA16 -> 0 | AW31: =AC16 -> 0 | AX31: =AC17 -> 0 | AY31: =N17 -> 0
E32: Cedula: | F32: =IF(D30<>"", VLOOKUP(D30,'Base de Datos'!$A$2:$D1268,4,FALSE()),"") | I32: Cedula: | J32: =IF(H30<>"", VLOOKUP(H30,'Base de Datos'!$A$2:$D1268,4,FALSE()),"") | M32: Cedula: | N32: =IF(L30<>"", VLOOKUP(L30,'Base de Datos'!$A$2:$D1268,4,FALSE()),"") | AN32: =A4 -> 46266 | AO32: =K5 -> Consultorio N° 3 | AP32: =K18 -> 0 | AQ32: =L18 -> 0 | AR32: =AC18 -> 0 | AS32: =AA18 -> 0 | AT32: =AA19 -> 0 | AU32: =AC19 -> 0 | AV32: =AA20 -> 0 | AW32: =AC20 -> 0 | AX32: =AC21 -> 0 | AY32: =N21 -> 0
E33: Doctor: | I33: Doctor: | M33: Doctor: | S33: =IF(OR(S30="Empleado",S30="Familiar"),"Nombre del Empleado","N° Factura") -> N° Factura | W33: =IF(OR(W30="Empleado",W30="Familiar"),"Nombre del Empleado","N° Factura") -> N° Factura | AA33: =IF(OR(AA30="Empleado",AA30="Familiar"),"Nombre del Empleado","N° Factura") -> N° Factura | AN33: =A4 -> 46266 | AO33: =K5 -> Consultorio N° 3 | AP33: =K22 -> 0 | AQ33: =L22 -> 0 | AR33: =AC22 -> 0 | AS33: =AA22 -> 0 | AT33: =AA23 -> 0 | AU33: =AC23 -> 0 | AV33: =AA24 -> 0 | AW33: =AC24 -> 0 | AX33: =AC25 -> 0 | AY33: =N25 -> 0
A34: =A30+$Q$13/1440 -> 0.625 | E34: Representante: | F34: =IF(D34<>"", VLOOKUP(D34,'Base de Datos'!$A$2:$D1268,2,FALSE()),"") | I34: Representante: | J34: =IF(H34<>"", VLOOKUP(H34,'Base de Datos'!$A$2:$D1268,2,FALSE()),"") | M34: Representante: | N34: =IF(L34<>"", VLOOKUP(L34,'Base de Datos'!$A$2:$D1268,2,FALSE()),"") | T34: Precio: | X34: Precio: | AB34: Precio: | AN34: =A4 -> 46266 | AO34: =K5 -> Consultorio N° 3 | AP34: =K26 -> 0 | AQ34: =L26 -> 0 | AR34: =AC26 -> 0 | AS34: =AA26 -> 0 | AT34: =AA27 -> 0 | AU34: =AC27 -> 0 | AV34: =AA28 -> 0 | AW34: =AC28 -> 0 | AX34: =AC29 -> 0 | AY34: =N29 -> 0
E35: Teléfono: | F35: =IF(D34<>"", VLOOKUP(D34,'Base de Datos'!$A$2:$D1268,3,FALSE()),"") | I35: Teléfono: | J35: =IF(H34<>"", VLOOKUP(H34,'Base de Datos'!$A$2:$D1268,3,FALSE()),"") | M35: Teléfono: | N35: =IF(L34<>"", VLOOKUP(L34,'Base de Datos'!$A$2:$D1268,3,FALSE()),"") | AN35: =A4 -> 46266 | AO35: =K5 -> Consultorio N° 3 | AP35: =K30 -> 0 | AQ35: =L30 -> 0 | AR35: =AC30 -> 0 | AS35: =AA30 -> 0 | AT35: =AA31 -> 0 | AU35: =AC31 -> 0 | AV35: =AA32 -> 0 | AW35: =AC32 -> 0 | AX35: =AC33 -> 0 | AY35: =N33 -> 0
E36: Cedula: | F36: =IF(D34<>"", VLOOKUP(D34,'Base de Datos'!$A$2:$D1268,4,FALSE()),"") | I36: Cedula: | J36: =IF(H34<>"", VLOOKUP(H34,'Base de Datos'!$A$2:$D1268,4,FALSE()),"") | M36: Cedula: | N36: =IF(L34<>"", VLOOKUP(L34,'Base de Datos'!$A$2:$D1268,4,FALSE()),"") | AN36: =A4 -> 46266 | AO36: =K5 -> Consultorio N° 3 | AP36: =K34 -> 0 | AQ36: =L34 -> 0 | AR36: =AC34 -> 0 | AS36: =AA34 -> 0 | AT36: =AA35 -> 0 | AU36: =AC35 -> 0 | AV36: =AA36 -> 0 | AW36: =AC36 -> 0 | AX36: =AC37 -> 0 | AY36: =N37 -> 0
E37: Doctor: | I37: Doctor: | M37: Doctor: | S37: =IF(OR(S34="Empleado",S34="Familiar"),"Nombre del Empleado","N° Factura") -> N° Factura | W37: =IF(OR(W34="Empleado",W34="Familiar"),"Nombre del Empleado","N° Factura") -> N° Factura | AA37: =IF(OR(AA34="Empleado",AA34="Familiar"),"Nombre del Empleado","N° Factura") -> N° Factura | AN37: =A4 -> 46266 | AO37: =K5 -> Consultorio N° 3 | AP37: =K38 -> 0 | AQ37: =L38 -> 0 | AR37: =AC38 -> 0 | AS37: =AA38 -> 0 | AT37: =AA39 -> 0 | AU37: =AC39 -> 0 | AV37: =AA40 -> 0 | AW37: =AC40 -> 0 | AX37: =AC41 -> 0 | AY37: =N41 -> 0
A38: =A34+$Q$13/1440 -> 0.66666667 | E38: Representante: | F38: =IF(D38<>"", VLOOKUP(D38,'Base de Datos'!$A$2:$D1268,2,FALSE()),"") | I38: Representante: | J38: =IF(H38<>"", VLOOKUP(H38,'Base de Datos'!$A$2:$D1268,2,FALSE()),"") | M38: Representante: | N38: =IF(L38<>"", VLOOKUP(L38,'Base de Datos'!$A$2:$D1268,2,FALSE()),"") | T38: Precio: | X38: Precio: | AB38: Precio: | AN38: =A4 -> 46266 | AO38: =K5 -> Consultorio N° 3 | AP38: =K42 -> 0 | AQ38: =L42 -> 0 | AR38: =AC42 -> 0 | AS38: =AA42 -> 0 | AT38: =AA43 -> 0 | AU38: =AC43 -> 0 | AV38: =AA44 -> 0 | AW38: =AC44 -> 0 | AX38: =AC45 -> 0 | AY38: =N45 -> 0
E39: Teléfono: | F39: =IF(D38<>"", VLOOKUP(D38,'Base de Datos'!$A$2:$D1268,3,FALSE()),"") | I39: Teléfono: | J39: =IF(H38<>"", VLOOKUP(H38,'Base de Datos'!$A$2:$D1268,3,FALSE()),"") | M39: Teléfono: | N39: =IF(L38<>"", VLOOKUP(L38,'Base de Datos'!$A$2:$D1268,3,FALSE()),"") | AE39: =A4 -> 46266 | AN39: =A4 -> 46266 | AO39: =K5 -> Consultorio N° 3 | AP39: =K46 -> 0 | AQ39: =L46 -> 0 | AR39: =AC46 -> 0 | AS39: =AA46 -> 0 | AT39: =AA47 -> 0 | AU39: =AC47 -> 0 | AV39: =AA48 -> 0 | AW39: =AC48 -> 0 | AX39: =AC49 -> 0 | AY39: =N49 -> 0
E40: Cedula: | F40: =IF(D38<>"", VLOOKUP(D38,'Base de Datos'!$A$2:$D1268,4,FALSE()),"") | I40: Cedula: | J40: =IF(H38<>"", VLOOKUP(H38,'Base de Datos'!$A$2:$D1268,4,FALSE()),"") | M40: Cedula: | N40: =IF(L38<>"", VLOOKUP(L38,'Base de Datos'!$A$2:$D1268,4,FALSE()),"") | AE40: Doctor | AG40: Cantidad citas | AH40: Citas pagadas | AI40: Total | AJ40: Monto Cobrado | AK40: Monto ADH | AL40: Monto Médico | AN40: =A4 -> 46266 | AO40: =K5 -> Consultorio N° 3 | AP40: =K50 -> 0 | AQ40: =L50 -> 0 | AR40: =AC50 -> 0 | AS40: =AA50 -> 0 | AT40: =AA51 -> 0 | AU40: =AC51 -> 0 | AV40: =AA52 -> 0 | AW40: =AC52 -> 0 | AX40: =AC53 -> 0 | AY40: =N53 -> 0
E41: Doctor: | I41: Doctor: | M41: Doctor: | S41: =IF(OR(S38="Empleado",S38="Familiar"),"Nombre del Empleado","N° Factura") -> N° Factura | W41: =IF(OR(W38="Empleado",W38="Familiar"),"Nombre del Empleado","N° Factura") -> N° Factura | AA41: =IF(OR(AA38="Empleado",AA38="Familiar"),"Nombre del Empleado","N° Factura") -> N° Factura | AE41: Dra. Rosanny García | AG41: {=COUNTIFS(AP6:AP46, "💲", AY6:AY46, INDIRECT("AE" & ROW())) + COUNTIFS(AP6:AP46, "📦", AY6:AY46, INDIRECT("AE" & ROW())) + COUNTIFS(AP6:AP46, "✅", AY6:AY46, INDIRECT("AE" & ROW()))} -> 0 | AH41: {=COUNTIFS(AP6:AP46, "💲", AY6:AY46, INDIRECT("AE" & ROW())) + COUNTIFS(AP6:AP46, "📦", AY6:AY46, INDIRECT("AE" & ROW()))} -> 0 | AI41: {=SUMIFS(AR6:AR46, AY6:AY46, INDIRECT("AE" & ROW()), AP6:AP46, "💲") + SUMIFS(AR6:AR46, AY6:AY46, INDIRECT("AE" & ROW()), AP6:AP46, "📦")} -> 0 | AJ41: {=( SUMIFS(AR6:AR46, AY6:AY46, INDIRECT("AE" & ROW()), AP6:AP46, "💲") + SUMIFS(AR6:AR46, AY6:AY46, INDIRECT("AE" & ROW()), AP6:AP46, "📦") ) - ( SUMIFS(AR6:AR46, AY6:AY46, INDIRECT("AE" & ROW()), AP6:AP46, "💲", AS6:AS46, "Participante") + SUMIFS(AR6:AR46, AY6:AY46, INDIRECT("AE" & ROW()), AP6:AP46, "📦", AS6:AS46, "Participante") ) - ( SUMIFS(AR6:AR46, AY6:AY46, INDIRECT("AE" & ROW()), AP6:AP46, "💲", AS6:AS46, "Empleado") + SUMIFS(AR6:AR46, AY6:AY46, INDIRECT("AE" & ROW()), AP6:AP46, "📦", AS6:AS46, "Empleado") ) - ( ( SUMIFS(AR6:AR46, AY6:AY46, INDIRECT("AE" & ROW()), AP6:AP46, "💲", AS6:AS46, "Familiar") + SUMIFS(AR6:AR46, AY6:AY46, INDIRECT("AE" & ROW()), AP6:AP46, "📦", AS6:AS46, "Familiar") ) / 2 ) - ( ( SUMIFS(AR6:AR46, AY6:AY46, INDIRECT("AE" & ROW()), AP6:AP46, "💲", AS6:AS46, "Exonerado ADH") + SUMIFS(AR6:AR46, AY6:AY46, INDIRECT("AE" & ROW()), AP6:AP46, "📦", AS6:AS46, "Exonerado ADH") ) / 2 ) - ( ( SUMIFS(AR6:AR46, AY6:AY46, INDIRECT("AE" & ROW()), AP6:AP46, "💲", AS6:AS46, "Exonerado Doctor") + SUMIFS(AR6:AR46, AY6:AY46, INDIRECT("AE" & ROW()), AP6:AP46, "📦", AS6:AS46, "Exonerado Doctor") ) / 2 )} -> 0 | AK41: {=( SUMIFS(AR6:AR46, AY6:AY46, INDIRECT("AE" & ROW()), AP6:AP46, "💲") + SUMIFS(AR6:AR46, AY6:AY46, INDIRECT("AE" & ROW()), AP6:AP46, "📦") ) - ( SUMIFS(AR6:AR46, AY6:AY46, INDIRECT("AE" & ROW()), AP6:AP46, "💲", AS6:AS46, "Familiar") + SUMIFS(AR6:AR46, AY6:AY46, INDIRECT("AE" & ROW()), AP6:AP46, "📦", AS6:AS46, "Familiar") ) - ( SUMIFS(AR6:AR46, AY6:AY46, INDIRECT("AE" & ROW()), AP6:AP46, "💲", AS6:AS46, "Participante") + SUMIFS(AR6:AR46, AY6:AY46, INDIRECT("AE" & ROW()), AP6:AP46, "📦", AS6:AS46, "Participante") ) - ( SUMIFS(AR6:AR46, AY6:AY46, INDIRECT("AE" & ROW()), AP6:AP46, "💲", AS6:AS46, "Empleado") + SUMIFS(AR6:AR46, AY6:AY46, INDIRECT("AE" & ROW()), AP6:AP46, "📦", AS6:AS46, "Empleado") ) - ( SUMIFS(AR6:AR46, AY6:AY46, INDIRECT("AE" & ROW()), AP6:AP46, "💲", AS6:AS46, "Exonerado ADH") + SUMIFS(AR6:AR46, AY6:AY46, INDIRECT("AE" & ROW()), AP6:AP46, "📦", AS6:AS46, "Exonerado ADH") ) - ( ( SUMIFS(AR6:AR46, AY6:AY46, INDIRECT("AE" & ROW()), AP6:AP46, "💲", AS6:AS46, "Exonerado Doctor") + SUMIFS(AR6:AR46, AY6:AY46, INDIRECT("AE" & ROW()), AP6:AP46, "📦", AS6:AS46, "Exonerado Doctor") ) / 2 ) - ( ( SUMIFS(AR6:AR46, AY6:AY46, INDIRECT("AE" & ROW()), AP6:AP46, "💲", AS6:AS46, "") + SUMIFS(AR6:AR46, AY6:AY46, INDIRECT("AE" & ROW()), AP6:AP46, "📦", AS6:AS46, "") ) / 2 )} -> 0 | AL41: {=( SUMIFS(AR6:AR46, AY6:AY46, INDIRECT("AE" & ROW()), AP6:AP46, "💲") + SUMIFS(AR6:AR46, AY6:AY46, INDIRECT("AE" & ROW()), AP6:AP46, "📦") ) - ( ( SUMIFS(AR6:AR46, AY6:AY46, INDIRECT("AE" & ROW()), AP6:AP46, "💲", AS6:AS46, "Familiar") + SUMIFS(AR6:AR46, AY6:AY46, INDIRECT("AE" & ROW()), AP6:AP46, "📦", AS6:AS46, "Familiar") ) / 2 ) - ( ( SUMIFS(AR6:AR46, AY6:AY46, INDIRECT("AE" & ROW()), AP6:AP46, "💲", AS6:AS46, "Participante") + SUMIFS(AR6:AR46, AY6:AY46, INDIRECT("AE" & ROW()), AP6:AP46, "📦", AS6:AS46, "Participante") ) / 2 ) - ( ( SUMIFS(AR6:AR46, AY6:AY46, INDIRECT("AE" & ROW()), AP6:AP46, "💲", AS6:AS46, "Empleado") + SUMIFS(AR6:AR46, AY6:AY46, INDIRECT("AE" & ROW()), AP6:AP46, "📦", AS6:AS46, "Empleado") ) / 2 ) - ( ( SUMIFS(AR6:AR46, AY6:AY46, INDIRECT("AE" & ROW()), AP6:AP46, "💲", AS6:AS46, "Exonerado ADH") + SUMIFS(AR6:AR46, AY6:AY46, INDIRECT("AE" & ROW()), AP6:AP46, "📦", AS6:AS46, "Exonerado ADH") ) / 2 ) - ( SUMIFS(AR6:AR46, AY6:AY46, INDIRECT("AE" & ROW()), AP6:AP46, "💲", AS6:AS46, "Exonerado Doctor") + SUMIFS(AR6:AR46, AY6:AY46, INDIRECT("AE" & ROW()), AP6:AP46, "📦", AS6:AS46, "Exonerado Doctor") ) - ( ( SUMIFS(AR6:AR46, AY6:AY46, INDIRECT("AE" & ROW()), AP6:AP46, "💲", AS6:AS46, "") + SUMIFS(AR6:AR46, AY6:AY46, INDIRECT("AE" & ROW()), AP6:AP46, "📦", AS6:AS46, "") ) / 2 )} -> 0 | AN41: =A4 -> 46266 | AO41: =K5 -> Consultorio N° 3 | AP41: =K54 -> 0 | AQ41: =L54 -> 0 | AR41: =AC54 -> 0 | AS41: =AA54 -> 0 | AT41: =AA55 -> 0 | AU41: =AC55 -> 0 | AV41: =AA56 -> 0 | AW41: =AC56 -> 0 | AX41: =AC57 -> 0 | AY41: =N57 -> 0
A42: =A38+$Q$13/1440 -> 0.70833333 | E42: Representante: | F42: =IF(D42<>"", VLOOKUP(D42,'Base de Datos'!$A$2:$D1268,2,FALSE()),"") | I42: Representante: | J42: =IF(H42<>"", VLOOKUP(H42,'Base de Datos'!$A$2:$D1268,2,FALSE()),"") | M42: Representante: | N42: =IF(L42<>"", VLOOKUP(L42,'Base de Datos'!$A$2:$D1268,2,FALSE()),"") | T42: Precio: | X42: Precio: | AB42: Precio: | AE42: Dra. Maribel Guilarte | AG42: {=COUNTIFS(AP6:AP46, "💲", AY6:AY46, INDIRECT("AE" & ROW())) + COUNTIFS(AP6:AP46, "📦", AY6:AY46, INDIRECT("AE" & ROW())) + COUNTIFS(AP6:AP46, "✅", AY6:AY46, INDIRECT("AE" & ROW()))} -> 0 | AH42: {=COUNTIFS(AP6:AP46, "💲", AY6:AY46, INDIRECT("AE" & ROW())) + COUNTIFS(AP6:AP46, "📦", AY6:AY46, INDIRECT("AE" & ROW()))} -> 0 | AI42: {=SUMIFS(AR6:AR46, AY6:AY46, INDIRECT("AE" & ROW()), AP6:AP46, "💲") + SUMIFS(AR6:AR46, AY6:AY46, INDIRECT("AE" & ROW()), AP6:AP46, "📦")} -> 0 | AJ42: {=( SUMIFS(AR6:AR46, AY6:AY46, INDIRECT("AE" & ROW()), AP6:AP46, "💲") + SUMIFS(AR6:AR46, AY6:AY46, INDIRECT("AE" & ROW()), AP6:AP46, "📦") ) - ( SUMIFS(AR6:AR46, AY6:AY46, INDIRECT("AE" & ROW()), AP6:AP46, "💲", AS6:AS46, "Participante") + SUMIFS(AR6:AR46, AY6:AY46, INDIRECT("AE" & ROW()), AP6:AP46, "📦", AS6:AS46, "Participante") ) - ( SUMIFS(AR6:AR46, AY6:AY46, INDIRECT("AE" & ROW()), AP6:AP46, "💲", AS6:AS46, "Empleado") + SUMIFS(AR6:AR46, AY6:AY46, INDIRECT("AE" & ROW()), AP6:AP46, "📦", AS6:AS46, "Empleado") ) - ( ( SUMIFS(AR6:AR46, AY6:AY46, INDIRECT("AE" & ROW()), AP6:AP46, "💲", AS6:AS46, "Familiar") + SUMIFS(AR6:AR46, AY6:AY46, INDIRECT("AE" & ROW()), AP6:AP46, "📦", AS6:AS46, "Familiar") ) / 2 ) - ( ( SUMIFS(AR6:AR46, AY6:AY46, INDIRECT("AE" & ROW()), AP6:AP46, "💲", AS6:AS46, "Exonerado ADH") + SUMIFS(AR6:AR46, AY6:AY46, INDIRECT("AE" & ROW()), AP6:AP46, "📦", AS6:AS46, "Exonerado ADH") ) / 2 ) - ( ( SUMIFS(AR6:AR46, AY6:AY46, INDIRECT("AE" & ROW()), AP6:AP46, "💲", AS6:AS46, "Exonerado Doctor") + SUMIFS(AR6:AR46, AY6:AY46, INDIRECT("AE" & ROW()), AP6:AP46, "📦", AS6:AS46, "Exonerado Doctor") ) / 2 )} -> 0 | AK42: {=( SUMIFS(AR6:AR46, AY6:AY46, INDIRECT("AE" & ROW()), AP6:AP46, "💲") + SUMIFS(AR6:AR46, AY6:AY46, INDIRECT("AE" & ROW()), AP6:AP46, "📦") ) - ( SUMIFS(AR6:AR46, AY6:AY46, INDIRECT("AE" & ROW()), AP6:AP46, "💲", AS6:AS46, "Familiar") + SUMIFS(AR6:AR46, AY6:AY46, INDIRECT("AE" & ROW()), AP6:AP46, "📦", AS6:AS46, "Familiar") ) - ( SUMIFS(AR6:AR46, AY6:AY46, INDIRECT("AE" & ROW()), AP6:AP46, "💲", AS6:AS46, "Participante") + SUMIFS(AR6:AR46, AY6:AY46, INDIRECT("AE" & ROW()), AP6:AP46, "📦", AS6:AS46, "Participante") ) - ( SUMIFS(AR6:AR46, AY6:AY46, INDIRECT("AE" & ROW()), AP6:AP46, "💲", AS6:AS46, "Empleado") + SUMIFS(AR6:AR46, AY6:AY46, INDIRECT("AE" & ROW()), AP6:AP46, "📦", AS6:AS46, "Empleado") ) - ( SUMIFS(AR6:AR46, AY6:AY46, INDIRECT("AE" & ROW()), AP6:AP46, "💲", AS6:AS46, "Exonerado ADH") + SUMIFS(AR6:AR46, AY6:AY46, INDIRECT("AE" & ROW()), AP6:AP46, "📦", AS6:AS46, "Exonerado ADH") ) - ( ( SUMIFS(AR6:AR46, AY6:AY46, INDIRECT("AE" & ROW()), AP6:AP46, "💲", AS6:AS46, "Exonerado Doctor") + SUMIFS(AR6:AR46, AY6:AY46, INDIRECT("AE" & ROW()), AP6:AP46, "📦", AS6:AS46, "Exonerado Doctor") ) / 2 ) - ( ( SUMIFS(AR6:AR46, AY6:AY46, INDIRECT("AE" & ROW()), AP6:AP46, "💲", AS6:AS46, "") + SUMIFS(AR6:AR46, AY6:AY46, INDIRECT("AE" & ROW()), AP6:AP46, "📦", AS6:AS46, "") ) / 2 )} -> 0 | AL42: {=( SUMIFS(AR6:AR46, AY6:AY46, INDIRECT("AE" & ROW()), AP6:AP46, "💲") + SUMIFS(AR6:AR46, AY6:AY46, INDIRECT("AE" & ROW()), AP6:AP46, "📦") ) - ( ( SUMIFS(AR6:AR46, AY6:AY46, INDIRECT("AE" & ROW()), AP6:AP46, "💲", AS6:AS46, "Familiar") + SUMIFS(AR6:AR46, AY6:AY46, INDIRECT("AE" & ROW()), AP6:AP46, "📦", AS6:AS46, "Familiar") ) / 2 ) - ( ( SUMIFS(AR6:AR46, AY6:AY46, INDIRECT("AE" & ROW()), AP6:AP46, "💲", AS6:AS46, "Participante") + SUMIFS(AR6:AR46, AY6:AY46, INDIRECT("AE" & ROW()), AP6:AP46, "📦", AS6:AS46, "Participante") ) / 2 ) - ( ( SUMIFS(AR6:AR46, AY6:AY46, INDIRECT("AE" & ROW()), AP6:AP46, "💲", AS6:AS46, "Empleado") + SUMIFS(AR6:AR46, AY6:AY46, INDIRECT("AE" & ROW()), AP6:AP46, "📦", AS6:AS46, "Empleado") ) / 2 ) - ( ( SUMIFS(AR6:AR46, AY6:AY46, INDIRECT("AE" & ROW()), AP6:AP46, "💲", AS6:AS46, "Exonerado ADH") + SUMIFS(AR6:AR46, AY6:AY46, INDIRECT("AE" & ROW()), AP6:AP46, "📦", AS6:AS46, "Exonerado ADH") ) / 2 ) - ( SUMIFS(AR6:AR46, AY6:AY46, INDIRECT("AE" & ROW()), AP6:AP46, "💲", AS6:AS46, "Exonerado Doctor") + SUMIFS(AR6:AR46, AY6:AY46, INDIRECT("AE" & ROW()), AP6:AP46, "📦", AS6:AS46, "Exonerado Doctor") ) - ( ( SUMIFS(AR6:AR46, AY6:AY46, INDIRECT("AE" & ROW()), AP6:AP46, "💲", AS6:AS46, "") + SUMIFS(AR6:AR46, AY6:AY46, INDIRECT("AE" & ROW()), AP6:AP46, "📦", AS6:AS46, "") ) / 2 )} -> 0 | AQ42: =L50 -> 0 | AY42: =N45 -> 0
E43: Teléfono: | F43: =IF(D42<>"", VLOOKUP(D42,'Base de Datos'!$A$2:$D1268,3,FALSE()),"") | I43: Teléfono: | J43: =IF(H42<>"", VLOOKUP(H42,'Base de Datos'!$A$2:$D1268,3,FALSE()),"") | M43: Teléfono: | N43: =IF(L42<>"", VLOOKUP(L42,'Base de Datos'!$A$2:$D1268,3,FALSE()),"") | AE43: Dra. Lyl Belisario | AG43: {=COUNTIFS(AP6:AP46, "💲", AY6:AY46, INDIRECT("AE" & ROW())) + COUNTIFS(AP6:AP46, "📦", AY6:AY46, INDIRECT("AE" & ROW())) + COUNTIFS(AP6:AP46, "✅", AY6:AY46, INDIRECT("AE" & ROW()))} -> 0 | AH43: {=COUNTIFS(AP6:AP46, "💲", AY6:AY46, INDIRECT("AE" & ROW())) + COUNTIFS(AP6:AP46, "📦", AY6:AY46, INDIRECT("AE" & ROW()))} -> 0 | AI43: {=SUMIFS(AR6:AR46, AY6:AY46, INDIRECT("AE" & ROW()), AP6:AP46, "💲") + SUMIFS(AR6:AR46, AY6:AY46, INDIRECT("AE" & ROW()), AP6:AP46, "📦")} -> 0 | AJ43: {=( SUMIFS(AR6:AR46, AY6:AY46, INDIRECT("AE" & ROW()), AP6:AP46, "💲") + SUMIFS(AR6:AR46, AY6:AY46, INDIRECT("AE" & ROW()), AP6:AP46, "📦") ) - ( SUMIFS(AR6:AR46, AY6:AY46, INDIRECT("AE" & ROW()), AP6:AP46, "💲", AS6:AS46, "Participante") + SUMIFS(AR6:AR46, AY6:AY46, INDIRECT("AE" & ROW()), AP6:AP46, "📦", AS6:AS46, "Participante") ) - ( SUMIFS(AR6:AR46, AY6:AY46, INDIRECT("AE" & ROW()), AP6:AP46, "💲", AS6:AS46, "Empleado") + SUMIFS(AR6:AR46, AY6:AY46, INDIRECT("AE" & ROW()), AP6:AP46, "📦", AS6:AS46, "Empleado") ) - ( ( SUMIFS(AR6:AR46, AY6:AY46, INDIRECT("AE" & ROW()), AP6:AP46, "💲", AS6:AS46, "Familiar") + SUMIFS(AR6:AR46, AY6:AY46, INDIRECT("AE" & ROW()), AP6:AP46, "📦", AS6:AS46, "Familiar") ) / 2 ) - ( ( SUMIFS(AR6:AR46, AY6:AY46, INDIRECT("AE" & ROW()), AP6:AP46, "💲", AS6:AS46, "Exonerado ADH") + SUMIFS(AR6:AR46, AY6:AY46, INDIRECT("AE" & ROW()), AP6:AP46, "📦", AS6:AS46, "Exonerado ADH") ) / 2 ) - ( ( SUMIFS(AR6:AR46, AY6:AY46, INDIRECT("AE" & ROW()), AP6:AP46, "💲", AS6:AS46, "Exonerado Doctor") + SUMIFS(AR6:AR46, AY6:AY46, INDIRECT("AE" & ROW()), AP6:AP46, "📦", AS6:AS46, "Exonerado Doctor") ) / 2 )} -> 0 | AK43: {=( SUMIFS(AR6:AR46, AY6:AY46, INDIRECT("AE" & ROW()), AP6:AP46, "💲") + SUMIFS(AR6:AR46, AY6:AY46, INDIRECT("AE" & ROW()), AP6:AP46, "📦") ) - ( SUMIFS(AR6:AR46, AY6:AY46, INDIRECT("AE" & ROW()), AP6:AP46, "💲", AS6:AS46, "Familiar") + SUMIFS(AR6:AR46, AY6:AY46, INDIRECT("AE" & ROW()), AP6:AP46, "📦", AS6:AS46, "Familiar") ) - ( SUMIFS(AR6:AR46, AY6:AY46, INDIRECT("AE" & ROW()), AP6:AP46, "💲", AS6:AS46, "Participante") + SUMIFS(AR6:AR46, AY6:AY46, INDIRECT("AE" & ROW()), AP6:AP46, "📦", AS6:AS46, "Participante") ) - ( SUMIFS(AR6:AR46, AY6:AY46, INDIRECT("AE" & ROW()), AP6:AP46, "💲", AS6:AS46, "Empleado") + SUMIFS(AR6:AR46, AY6:AY46, INDIRECT("AE" & ROW()), AP6:AP46, "📦", AS6:AS46, "Empleado") ) - ( SUMIFS(AR6:AR46, AY6:AY46, INDIRECT("AE" & ROW()), AP6:AP46, "💲", AS6:AS46, "Exonerado ADH") + SUMIFS(AR6:AR46, AY6:AY46, INDIRECT("AE" & ROW()), AP6:AP46, "📦", AS6:AS46, "Exonerado ADH") ) - ( ( SUMIFS(AR6:AR46, AY6:AY46, INDIRECT("AE" & ROW()), AP6:AP46, "💲", AS6:AS46, "Exonerado Doctor") + SUMIFS(AR6:AR46, AY6:AY46, INDIRECT("AE" & ROW()), AP6:AP46, "📦", AS6:AS46, "Exonerado Doctor") ) / 2 ) - ( ( SUMIFS(AR6:AR46, AY6:AY46, INDIRECT("AE" & ROW()), AP6:AP46, "💲", AS6:AS46, "") + SUMIFS(AR6:AR46, AY6:AY46, INDIRECT("AE" & ROW()), AP6:AP46, "📦", AS6:AS46, "") ) / 2 )} -> 0 | AL43: {=( SUMIFS(AR6:AR46, AY6:AY46, INDIRECT("AE" & ROW()), AP6:AP46, "💲") + SUMIFS(AR6:AR46, AY6:AY46, INDIRECT("AE" & ROW()), AP6:AP46, "📦") ) - ( ( SUMIFS(AR6:AR46, AY6:AY46, INDIRECT("AE" & ROW()), AP6:AP46, "💲", AS6:AS46, "Familiar") + SUMIFS(AR6:AR46, AY6:AY46, INDIRECT("AE" & ROW()), AP6:AP46, "📦", AS6:AS46, "Familiar") ) / 2 ) - ( ( SUMIFS(AR6:AR46, AY6:AY46, INDIRECT("AE" & ROW()), AP6:AP46, "💲", AS6:AS46, "Participante") + SUMIFS(AR6:AR46, AY6:AY46, INDIRECT("AE" & ROW()), AP6:AP46, "📦", AS6:AS46, "Participante") ) / 2 ) - ( ( SUMIFS(AR6:AR46, AY6:AY46, INDIRECT("AE" & ROW()), AP6:AP46, "💲", AS6:AS46, "Empleado") + SUMIFS(AR6:AR46, AY6:AY46, INDIRECT("AE" & ROW()), AP6:AP46, "📦", AS6:AS46, "Empleado") ) / 2 ) - ( ( SUMIFS(AR6:AR46, AY6:AY46, INDIRECT("AE" & ROW()), AP6:AP46, "💲", AS6:AS46, "Exonerado ADH") + SUMIFS(AR6:AR46, AY6:AY46, INDIRECT("AE" & ROW()), AP6:AP46, "📦", AS6:AS46, "Exonerado ADH") ) / 2 ) - ( SUMIFS(AR6:AR46, AY6:AY46, INDIRECT("AE" & ROW()), AP6:AP46, "💲", AS6:AS46, "Exonerado Doctor") + SUMIFS(AR6:AR46, AY6:AY46, INDIRECT("AE" & ROW()), AP6:AP46, "📦", AS6:AS46, "Exonerado Doctor") ) - ( ( SUMIFS(AR6:AR46, AY6:AY46, INDIRECT("AE" & ROW()), AP6:AP46, "💲", AS6:AS46, "") + SUMIFS(AR6:AR46, AY6:AY46, INDIRECT("AE" & ROW()), AP6:AP46, "📦", AS6:AS46, "") ) / 2 )} -> 0 | AQ43: =L54 -> 0 | AY43: =N49 -> 0
E44: Cedula: | F44: =IF(D42<>"", VLOOKUP(D42,'Base de Datos'!$A$2:$D1268,4,FALSE()),"") | I44: Cedula: | J44: =IF(H42<>"", VLOOKUP(H42,'Base de Datos'!$A$2:$D1268,4,FALSE()),"") | M44: Cedula: | N44: =IF(L42<>"", VLOOKUP(L42,'Base de Datos'!$A$2:$D1268,4,FALSE()),"") | AE44: Dra. Ma.Auxliliadora Aguilera | AG44: {=COUNTIFS(AP6:AP46, "💲", AY6:AY46, INDIRECT("AE" & ROW())) + COUNTIFS(AP6:AP46, "📦", AY6:AY46, INDIRECT("AE" & ROW())) + COUNTIFS(AP6:AP46, "✅", AY6:AY46, INDIRECT("AE" & ROW()))} -> 0 | AH44: {=COUNTIFS(AP6:AP46, "💲", AY6:AY46, INDIRECT("AE" & ROW())) + COUNTIFS(AP6:AP46, "📦", AY6:AY46, INDIRECT("AE" & ROW()))} -> 0 | AI44: {=SUMIFS(AR6:AR46, AY6:AY46, INDIRECT("AE" & ROW()), AP6:AP46, "💲") + SUMIFS(AR6:AR46, AY6:AY46, INDIRECT("AE" & ROW()), AP6:AP46, "📦")} -> 0 | AJ44: {=( SUMIFS(AR6:AR46, AY6:AY46, INDIRECT("AE" & ROW()), AP6:AP46, "💲") + SUMIFS(AR6:AR46, AY6:AY46, INDIRECT("AE" & ROW()), AP6:AP46, "📦") ) - ( SUMIFS(AR6:AR46, AY6:AY46, INDIRECT("AE" & ROW()), AP6:AP46, "💲", AS6:AS46, "Participante") + SUMIFS(AR6:AR46, AY6:AY46, INDIRECT("AE" & ROW()), AP6:AP46, "📦", AS6:AS46, "Participante") ) - ( SUMIFS(AR6:AR46, AY6:AY46, INDIRECT("AE" & ROW()), AP6:AP46, "💲", AS6:AS46, "Empleado") + SUMIFS(AR6:AR46, AY6:AY46, INDIRECT("AE" & ROW()), AP6:AP46, "📦", AS6:AS46, "Empleado") ) - ( ( SUMIFS(AR6:AR46, AY6:AY46, INDIRECT("AE" & ROW()), AP6:AP46, "💲", AS6:AS46, "Familiar") + SUMIFS(AR6:AR46, AY6:AY46, INDIRECT("AE" & ROW()), AP6:AP46, "📦", AS6:AS46, "Familiar") ) / 2 ) - ( ( SUMIFS(AR6:AR46, AY6:AY46, INDIRECT("AE" & ROW()), AP6:AP46, "💲", AS6:AS46, "Exonerado ADH") + SUMIFS(AR6:AR46, AY6:AY46, INDIRECT("AE" & ROW()), AP6:AP46, "📦", AS6:AS46, "Exonerado ADH") ) / 2 ) - ( ( SUMIFS(AR6:AR46, AY6:AY46, INDIRECT("AE" & ROW()), AP6:AP46, "💲", AS6:AS46, "Exonerado Doctor") + SUMIFS(AR6:AR46, AY6:AY46, INDIRECT("AE" & ROW()), AP6:AP46, "📦", AS6:AS46, "Exonerado Doctor") ) / 2 )} -> 0 | AK44: {=( SUMIFS(AR6:AR46, AY6:AY46, INDIRECT("AE" & ROW()), AP6:AP46, "💲") + SUMIFS(AR6:AR46, AY6:AY46, INDIRECT("AE" & ROW()), AP6:AP46, "📦") ) - ( SUMIFS(AR6:AR46, AY6:AY46, INDIRECT("AE" & ROW()), AP6:AP46, "💲", AS6:AS46, "Familiar") + SUMIFS(AR6:AR46, AY6:AY46, INDIRECT("AE" & ROW()), AP6:AP46, "📦", AS6:AS46, "Familiar") ) - ( SUMIFS(AR6:AR46, AY6:AY46, INDIRECT("AE" & ROW()), AP6:AP46, "💲", AS6:AS46, "Participante") + SUMIFS(AR6:AR46, AY6:AY46, INDIRECT("AE" & ROW()), AP6:AP46, "📦", AS6:AS46, "Participante") ) - ( SUMIFS(AR6:AR46, AY6:AY46, INDIRECT("AE" & ROW()), AP6:AP46, "💲", AS6:AS46, "Empleado") + SUMIFS(AR6:AR46, AY6:AY46, INDIRECT("AE" & ROW()), AP6:AP46, "📦", AS6:AS46, "Empleado") ) - ( SUMIFS(AR6:AR46, AY6:AY46, INDIRECT("AE" & ROW()), AP6:AP46, "💲", AS6:AS46, "Exonerado ADH") + SUMIFS(AR6:AR46, AY6:AY46, INDIRECT("AE" & ROW()), AP6:AP46, "📦", AS6:AS46, "Exonerado ADH") ) - ( ( SUMIFS(AR6:AR46, AY6:AY46, INDIRECT("AE" & ROW()), AP6:AP46, "💲", AS6:AS46, "Exonerado Doctor") + SUMIFS(AR6:AR46, AY6:AY46, INDIRECT("AE" & ROW()), AP6:AP46, "📦", AS6:AS46, "Exonerado Doctor") ) / 2 ) - ( ( SUMIFS(AR6:AR46, AY6:AY46, INDIRECT("AE" & ROW()), AP6:AP46, "💲", AS6:AS46, "") + SUMIFS(AR6:AR46, AY6:AY46, INDIRECT("AE" & ROW()), AP6:AP46, "📦", AS6:AS46, "") ) / 2 )} -> 0 | AL44: {=( SUMIFS(AR6:AR46, AY6:AY46, INDIRECT("AE" & ROW()), AP6:AP46, "💲") + SUMIFS(AR6:AR46, AY6:AY46, INDIRECT("AE" & ROW()), AP6:AP46, "📦") ) - ( ( SUMIFS(AR6:AR46, AY6:AY46, INDIRECT("AE" & ROW()), AP6:AP46, "💲", AS6:AS46, "Familiar") + SUMIFS(AR6:AR46, AY6:AY46, INDIRECT("AE" & ROW()), AP6:AP46, "📦", AS6:AS46, "Familiar") ) / 2 ) - ( ( SUMIFS(AR6:AR46, AY6:AY46, INDIRECT("AE" & ROW()), AP6:AP46, "💲", AS6:AS46, "Participante") + SUMIFS(AR6:AR46, AY6:AY46, INDIRECT("AE" & ROW()), AP6:AP46, "📦", AS6:AS46, "Participante") ) / 2 ) - ( ( SUMIFS(AR6:AR46, AY6:AY46, INDIRECT("AE" & ROW()), AP6:AP46, "💲", AS6:AS46, "Empleado") + SUMIFS(AR6:AR46, AY6:AY46, INDIRECT("AE" & ROW()), AP6:AP46, "📦", AS6:AS46, "Empleado") ) / 2 ) - ( ( SUMIFS(AR6:AR46, AY6:AY46, INDIRECT("AE" & ROW()), AP6:AP46, "💲", AS6:AS46, "Exonerado ADH") + SUMIFS(AR6:AR46, AY6:AY46, INDIRECT("AE" & ROW()), AP6:AP46, "📦", AS6:AS46, "Exonerado ADH") ) / 2 ) - ( SUMIFS(AR6:AR46, AY6:AY46, INDIRECT("AE" & ROW()), AP6:AP46, "💲", AS6:AS46, "Exonerado Doctor") + SUMIFS(AR6:AR46, AY6:AY46, INDIRECT("AE" & ROW()), AP6:AP46, "📦", AS6:AS46, "Exonerado Doctor") ) - ( ( SUMIFS(AR6:AR46, AY6:AY46, INDIRECT("AE" & ROW()), AP6:AP46, "💲", AS6:AS46, "") + SUMIFS(AR6:AR46, AY6:AY46, INDIRECT("AE" & ROW()), AP6:AP46, "📦", AS6:AS46, "") ) / 2 )} -> 0 | AY44: =N53 -> 0
E45: Doctor: | I45: Doctor: | M45: Doctor: | S45: =IF(OR(S42="Empleado",S42="Familiar"),"Nombre del Empleado","N° Factura") -> N° Factura | W45: =IF(OR(W42="Empleado",W42="Familiar"),"Nombre del Empleado","N° Factura") -> N° Factura | AA45: =IF(OR(AA42="Empleado",AA42="Familiar"),"Nombre del Empleado","N° Factura") -> N° Factura | AE45: Dr. Jorge Valeri | AG45: {=COUNTIFS(AP6:AP46, "💲", AY6:AY46, INDIRECT("AE" & ROW())) + COUNTIFS(AP6:AP46, "📦", AY6:AY46, INDIRECT("AE" & ROW())) + COUNTIFS(AP6:AP46, "✅", AY6:AY46, INDIRECT("AE" & ROW()))} -> 0 | AH45: {=COUNTIFS(AP6:AP46, "💲", AY6:AY46, INDIRECT("AE" & ROW())) + COUNTIFS(AP6:AP46, "📦", AY6:AY46, INDIRECT("AE" & ROW()))} -> 0 | AI45: {=SUMIFS(AR6:AR46, AY6:AY46, INDIRECT("AE" & ROW()), AP6:AP46, "💲") + SUMIFS(AR6:AR46, AY6:AY46, INDIRECT("AE" & ROW()), AP6:AP46, "📦")} -> 0 | AJ45: {=( SUMIFS(AR6:AR46, AY6:AY46, INDIRECT("AE" & ROW()), AP6:AP46, "💲") + SUMIFS(AR6:AR46, AY6:AY46, INDIRECT("AE" & ROW()), AP6:AP46, "📦") ) - ( SUMIFS(AR6:AR46, AY6:AY46, INDIRECT("AE" & ROW()), AP6:AP46, "💲", AS6:AS46, "Participante") + SUMIFS(AR6:AR46, AY6:AY46, INDIRECT("AE" & ROW()), AP6:AP46, "📦", AS6:AS46, "Participante") ) - ( SUMIFS(AR6:AR46, AY6:AY46, INDIRECT("AE" & ROW()), AP6:AP46, "💲", AS6:AS46, "Empleado") + SUMIFS(AR6:AR46, AY6:AY46, INDIRECT("AE" & ROW()), AP6:AP46, "📦", AS6:AS46, "Empleado") ) - ( ( SUMIFS(AR6:AR46, AY6:AY46, INDIRECT("AE" & ROW()), AP6:AP46, "💲", AS6:AS46, "Familiar") + SUMIFS(AR6:AR46, AY6:AY46, INDIRECT("AE" & ROW()), AP6:AP46, "📦", AS6:AS46, "Familiar") ) / 2 ) - ( ( SUMIFS(AR6:AR46, AY6:AY46, INDIRECT("AE" & ROW()), AP6:AP46, "💲", AS6:AS46, "Exonerado ADH") + SUMIFS(AR6:AR46, AY6:AY46, INDIRECT("AE" & ROW()), AP6:AP46, "📦", AS6:AS46, "Exonerado ADH") ) / 2 ) - ( ( SUMIFS(AR6:AR46, AY6:AY46, INDIRECT("AE" & ROW()), AP6:AP46, "💲", AS6:AS46, "Exonerado Doctor") + SUMIFS(AR6:AR46, AY6:AY46, INDIRECT("AE" & ROW()), AP6:AP46, "📦", AS6:AS46, "Exonerado Doctor") ) / 2 )} -> 0 | AK45: {=( SUMIFS(AR6:AR46, AY6:AY46, INDIRECT("AE" & ROW()), AP6:AP46, "💲") + SUMIFS(AR6:AR46, AY6:AY46, INDIRECT("AE" & ROW()), AP6:AP46, "📦") ) - ( SUMIFS(AR6:AR46, AY6:AY46, INDIRECT("AE" & ROW()), AP6:AP46, "💲", AS6:AS46, "Familiar") + SUMIFS(AR6:AR46, AY6:AY46, INDIRECT("AE" & ROW()), AP6:AP46, "📦", AS6:AS46, "Familiar") ) - ( SUMIFS(AR6:AR46, AY6:AY46, INDIRECT("AE" & ROW()), AP6:AP46, "💲", AS6:AS46, "Participante") + SUMIFS(AR6:AR46, AY6:AY46, INDIRECT("AE" & ROW()), AP6:AP46, "📦", AS6:AS46, "Participante") ) - ( SUMIFS(AR6:AR46, AY6:AY46, INDIRECT("AE" & ROW()), AP6:AP46, "💲", AS6:AS46, "Empleado") + SUMIFS(AR6:AR46, AY6:AY46, INDIRECT("AE" & ROW()), AP6:AP46, "📦", AS6:AS46, "Empleado") ) - ( SUMIFS(AR6:AR46, AY6:AY46, INDIRECT("AE" & ROW()), AP6:AP46, "💲", AS6:AS46, "Exonerado ADH") + SUMIFS(AR6:AR46, AY6:AY46, INDIRECT("AE" & ROW()), AP6:AP46, "📦", AS6:AS46, "Exonerado ADH") ) - ( ( SUMIFS(AR6:AR46, AY6:AY46, INDIRECT("AE" & ROW()), AP6:AP46, "💲", AS6:AS46, "Exonerado Doctor") + SUMIFS(AR6:AR46, AY6:AY46, INDIRECT("AE" & ROW()), AP6:AP46, "📦", AS6:AS46, "Exonerado Doctor") ) / 2 ) - ( ( SUMIFS(AR6:AR46, AY6:AY46, INDIRECT("AE" & ROW()), AP6:AP46, "💲", AS6:AS46, "") + SUMIFS(AR6:AR46, AY6:AY46, INDIRECT("AE" & ROW()), AP6:AP46, "📦", AS6:AS46, "") ) / 2 )} -> 0 | AL45: {=( SUMIFS(AR6:AR46, AY6:AY46, INDIRECT("AE" & ROW()), AP6:AP46, "💲") + SUMIFS(AR6:AR46, AY6:AY46, INDIRECT("AE" & ROW()), AP6:AP46, "📦") ) - ( ( SUMIFS(AR6:AR46, AY6:AY46, INDIRECT("AE" & ROW()), AP6:AP46, "💲", AS6:AS46, "Familiar") + SUMIFS(AR6:AR46, AY6:AY46, INDIRECT("AE" & ROW()), AP6:AP46, "📦", AS6:AS46, "Familiar") ) / 2 ) - ( ( SUMIFS(AR6:AR46, AY6:AY46, INDIRECT("AE" & ROW()), AP6:AP46, "💲", AS6:AS46, "Participante") + SUMIFS(AR6:AR46, AY6:AY46, INDIRECT("AE" & ROW()), AP6:AP46, "📦", AS6:AS46, "Participante") ) / 2 ) - ( ( SUMIFS(AR6:AR46, AY6:AY46, INDIRECT("AE" & ROW()), AP6:AP46, "💲", AS6:AS46, "Empleado") + SUMIFS(AR6:AR46, AY6:AY46, INDIRECT("AE" & ROW()), AP6:AP46, "📦", AS6:AS46, "Empleado") ) / 2 ) - ( ( SUMIFS(AR6:AR46, AY6:AY46, INDIRECT("AE" & ROW()), AP6:AP46, "💲", AS6:AS46, "Exonerado ADH") + SUMIFS(AR6:AR46, AY6:AY46, INDIRECT("AE" & ROW()), AP6:AP46, "📦", AS6:AS46, "Exonerado ADH") ) / 2 ) - ( SUMIFS(AR6:AR46, AY6:AY46, INDIRECT("AE" & ROW()), AP6:AP46, "💲", AS6:AS46, "Exonerado Doctor") + SUMIFS(AR6:AR46, AY6:AY46, INDIRECT("AE" & ROW()), AP6:AP46, "📦", AS6:AS46, "Exonerado Doctor") ) - ( ( SUMIFS(AR6:AR46, AY6:AY46, INDIRECT("AE" & ROW()), AP6:AP46, "💲", AS6:AS46, "") + SUMIFS(AR6:AR46, AY6:AY46, INDIRECT("AE" & ROW()), AP6:AP46, "📦", AS6:AS46, "") ) / 2 )} -> 0 | AY45: =N57 -> 0
A46: =A42+$Q$13/1440 -> 0.75 | E46: Representante: | F46: =IF(D46<>"", VLOOKUP(D46,'Base de Datos'!$A$2:$D1268,2,FALSE()),"") | I46: Representante: | J46: =IF(H46<>"", VLOOKUP(H46,'Base de Datos'!$A$2:$D1268,2,FALSE()),"") | M46: Representante: | N46: =IF(L46<>"", VLOOKUP(L46,'Base de Datos'!$A$2:$D1268,2,FALSE()),"") | T46: Precio: | X46: Precio: | AB46: Precio: | AE46: Dr. José Francisco Cordero | AG46: {=COUNTIFS(AP6:AP46, "💲", AY6:AY46, INDIRECT("AE" & ROW())) + COUNTIFS(AP6:AP46, "📦", AY6:AY46, INDIRECT("AE" & ROW())) + COUNTIFS(AP6:AP46, "✅", AY6:AY46, INDIRECT("AE" & ROW()))} -> 0 | AH46: {=COUNTIFS(AP6:AP46, "💲", AY6:AY46, INDIRECT("AE" & ROW())) + COUNTIFS(AP6:AP46, "📦", AY6:AY46, INDIRECT("AE" & ROW()))} -> 0 | AI46: {=SUMIFS(AR6:AR46, AY6:AY46, INDIRECT("AE" & ROW()), AP6:AP46, "💲") + SUMIFS(AR6:AR46, AY6:AY46, INDIRECT("AE" & ROW()), AP6:AP46, "📦")} -> 0 | AJ46: {=( SUMIFS(AR6:AR46, AY6:AY46, INDIRECT("AE" & ROW()), AP6:AP46, "💲") + SUMIFS(AR6:AR46, AY6:AY46, INDIRECT("AE" & ROW()), AP6:AP46, "📦") ) - ( SUMIFS(AR6:AR46, AY6:AY46, INDIRECT("AE" & ROW()), AP6:AP46, "💲", AS6:AS46, "Participante") + SUMIFS(AR6:AR46, AY6:AY46, INDIRECT("AE" & ROW()), AP6:AP46, "📦", AS6:AS46, "Participante") ) - ( SUMIFS(AR6:AR46, AY6:AY46, INDIRECT("AE" & ROW()), AP6:AP46, "💲", AS6:AS46, "Empleado") + SUMIFS(AR6:AR46, AY6:AY46, INDIRECT("AE" & ROW()), AP6:AP46, "📦", AS6:AS46, "Empleado") ) - ( ( SUMIFS(AR6:AR46, AY6:AY46, INDIRECT("AE" & ROW()), AP6:AP46, "💲", AS6:AS46, "Familiar") + SUMIFS(AR6:AR46, AY6:AY46, INDIRECT("AE" & ROW()), AP6:AP46, "📦", AS6:AS46, "Familiar") ) / 2 ) - ( ( SUMIFS(AR6:AR46, AY6:AY46, INDIRECT("AE" & ROW()), AP6:AP46, "💲", AS6:AS46, "Exonerado ADH") + SUMIFS(AR6:AR46, AY6:AY46, INDIRECT("AE" & ROW()), AP6:AP46, "📦", AS6:AS46, "Exonerado ADH") ) / 2 ) - ( ( SUMIFS(AR6:AR46, AY6:AY46, INDIRECT("AE" & ROW()), AP6:AP46, "💲", AS6:AS46, "Exonerado Doctor") + SUMIFS(AR6:AR46, AY6:AY46, INDIRECT("AE" & ROW()), AP6:AP46, "📦", AS6:AS46, "Exonerado Doctor") ) / 2 )} -> 0 | AK46: {=( SUMIFS(AR6:AR46, AY6:AY46, INDIRECT("AE" & ROW()), AP6:AP46, "💲") + SUMIFS(AR6:AR46, AY6:AY46, INDIRECT("AE" & ROW()), AP6:AP46, "📦") ) - ( SUMIFS(AR6:AR46, AY6:AY46, INDIRECT("AE" & ROW()), AP6:AP46, "💲", AS6:AS46, "Familiar") + SUMIFS(AR6:AR46, AY6:AY46, INDIRECT("AE" & ROW()), AP6:AP46, "📦", AS6:AS46, "Familiar") ) - ( SUMIFS(AR6:AR46, AY6:AY46, INDIRECT("AE" & ROW()), AP6:AP46, "💲", AS6:AS46, "Participante") + SUMIFS(AR6:AR46, AY6:AY46, INDIRECT("AE" & ROW()), AP6:AP46, "📦", AS6:AS46, "Participante") ) - ( SUMIFS(AR6:AR46, AY6:AY46, INDIRECT("AE" & ROW()), AP6:AP46, "💲", AS6:AS46, "Empleado") + SUMIFS(AR6:AR46, AY6:AY46, INDIRECT("AE" & ROW()), AP6:AP46, "📦", AS6:AS46, "Empleado") ) - ( SUMIFS(AR6:AR46, AY6:AY46, INDIRECT("AE" & ROW()), AP6:AP46, "💲", AS6:AS46, "Exonerado ADH") + SUMIFS(AR6:AR46, AY6:AY46, INDIRECT("AE" & ROW()), AP6:AP46, "📦", AS6:AS46, "Exonerado ADH") ) - ( ( SUMIFS(AR6:AR46, AY6:AY46, INDIRECT("AE" & ROW()), AP6:AP46, "💲", AS6:AS46, "Exonerado Doctor") + SUMIFS(AR6:AR46, AY6:AY46, INDIRECT("AE" & ROW()), AP6:AP46, "📦", AS6:AS46, "Exonerado Doctor") ) / 2 ) - ( ( SUMIFS(AR6:AR46, AY6:AY46, INDIRECT("AE" & ROW()), AP6:AP46, "💲", AS6:AS46, "") + SUMIFS(AR6:AR46, AY6:AY46, INDIRECT("AE" & ROW()), AP6:AP46, "📦", AS6:AS46, "") ) / 2 )} -> 0 | AL46: {=( SUMIFS(AR6:AR46, AY6:AY46, INDIRECT("AE" & ROW()), AP6:AP46, "💲") + SUMIFS(AR6:AR46, AY6:AY46, INDIRECT("AE" & ROW()), AP6:AP46, "📦") ) - ( ( SUMIFS(AR6:AR46, AY6:AY46, INDIRECT("AE" & ROW()), AP6:AP46, "💲", AS6:AS46, "Familiar") + SUMIFS(AR6:AR46, AY6:AY46, INDIRECT("AE" & ROW()), AP6:AP46, "📦", AS6:AS46, "Familiar") ) / 2 ) - ( ( SUMIFS(AR6:AR46, AY6:AY46, INDIRECT("AE" & ROW()), AP6:AP46, "💲", AS6:AS46, "Participante") + SUMIFS(AR6:AR46, AY6:AY46, INDIRECT("AE" & ROW()), AP6:AP46, "📦", AS6:AS46, "Participante") ) / 2 ) - ( ( SUMIFS(AR6:AR46, AY6:AY46, INDIRECT("AE" & ROW()), AP6:AP46, "💲", AS6:AS46, "Empleado") + SUMIFS(AR6:AR46, AY6:AY46, INDIRECT("AE" & ROW()), AP6:AP46, "📦", AS6:AS46, "Empleado") ) / 2 ) - ( ( SUMIFS(AR6:AR46, AY6:AY46, INDIRECT("AE" & ROW()), AP6:AP46, "💲", AS6:AS46, "Exonerado ADH") + SUMIFS(AR6:AR46, AY6:AY46, INDIRECT("AE" & ROW()), AP6:AP46, "📦", AS6:AS46, "Exonerado ADH") ) / 2 ) - ( SUMIFS(AR6:AR46, AY6:AY46, INDIRECT("AE" & ROW()), AP6:AP46, "💲", AS6:AS46, "Exonerado Doctor") + SUMIFS(AR6:AR46, AY6:AY46, INDIRECT("AE" & ROW()), AP6:AP46, "📦", AS6:AS46, "Exonerado Doctor") ) - ( ( SUMIFS(AR6:AR46, AY6:AY46, INDIRECT("AE" & ROW()), AP6:AP46, "💲", AS6:AS46, "") + SUMIFS(AR6:AR46, AY6:AY46, INDIRECT("AE" & ROW()), AP6:AP46, "📦", AS6:AS46, "") ) / 2 )} -> 0
E47: Teléfono: | F47: =IF(D46<>"", VLOOKUP(D46,'Base de Datos'!$A$2:$D1268,3,FALSE()),"") | I47: Teléfono: | J47: =IF(H46<>"", VLOOKUP(H46,'Base de Datos'!$A$2:$D1268,3,FALSE()),"") | M47: Teléfono: | N47: =IF(L46<>"", VLOOKUP(L46,'Base de Datos'!$A$2:$D1268,3,FALSE()),"") | AE47: Dra. Mónica Porras | AG47: {=COUNTIFS(AP6:AP46, "💲", AY6:AY46, INDIRECT("AE" & ROW())) + COUNTIFS(AP6:AP46, "📦", AY6:AY46, INDIRECT("AE" & ROW())) + COUNTIFS(AP6:AP46, "✅", AY6:AY46, INDIRECT("AE" & ROW()))} -> 0 | AH47: {=COUNTIFS(AP6:AP46, "💲", AY6:AY46, INDIRECT("AE" & ROW())) + COUNTIFS(AP6:AP46, "📦", AY6:AY46, INDIRECT("AE" & ROW()))} -> 0 | AI47: {=SUMIFS(AR6:AR46, AY6:AY46, INDIRECT("AE" & ROW()), AP6:AP46, "💲") + SUMIFS(AR6:AR46, AY6:AY46, INDIRECT("AE" & ROW()), AP6:AP46, "📦")} -> 0 | AJ47: {=( SUMIFS(AR6:AR46, AY6:AY46, INDIRECT("AE" & ROW()), AP6:AP46, "💲") + SUMIFS(AR6:AR46, AY6:AY46, INDIRECT("AE" & ROW()), AP6:AP46, "📦") ) - ( SUMIFS(AR6:AR46, AY6:AY46, INDIRECT("AE" & ROW()), AP6:AP46, "💲", AS6:AS46, "Participante") + SUMIFS(AR6:AR46, AY6:AY46, INDIRECT("AE" & ROW()), AP6:AP46, "📦", AS6:AS46, "Participante") ) - ( SUMIFS(AR6:AR46, AY6:AY46, INDIRECT("AE" & ROW()), AP6:AP46, "💲", AS6:AS46, "Empleado") + SUMIFS(AR6:AR46, AY6:AY46, INDIRECT("AE" & ROW()), AP6:AP46, "📦", AS6:AS46, "Empleado") ) - ( ( SUMIFS(AR6:AR46, AY6:AY46, INDIRECT("AE" & ROW()), AP6:AP46, "💲", AS6:AS46, "Familiar") + SUMIFS(AR6:AR46, AY6:AY46, INDIRECT("AE" & ROW()), AP6:AP46, "📦", AS6:AS46, "Familiar") ) / 2 ) - ( ( SUMIFS(AR6:AR46, AY6:AY46, INDIRECT("AE" & ROW()), AP6:AP46, "💲", AS6:AS46, "Exonerado ADH") + SUMIFS(AR6:AR46, AY6:AY46, INDIRECT("AE" & ROW()), AP6:AP46, "📦", AS6:AS46, "Exonerado ADH") ) / 2 ) - ( ( SUMIFS(AR6:AR46, AY6:AY46, INDIRECT("AE" & ROW()), AP6:AP46, "💲", AS6:AS46, "Exonerado Doctor") + SUMIFS(AR6:AR46, AY6:AY46, INDIRECT("AE" & ROW()), AP6:AP46, "📦", AS6:AS46, "Exonerado Doctor") ) / 2 )} -> 0 | AK47: {=( SUMIFS(AR6:AR46, AY6:AY46, INDIRECT("AE" & ROW()), AP6:AP46, "💲") + SUMIFS(AR6:AR46, AY6:AY46, INDIRECT("AE" & ROW()), AP6:AP46, "📦") ) - ( SUMIFS(AR6:AR46, AY6:AY46, INDIRECT("AE" & ROW()), AP6:AP46, "💲", AS6:AS46, "Familiar") + SUMIFS(AR6:AR46, AY6:AY46, INDIRECT("AE" & ROW()), AP6:AP46, "📦", AS6:AS46, "Familiar") ) - ( SUMIFS(AR6:AR46, AY6:AY46, INDIRECT("AE" & ROW()), AP6:AP46, "💲", AS6:AS46, "Participante") + SUMIFS(AR6:AR46, AY6:AY46, INDIRECT("AE" & ROW()), AP6:AP46, "📦", AS6:AS46, "Participante") ) - ( SUMIFS(AR6:AR46, AY6:AY46, INDIRECT("AE" & ROW()), AP6:AP46, "💲", AS6:AS46, "Empleado") + SUMIFS(AR6:AR46, AY6:AY46, INDIRECT("AE" & ROW()), AP6:AP46, "📦", AS6:AS46, "Empleado") ) - ( SUMIFS(AR6:AR46, AY6:AY46, INDIRECT("AE" & ROW()), AP6:AP46, "💲", AS6:AS46, "Exonerado ADH") + SUMIFS(AR6:AR46, AY6:AY46, INDIRECT("AE" & ROW()), AP6:AP46, "📦", AS6:AS46, "Exonerado ADH") ) - ( ( SUMIFS(AR6:AR46, AY6:AY46, INDIRECT("AE" & ROW()), AP6:AP46, "💲", AS6:AS46, "Exonerado Doctor") + SUMIFS(AR6:AR46, AY6:AY46, INDIRECT("AE" & ROW()), AP6:AP46, "📦", AS6:AS46, "Exonerado Doctor") ) / 2 ) - ( ( SUMIFS(AR6:AR46, AY6:AY46, INDIRECT("AE" & ROW()), AP6:AP46, "💲", AS6:AS46, "") + SUMIFS(AR6:AR46, AY6:AY46, INDIRECT("AE" & ROW()), AP6:AP46, "📦", AS6:AS46, "") ) / 2 )} -> 0 | AL47: {=( SUMIFS(AR6:AR46, AY6:AY46, INDIRECT("AE" & ROW()), AP6:AP46, "💲") + SUMIFS(AR6:AR46, AY6:AY46, INDIRECT("AE" & ROW()), AP6:AP46, "📦") ) - ( ( SUMIFS(AR6:AR46, AY6:AY46, INDIRECT("AE" & ROW()), AP6:AP46, "💲", AS6:AS46, "Familiar") + SUMIFS(AR6:AR46, AY6:AY46, INDIRECT("AE" & ROW()), AP6:AP46, "📦", AS6:AS46, "Familiar") ) / 2 ) - ( ( SUMIFS(AR6:AR46, AY6:AY46, INDIRECT("AE" & ROW()), AP6:AP46, "💲", AS6:AS46, "Participante") + SUMIFS(AR6:AR46, AY6:AY46, INDIRECT("AE" & ROW()), AP6:AP46, "📦", AS6:AS46, "Participante") ) / 2 ) - ( ( SUMIFS(AR6:AR46, AY6:AY46, INDIRECT("AE" & ROW()), AP6:AP46, "💲", AS6:AS46, "Empleado") + SUMIFS(AR6:AR46, AY6:AY46, INDIRECT("AE" & ROW()), AP6:AP46, "📦", AS6:AS46, "Empleado") ) / 2 ) - ( ( SUMIFS(AR6:AR46, AY6:AY46, INDIRECT("AE" & ROW()), AP6:AP46, "💲", AS6:AS46, "Exonerado ADH") + SUMIFS(AR6:AR46, AY6:AY46, INDIRECT("AE" & ROW()), AP6:AP46, "📦", AS6:AS46, "Exonerado ADH") ) / 2 ) - ( SUMIFS(AR6:AR46, AY6:AY46, INDIRECT("AE" & ROW()), AP6:AP46, "💲", AS6:AS46, "Exonerado Doctor") + SUMIFS(AR6:AR46, AY6:AY46, INDIRECT("AE" & ROW()), AP6:AP46, "📦", AS6:AS46, "Exonerado Doctor") ) - ( ( SUMIFS(AR6:AR46, AY6:AY46, INDIRECT("AE" & ROW()), AP6:AP46, "💲", AS6:AS46, "") + SUMIFS(AR6:AR46, AY6:AY46, INDIRECT("AE" & ROW()), AP6:AP46, "📦", AS6:AS46, "") ) / 2 )} -> 0
E48: Cedula: | F48: =IF(D46<>"", VLOOKUP(D46,'Base de Datos'!$A$2:$D1268,4,FALSE()),"") | I48: Cedula: | J48: =IF(H46<>"", VLOOKUP(H46,'Base de Datos'!$A$2:$D1268,4,FALSE()),"") | M48: Cedula: | N48: =IF(L46<>"", VLOOKUP(L46,'Base de Datos'!$A$2:$D1268,4,FALSE()),"") | AE48: Dra. Conchita Sánchez | AG48: {=COUNTIFS(AP6:AP46, "💲", AY6:AY46, INDIRECT("AE" & ROW())) + COUNTIFS(AP6:AP46, "📦", AY6:AY46, INDIRECT("AE" & ROW())) + COUNTIFS(AP6:AP46, "✅", AY6:AY46, INDIRECT("AE" & ROW()))} -> 0 | AH48: {=COUNTIFS(AP6:AP46, "💲", AY6:AY46, INDIRECT("AE" & ROW())) + COUNTIFS(AP6:AP46, "📦", AY6:AY46, INDIRECT("AE" & ROW()))} -> 0 | AI48: {=SUMIFS(AR6:AR46, AY6:AY46, INDIRECT("AE" & ROW()), AP6:AP46, "💲") + SUMIFS(AR6:AR46, AY6:AY46, INDIRECT("AE" & ROW()), AP6:AP46, "📦")} -> 0 | AJ48: {=( SUMIFS(AR6:AR46, AY6:AY46, INDIRECT("AE" & ROW()), AP6:AP46, "💲") + SUMIFS(AR6:AR46, AY6:AY46, INDIRECT("AE" & ROW()), AP6:AP46, "📦") ) - ( SUMIFS(AR6:AR46, AY6:AY46, INDIRECT("AE" & ROW()), AP6:AP46, "💲", AS6:AS46, "Participante") + SUMIFS(AR6:AR46, AY6:AY46, INDIRECT("AE" & ROW()), AP6:AP46, "📦", AS6:AS46, "Participante") ) - ( SUMIFS(AR6:AR46, AY6:AY46, INDIRECT("AE" & ROW()), AP6:AP46, "💲", AS6:AS46, "Empleado") + SUMIFS(AR6:AR46, AY6:AY46, INDIRECT("AE" & ROW()), AP6:AP46, "📦", AS6:AS46, "Empleado") ) - ( ( SUMIFS(AR6:AR46, AY6:AY46, INDIRECT("AE" & ROW()), AP6:AP46, "💲", AS6:AS46, "Familiar") + SUMIFS(AR6:AR46, AY6:AY46, INDIRECT("AE" & ROW()), AP6:AP46, "📦", AS6:AS46, "Familiar") ) / 2 ) - ( ( SUMIFS(AR6:AR46, AY6:AY46, INDIRECT("AE" & ROW()), AP6:AP46, "💲", AS6:AS46, "Exonerado ADH") + SUMIFS(AR6:AR46, AY6:AY46, INDIRECT("AE" & ROW()), AP6:AP46, "📦", AS6:AS46, "Exonerado ADH") ) / 2 ) - ( ( SUMIFS(AR6:AR46, AY6:AY46, INDIRECT("AE" & ROW()), AP6:AP46, "💲", AS6:AS46, "Exonerado Doctor") + SUMIFS(AR6:AR46, AY6:AY46, INDIRECT("AE" & ROW()), AP6:AP46, "📦", AS6:AS46, "Exonerado Doctor") ) / 2 )} -> 0 | AK48: {=( SUMIFS(AR6:AR46, AY6:AY46, INDIRECT("AE" & ROW()), AP6:AP46, "💲") + SUMIFS(AR6:AR46, AY6:AY46, INDIRECT("AE" & ROW()), AP6:AP46, "📦") ) - ( SUMIFS(AR6:AR46, AY6:AY46, INDIRECT("AE" & ROW()), AP6:AP46, "💲", AS6:AS46, "Familiar") + SUMIFS(AR6:AR46, AY6:AY46, INDIRECT("AE" & ROW()), AP6:AP46, "📦", AS6:AS46, "Familiar") ) - ( SUMIFS(AR6:AR46, AY6:AY46, INDIRECT("AE" & ROW()), AP6:AP46, "💲", AS6:AS46, "Participante") + SUMIFS(AR6:AR46, AY6:AY46, INDIRECT("AE" & ROW()), AP6:AP46, "📦", AS6:AS46, "Participante") ) - ( SUMIFS(AR6:AR46, AY6:AY46, INDIRECT("AE" & ROW()), AP6:AP46, "💲", AS6:AS46, "Empleado") + SUMIFS(AR6:AR46, AY6:AY46, INDIRECT("AE" & ROW()), AP6:AP46, "📦", AS6:AS46, "Empleado") ) - ( SUMIFS(AR6:AR46, AY6:AY46, INDIRECT("AE" & ROW()), AP6:AP46, "💲", AS6:AS46, "Exonerado ADH") + SUMIFS(AR6:AR46, AY6:AY46, INDIRECT("AE" & ROW()), AP6:AP46, "📦", AS6:AS46, "Exonerado ADH") ) - ( ( SUMIFS(AR6:AR46, AY6:AY46, INDIRECT("AE" & ROW()), AP6:AP46, "💲", AS6:AS46, "Exonerado Doctor") + SUMIFS(AR6:AR46, AY6:AY46, INDIRECT("AE" & ROW()), AP6:AP46, "📦", AS6:AS46, "Exonerado Doctor") ) / 2 ) - ( ( SUMIFS(AR6:AR46, AY6:AY46, INDIRECT("AE" & ROW()), AP6:AP46, "💲", AS6:AS46, "") + SUMIFS(AR6:AR46, AY6:AY46, INDIRECT("AE" & ROW()), AP6:AP46, "📦", AS6:AS46, "") ) / 2 )} -> 0 | AL48: {=( SUMIFS(AR6:AR46, AY6:AY46, INDIRECT("AE" & ROW()), AP6:AP46, "💲") + SUMIFS(AR6:AR46, AY6:AY46, INDIRECT("AE" & ROW()), AP6:AP46, "📦") ) - ( ( SUMIFS(AR6:AR46, AY6:AY46, INDIRECT("AE" & ROW()), AP6:AP46, "💲", AS6:AS46, "Familiar") + SUMIFS(AR6:AR46, AY6:AY46, INDIRECT("AE" & ROW()), AP6:AP46, "📦", AS6:AS46, "Familiar") ) / 2 ) - ( ( SUMIFS(AR6:AR46, AY6:AY46, INDIRECT("AE" & ROW()), AP6:AP46, "💲", AS6:AS46, "Participante") + SUMIFS(AR6:AR46, AY6:AY46, INDIRECT("AE" & ROW()), AP6:AP46, "📦", AS6:AS46, "Participante") ) / 2 ) - ( ( SUMIFS(AR6:AR46, AY6:AY46, INDIRECT("AE" & ROW()), AP6:AP46, "💲", AS6:AS46, "Empleado") + SUMIFS(AR6:AR46, AY6:AY46, INDIRECT("AE" & ROW()), AP6:AP46, "📦", AS6:AS46, "Empleado") ) / 2 ) - ( ( SUMIFS(AR6:AR46, AY6:AY46, INDIRECT("AE" & ROW()), AP6:AP46, "💲", AS6:AS46, "Exonerado ADH") + SUMIFS(AR6:AR46, AY6:AY46, INDIRECT("AE" & ROW()), AP6:AP46, "📦", AS6:AS46, "Exonerado ADH") ) / 2 ) - ( SUMIFS(AR6:AR46, AY6:AY46, INDIRECT("AE" & ROW()), AP6:AP46, "💲", AS6:AS46, "Exonerado Doctor") + SUMIFS(AR6:AR46, AY6:AY46, INDIRECT("AE" & ROW()), AP6:AP46, "📦", AS6:AS46, "Exonerado Doctor") ) - ( ( SUMIFS(AR6:AR46, AY6:AY46, INDIRECT("AE" & ROW()), AP6:AP46, "💲", AS6:AS46, "") + SUMIFS(AR6:AR46, AY6:AY46, INDIRECT("AE" & ROW()), AP6:AP46, "📦", AS6:AS46, "") ) / 2 )} -> 0
E49: Doctor: | I49: Doctor: | M49: Doctor: | S49: =IF(OR(S46="Empleado",S46="Familiar"),"Nombre del Empleado","N° Factura") -> N° Factura | W49: =IF(OR(W46="Empleado",W46="Familiar"),"Nombre del Empleado","N° Factura") -> N° Factura | AA49: =IF(OR(AA46="Empleado",AA46="Familiar"),"Nombre del Empleado","N° Factura") -> N° Factura | AE49: Dr. Carlos Eduardo Márquez | AG49: {=COUNTIFS(AP6:AP46, "💲", AY6:AY46, INDIRECT("AE" & ROW())) + COUNTIFS(AP6:AP46, "📦", AY6:AY46, INDIRECT("AE" & ROW())) + COUNTIFS(AP6:AP46, "✅", AY6:AY46, INDIRECT("AE" & ROW()))} -> 0 | AH49: {=COUNTIFS(AP6:AP46, "💲", AY6:AY46, INDIRECT("AE" & ROW())) + COUNTIFS(AP6:AP46, "📦", AY6:AY46, INDIRECT("AE" & ROW()))} -> 0 | AI49: {=SUMIFS(AR6:AR46, AY6:AY46, INDIRECT("AE" & ROW()), AP6:AP46, "💲") + SUMIFS(AR6:AR46, AY6:AY46, INDIRECT("AE" & ROW()), AP6:AP46, "📦")} -> 0 | AJ49: {=( SUMIFS(AR6:AR46, AY6:AY46, INDIRECT("AE" & ROW()), AP6:AP46, "💲") + SUMIFS(AR6:AR46, AY6:AY46, INDIRECT("AE" & ROW()), AP6:AP46, "📦") ) - ( SUMIFS(AR6:AR46, AY6:AY46, INDIRECT("AE" & ROW()), AP6:AP46, "💲", AS6:AS46, "Participante") + SUMIFS(AR6:AR46, AY6:AY46, INDIRECT("AE" & ROW()), AP6:AP46, "📦", AS6:AS46, "Participante") ) - ( SUMIFS(AR6:AR46, AY6:AY46, INDIRECT("AE" & ROW()), AP6:AP46, "💲", AS6:AS46, "Empleado") + SUMIFS(AR6:AR46, AY6:AY46, INDIRECT("AE" & ROW()), AP6:AP46, "📦", AS6:AS46, "Empleado") ) - ( ( SUMIFS(AR6:AR46, AY6:AY46, INDIRECT("AE" & ROW()), AP6:AP46, "💲", AS6:AS46, "Familiar") + SUMIFS(AR6:AR46, AY6:AY46, INDIRECT("AE" & ROW()), AP6:AP46, "📦", AS6:AS46, "Familiar") ) / 2 ) - ( ( SUMIFS(AR6:AR46, AY6:AY46, INDIRECT("AE" & ROW()), AP6:AP46, "💲", AS6:AS46, "Exonerado ADH") + SUMIFS(AR6:AR46, AY6:AY46, INDIRECT("AE" & ROW()), AP6:AP46, "📦", AS6:AS46, "Exonerado ADH") ) / 2 ) - ( ( SUMIFS(AR6:AR46, AY6:AY46, INDIRECT("AE" & ROW()), AP6:AP46, "💲", AS6:AS46, "Exonerado Doctor") + SUMIFS(AR6:AR46, AY6:AY46, INDIRECT("AE" & ROW()), AP6:AP46, "📦", AS6:AS46, "Exonerado Doctor") ) / 2 )} -> 0 | AK49: {=( SUMIFS(AR6:AR46, AY6:AY46, INDIRECT("AE" & ROW()), AP6:AP46, "💲") + SUMIFS(AR6:AR46, AY6:AY46, INDIRECT("AE" & ROW()), AP6:AP46, "📦") ) - ( SUMIFS(AR6:AR46, AY6:AY46, INDIRECT("AE" & ROW()), AP6:AP46, "💲", AS6:AS46, "Familiar") + SUMIFS(AR6:AR46, AY6:AY46, INDIRECT("AE" & ROW()), AP6:AP46, "📦", AS6:AS46, "Familiar") ) - ( SUMIFS(AR6:AR46, AY6:AY46, INDIRECT("AE" & ROW()), AP6:AP46, "💲", AS6:AS46, "Participante") + SUMIFS(AR6:AR46, AY6:AY46, INDIRECT("AE" & ROW()), AP6:AP46, "📦", AS6:AS46, "Participante") ) - ( SUMIFS(AR6:AR46, AY6:AY46, INDIRECT("AE" & ROW()), AP6:AP46, "💲", AS6:AS46, "Empleado") + SUMIFS(AR6:AR46, AY6:AY46, INDIRECT("AE" & ROW()), AP6:AP46, "📦", AS6:AS46, "Empleado") ) - ( SUMIFS(AR6:AR46, AY6:AY46, INDIRECT("AE" & ROW()), AP6:AP46, "💲", AS6:AS46, "Exonerado ADH") + SUMIFS(AR6:AR46, AY6:AY46, INDIRECT("AE" & ROW()), AP6:AP46, "📦", AS6:AS46, "Exonerado ADH") ) - ( ( SUMIFS(AR6:AR46, AY6:AY46, INDIRECT("AE" & ROW()), AP6:AP46, "💲", AS6:AS46, "Exonerado Doctor") + SUMIFS(AR6:AR46, AY6:AY46, INDIRECT("AE" & ROW()), AP6:AP46, "📦", AS6:AS46, "Exonerado Doctor") ) / 2 ) - ( ( SUMIFS(AR6:AR46, AY6:AY46, INDIRECT("AE" & ROW()), AP6:AP46, "💲", AS6:AS46, "") + SUMIFS(AR6:AR46, AY6:AY46, INDIRECT("AE" & ROW()), AP6:AP46, "📦", AS6:AS46, "") ) / 2 )} -> 0 | AL49: {=( SUMIFS(AR6:AR46, AY6:AY46, INDIRECT("AE" & ROW()), AP6:AP46, "💲") + SUMIFS(AR6:AR46, AY6:AY46, INDIRECT("AE" & ROW()), AP6:AP46, "📦") ) - ( ( SUMIFS(AR6:AR46, AY6:AY46, INDIRECT("AE" & ROW()), AP6:AP46, "💲", AS6:AS46, "Familiar") + SUMIFS(AR6:AR46, AY6:AY46, INDIRECT("AE" & ROW()), AP6:AP46, "📦", AS6:AS46, "Familiar") ) / 2 ) - ( ( SUMIFS(AR6:AR46, AY6:AY46, INDIRECT("AE" & ROW()), AP6:AP46, "💲", AS6:AS46, "Participante") + SUMIFS(AR6:AR46, AY6:AY46, INDIRECT("AE" & ROW()), AP6:AP46, "📦", AS6:AS46, "Participante") ) / 2 ) - ( ( SUMIFS(AR6:AR46, AY6:AY46, INDIRECT("AE" & ROW()), AP6:AP46, "💲", AS6:AS46, "Empleado") + SUMIFS(AR6:AR46, AY6:AY46, INDIRECT("AE" & ROW()), AP6:AP46, "📦", AS6:AS46, "Empleado") ) / 2 ) - ( ( SUMIFS(AR6:AR46, AY6:AY46, INDIRECT("AE" & ROW()), AP6:AP46, "💲", AS6:AS46, "Exonerado ADH") + SUMIFS(AR6:AR46, AY6:AY46, INDIRECT("AE" & ROW()), AP6:AP46, "📦", AS6:AS46, "Exonerado ADH") ) / 2 ) - ( SUMIFS(AR6:AR46, AY6:AY46, INDIRECT("AE" & ROW()), AP6:AP46, "💲", AS6:AS46, "Exonerado Doctor") + SUMIFS(AR6:AR46, AY6:AY46, INDIRECT("AE" & ROW()), AP6:AP46, "📦", AS6:AS46, "Exonerado Doctor") ) - ( ( SUMIFS(AR6:AR46, AY6:AY46, INDIRECT("AE" & ROW()), AP6:AP46, "💲", AS6:AS46, "") + SUMIFS(AR6:AR46, AY6:AY46, INDIRECT("AE" & ROW()), AP6:AP46, "📦", AS6:AS46, "") ) / 2 )} -> 0
A50: =A46+$Q$13/1440 -> 0.79166667 | E50: Representante: | F50: =IF(D50<>"", VLOOKUP(D50,'Base de Datos'!$A$2:$D1268,2,FALSE()),"") | I50: Representante: | J50: =IF(H50<>"", VLOOKUP(H50,'Base de Datos'!$A$2:$D1268,2,FALSE()),"") | M50: Representante: | N50: =IF(L50<>"", VLOOKUP(L50,'Base de Datos'!$A$2:$D1268,2,FALSE()),"") | T50: Precio: | X50: Precio: | AB50: Precio: | AE50: Odo. Geraldine Cabrera | AG50: {=COUNTIFS(AP6:AP46, "💲", AY6:AY46, INDIRECT("AE" & ROW())) + COUNTIFS(AP6:AP46, "📦", AY6:AY46, INDIRECT("AE" & ROW())) + COUNTIFS(AP6:AP46, "✅", AY6:AY46, INDIRECT("AE" & ROW()))} -> 0 | AH50: {=COUNTIFS(AP6:AP46, "💲", AY6:AY46, INDIRECT("AE" & ROW())) + COUNTIFS(AP6:AP46, "📦", AY6:AY46, INDIRECT("AE" & ROW()))} -> 0 | AI50: {=SUMIFS(AR6:AR46, AY6:AY46, INDIRECT("AE" & ROW()), AP6:AP46, "💲") + SUMIFS(AR6:AR46, AY6:AY46, INDIRECT("AE" & ROW()), AP6:AP46, "📦")} -> 0 | AJ50: {=( SUMIFS(AR6:AR46, AY6:AY46, INDIRECT("AE" & ROW()), AP6:AP46, "💲") + SUMIFS(AR6:AR46, AY6:AY46, INDIRECT("AE" & ROW()), AP6:AP46, "📦") ) - ( SUMIFS(AR6:AR46, AY6:AY46, INDIRECT("AE" & ROW()), AP6:AP46, "💲", AS6:AS46, "Participante") + SUMIFS(AR6:AR46, AY6:AY46, INDIRECT("AE" & ROW()), AP6:AP46, "📦", AS6:AS46, "Participante") ) - ( SUMIFS(AR6:AR46, AY6:AY46, INDIRECT("AE" & ROW()), AP6:AP46, "💲", AS6:AS46, "Empleado") + SUMIFS(AR6:AR46, AY6:AY46, INDIRECT("AE" & ROW()), AP6:AP46, "📦", AS6:AS46, "Empleado") ) - ( ( SUMIFS(AR6:AR46, AY6:AY46, INDIRECT("AE" & ROW()), AP6:AP46, "💲", AS6:AS46, "Familiar") + SUMIFS(AR6:AR46, AY6:AY46, INDIRECT("AE" & ROW()), AP6:AP46, "📦", AS6:AS46, "Familiar") ) / 2 ) - ( ( SUMIFS(AR6:AR46, AY6:AY46, INDIRECT("AE" & ROW()), AP6:AP46, "💲", AS6:AS46, "Exonerado ADH") + SUMIFS(AR6:AR46, AY6:AY46, INDIRECT("AE" & ROW()), AP6:AP46, "📦", AS6:AS46, "Exonerado ADH") ) / 2 ) - ( ( SUMIFS(AR6:AR46, AY6:AY46, INDIRECT("AE" & ROW()), AP6:AP46, "💲", AS6:AS46, "Exonerado Doctor") + SUMIFS(AR6:AR46, AY6:AY46, INDIRECT("AE" & ROW()), AP6:AP46, "📦", AS6:AS46, "Exonerado Doctor") ) / 2 )} -> 0 | AK50: {=( SUMIFS(AR6:AR46, AY6:AY46, INDIRECT("AE" & ROW()), AP6:AP46, "💲") + SUMIFS(AR6:AR46, AY6:AY46, INDIRECT("AE" & ROW()), AP6:AP46, "📦") ) - ( SUMIFS(AR6:AR46, AY6:AY46, INDIRECT("AE" & ROW()), AP6:AP46, "💲", AS6:AS46, "Familiar") + SUMIFS(AR6:AR46, AY6:AY46, INDIRECT("AE" & ROW()), AP6:AP46, "📦", AS6:AS46, "Familiar") ) - ( SUMIFS(AR6:AR46, AY6:AY46, INDIRECT("AE" & ROW()), AP6:AP46, "💲", AS6:AS46, "Participante") + SUMIFS(AR6:AR46, AY6:AY46, INDIRECT("AE" & ROW()), AP6:AP46, "📦", AS6:AS46, "Participante") ) - ( SUMIFS(AR6:AR46, AY6:AY46, INDIRECT("AE" & ROW()), AP6:AP46, "💲", AS6:AS46, "Empleado") + SUMIFS(AR6:AR46, AY6:AY46, INDIRECT("AE" & ROW()), AP6:AP46, "📦", AS6:AS46, "Empleado") ) - ( SUMIFS(AR6:AR46, AY6:AY46, INDIRECT("AE" & ROW()), AP6:AP46, "💲", AS6:AS46, "Exonerado ADH") + SUMIFS(AR6:AR46, AY6:AY46, INDIRECT("AE" & ROW()), AP6:AP46, "📦", AS6:AS46, "Exonerado ADH") ) - ( ( SUMIFS(AR6:AR46, AY6:AY46, INDIRECT("AE" & ROW()), AP6:AP46, "💲", AS6:AS46, "Exonerado Doctor") + SUMIFS(AR6:AR46, AY6:AY46, INDIRECT("AE" & ROW()), AP6:AP46, "📦", AS6:AS46, "Exonerado Doctor") ) / 2 ) - ( ( SUMIFS(AR6:AR46, AY6:AY46, INDIRECT("AE" & ROW()), AP6:AP46, "💲", AS6:AS46, "") + SUMIFS(AR6:AR46, AY6:AY46, INDIRECT("AE" & ROW()), AP6:AP46, "📦", AS6:AS46, "") ) / 2 )} -> 0 | AL50: {=( SUMIFS(AR6:AR46, AY6:AY46, INDIRECT("AE" & ROW()), AP6:AP46, "💲") + SUMIFS(AR6:AR46, AY6:AY46, INDIRECT("AE" & ROW()), AP6:AP46, "📦") ) - ( ( SUMIFS(AR6:AR46, AY6:AY46, INDIRECT("AE" & ROW()), AP6:AP46, "💲", AS6:AS46, "Familiar") + SUMIFS(AR6:AR46, AY6:AY46, INDIRECT("AE" & ROW()), AP6:AP46, "📦", AS6:AS46, "Familiar") ) / 2 ) - ( ( SUMIFS(AR6:AR46, AY6:AY46, INDIRECT("AE" & ROW()), AP6:AP46, "💲", AS6:AS46, "Participante") + SUMIFS(AR6:AR46, AY6:AY46, INDIRECT("AE" & ROW()), AP6:AP46, "📦", AS6:AS46, "Participante") ) / 2 ) - ( ( SUMIFS(AR6:AR46, AY6:AY46, INDIRECT("AE" & ROW()), AP6:AP46, "💲", AS6:AS46, "Empleado") + SUMIFS(AR6:AR46, AY6:AY46, INDIRECT("AE" & ROW()), AP6:AP46, "📦", AS6:AS46, "Empleado") ) / 2 ) - ( ( SUMIFS(AR6:AR46, AY6:AY46, INDIRECT("AE" & ROW()), AP6:AP46, "💲", AS6:AS46, "Exonerado ADH") + SUMIFS(AR6:AR46, AY6:AY46, INDIRECT("AE" & ROW()), AP6:AP46, "📦", AS6:AS46, "Exonerado ADH") ) / 2 ) - ( SUMIFS(AR6:AR46, AY6:AY46, INDIRECT("AE" & ROW()), AP6:AP46, "💲", AS6:AS46, "Exonerado Doctor") + SUMIFS(AR6:AR46, AY6:AY46, INDIRECT("AE" & ROW()), AP6:AP46, "📦", AS6:AS46, "Exonerado Doctor") ) - ( ( SUMIFS(AR6:AR46, AY6:AY46, INDIRECT("AE" & ROW()), AP6:AP46, "💲", AS6:AS46, "") + SUMIFS(AR6:AR46, AY6:AY46, INDIRECT("AE" & ROW()), AP6:AP46, "📦", AS6:AS46, "") ) / 2 )} -> 0
E51: Teléfono: | F51: =IF(D50<>"", VLOOKUP(D50,'Base de Datos'!$A$2:$D1268,3,FALSE()),"") | I51: Teléfono: | J51: =IF(H50<>"", VLOOKUP(H50,'Base de Datos'!$A$2:$D1268,3,FALSE()),"") | M51: Teléfono: | N51: =IF(L50<>"", VLOOKUP(L50,'Base de Datos'!$A$2:$D1268,3,FALSE()),"") | AE51: Luzmir Fagúndez | AG51: {=COUNTIFS(AP6:AP46, "💲", AY6:AY46, INDIRECT("AE" & ROW())) + COUNTIFS(AP6:AP46, "📦", AY6:AY46, INDIRECT("AE" & ROW())) + COUNTIFS(AP6:AP46, "✅", AY6:AY46, INDIRECT("AE" & ROW()))} -> 0 | AH51: {=COUNTIFS(AP6:AP46, "💲", AY6:AY46, INDIRECT("AE" & ROW())) + COUNTIFS(AP6:AP46, "📦", AY6:AY46, INDIRECT("AE" & ROW()))} -> 0 | AI51: {=SUMIFS(AR6:AR46, AY6:AY46, INDIRECT("AE" & ROW()), AP6:AP46, "💲") + SUMIFS(AR6:AR46, AY6:AY46, INDIRECT("AE" & ROW()), AP6:AP46, "📦")} -> 0 | AJ51: {=( SUMIFS(AR6:AR46, AY6:AY46, INDIRECT("AE" & ROW()), AP6:AP46, "💲") + SUMIFS(AR6:AR46, AY6:AY46, INDIRECT("AE" & ROW()), AP6:AP46, "📦") ) - ( SUMIFS(AR6:AR46, AY6:AY46, INDIRECT("AE" & ROW()), AP6:AP46, "💲", AS6:AS46, "Participante") + SUMIFS(AR6:AR46, AY6:AY46, INDIRECT("AE" & ROW()), AP6:AP46, "📦", AS6:AS46, "Participante") ) - ( SUMIFS(AR6:AR46, AY6:AY46, INDIRECT("AE" & ROW()), AP6:AP46, "💲", AS6:AS46, "Empleado") + SUMIFS(AR6:AR46, AY6:AY46, INDIRECT("AE" & ROW()), AP6:AP46, "📦", AS6:AS46, "Empleado") ) - ( ( SUMIFS(AR6:AR46, AY6:AY46, INDIRECT("AE" & ROW()), AP6:AP46, "💲", AS6:AS46, "Familiar") + SUMIFS(AR6:AR46, AY6:AY46, INDIRECT("AE" & ROW()), AP6:AP46, "📦", AS6:AS46, "Familiar") ) / 2 ) - ( ( SUMIFS(AR6:AR46, AY6:AY46, INDIRECT("AE" & ROW()), AP6:AP46, "💲", AS6:AS46, "Exonerado ADH") + SUMIFS(AR6:AR46, AY6:AY46, INDIRECT("AE" & ROW()), AP6:AP46, "📦", AS6:AS46, "Exonerado ADH") ) / 2 ) - ( ( SUMIFS(AR6:AR46, AY6:AY46, INDIRECT("AE" & ROW()), AP6:AP46, "💲", AS6:AS46, "Exonerado Doctor") + SUMIFS(AR6:AR46, AY6:AY46, INDIRECT("AE" & ROW()), AP6:AP46, "📦", AS6:AS46, "Exonerado Doctor") ) / 2 )} -> 0 | AK51: {=( SUMIFS(AR6:AR46, AY6:AY46, INDIRECT("AE" & ROW()), AP6:AP46, "💲") + SUMIFS(AR6:AR46, AY6:AY46, INDIRECT("AE" & ROW()), AP6:AP46, "📦") ) - ( SUMIFS(AR6:AR46, AY6:AY46, INDIRECT("AE" & ROW()), AP6:AP46, "💲", AS6:AS46, "Familiar") + SUMIFS(AR6:AR46, AY6:AY46, INDIRECT("AE" & ROW()), AP6:AP46, "📦", AS6:AS46, "Familiar") ) - ( SUMIFS(AR6:AR46, AY6:AY46, INDIRECT("AE" & ROW()), AP6:AP46, "💲", AS6:AS46, "Participante") + SUMIFS(AR6:AR46, AY6:AY46, INDIRECT("AE" & ROW()), AP6:AP46, "📦", AS6:AS46, "Participante") ) - ( SUMIFS(AR6:AR46, AY6:AY46, INDIRECT("AE" & ROW()), AP6:AP46, "💲", AS6:AS46, "Empleado") + SUMIFS(AR6:AR46, AY6:AY46, INDIRECT("AE" & ROW()), AP6:AP46, "📦", AS6:AS46, "Empleado") ) - ( SUMIFS(AR6:AR46, AY6:AY46, INDIRECT("AE" & ROW()), AP6:AP46, "💲", AS6:AS46, "Exonerado ADH") + SUMIFS(AR6:AR46, AY6:AY46, INDIRECT("AE" & ROW()), AP6:AP46, "📦", AS6:AS46, "Exonerado ADH") ) - ( ( SUMIFS(AR6:AR46, AY6:AY46, INDIRECT("AE" & ROW()), AP6:AP46, "💲", AS6:AS46, "Exonerado Doctor") + SUMIFS(AR6:AR46, AY6:AY46, INDIRECT("AE" & ROW()), AP6:AP46, "📦", AS6:AS46, "Exonerado Doctor") ) / 2 ) - ( ( SUMIFS(AR6:AR46, AY6:AY46, INDIRECT("AE" & ROW()), AP6:AP46, "💲", AS6:AS46, "") + SUMIFS(AR6:AR46, AY6:AY46, INDIRECT("AE" & ROW()), AP6:AP46, "📦", AS6:AS46, "") ) / 2 )} -> 0 | AL51: {=( SUMIFS(AR6:AR46, AY6:AY46, INDIRECT("AE" & ROW()), AP6:AP46, "💲") + SUMIFS(AR6:AR46, AY6:AY46, INDIRECT("AE" & ROW()), AP6:AP46, "📦") ) - ( ( SUMIFS(AR6:AR46, AY6:AY46, INDIRECT("AE" & ROW()), AP6:AP46, "💲", AS6:AS46, "Familiar") + SUMIFS(AR6:AR46, AY6:AY46, INDIRECT("AE" & ROW()), AP6:AP46, "📦", AS6:AS46, "Familiar") ) / 2 ) - ( ( SUMIFS(AR6:AR46, AY6:AY46, INDIRECT("AE" & ROW()), AP6:AP46, "💲", AS6:AS46, "Participante") + SUMIFS(AR6:AR46, AY6:AY46, INDIRECT("AE" & ROW()), AP6:AP46, "📦", AS6:AS46, "Participante") ) / 2 ) - ( ( SUMIFS(AR6:AR46, AY6:AY46, INDIRECT("AE" & ROW()), AP6:AP46, "💲", AS6:AS46, "Empleado") + SUMIFS(AR6:AR46, AY6:AY46, INDIRECT("AE" & ROW()), AP6:AP46, "📦", AS6:AS46, "Empleado") ) / 2 ) - ( ( SUMIFS(AR6:AR46, AY6:AY46, INDIRECT("AE" & ROW()), AP6:AP46, "💲", AS6:AS46, "Exonerado ADH") + SUMIFS(AR6:AR46, AY6:AY46, INDIRECT("AE" & ROW()), AP6:AP46, "📦", AS6:AS46, "Exonerado ADH") ) / 2 ) - ( SUMIFS(AR6:AR46, AY6:AY46, INDIRECT("AE" & ROW()), AP6:AP46, "💲", AS6:AS46, "Exonerado Doctor") + SUMIFS(AR6:AR46, AY6:AY46, INDIRECT("AE" & ROW()), AP6:AP46, "📦", AS6:AS46, "Exonerado Doctor") ) - ( ( SUMIFS(AR6:AR46, AY6:AY46, INDIRECT("AE" & ROW()), AP6:AP46, "💲", AS6:AS46, "") + SUMIFS(AR6:AR46, AY6:AY46, INDIRECT("AE" & ROW()), AP6:AP46, "📦", AS6:AS46, "") ) / 2 )} -> 0
E52: Cedula: | F52: =IF(D50<>"", VLOOKUP(D50,'Base de Datos'!$A$2:$D1268,4,FALSE()),"") | I52: Cedula: | J52: =IF(H50<>"", VLOOKUP(H50,'Base de Datos'!$A$2:$D1268,4,FALSE()),"") | M52: Cedula: | N52: =IF(L50<>"", VLOOKUP(L50,'Base de Datos'!$A$2:$D1268,4,FALSE()),"") | AE52: Dra. Mariana Morales | AG52: {=COUNTIFS(AP6:AP46, "💲", AY6:AY46, INDIRECT("AE" & ROW())) + COUNTIFS(AP6:AP46, "📦", AY6:AY46, INDIRECT("AE" & ROW())) + COUNTIFS(AP6:AP46, "✅", AY6:AY46, INDIRECT("AE" & ROW()))} -> 0 | AH52: {=COUNTIFS(AP6:AP46, "💲", AY6:AY46, INDIRECT("AE" & ROW())) + COUNTIFS(AP6:AP46, "📦", AY6:AY46, INDIRECT("AE" & ROW()))} -> 0 | AI52: {=SUMIFS(AR6:AR46, AY6:AY46, INDIRECT("AE" & ROW()), AP6:AP46, "💲") + SUMIFS(AR6:AR46, AY6:AY46, INDIRECT("AE" & ROW()), AP6:AP46, "📦")} -> 0 | AJ52: {=( SUMIFS(AR6:AR46, AY6:AY46, INDIRECT("AE" & ROW()), AP6:AP46, "💲") + SUMIFS(AR6:AR46, AY6:AY46, INDIRECT("AE" & ROW()), AP6:AP46, "📦") ) - ( SUMIFS(AR6:AR46, AY6:AY46, INDIRECT("AE" & ROW()), AP6:AP46, "💲", AS6:AS46, "Participante") + SUMIFS(AR6:AR46, AY6:AY46, INDIRECT("AE" & ROW()), AP6:AP46, "📦", AS6:AS46, "Participante") ) - ( SUMIFS(AR6:AR46, AY6:AY46, INDIRECT("AE" & ROW()), AP6:AP46, "💲", AS6:AS46, "Empleado") + SUMIFS(AR6:AR46, AY6:AY46, INDIRECT("AE" & ROW()), AP6:AP46, "📦", AS6:AS46, "Empleado") ) - ( ( SUMIFS(AR6:AR46, AY6:AY46, INDIRECT("AE" & ROW()), AP6:AP46, "💲", AS6:AS46, "Familiar") + SUMIFS(AR6:AR46, AY6:AY46, INDIRECT("AE" & ROW()), AP6:AP46, "📦", AS6:AS46, "Familiar") ) / 2 ) - ( ( SUMIFS(AR6:AR46, AY6:AY46, INDIRECT("AE" & ROW()), AP6:AP46, "💲", AS6:AS46, "Exonerado ADH") + SUMIFS(AR6:AR46, AY6:AY46, INDIRECT("AE" & ROW()), AP6:AP46, "📦", AS6:AS46, "Exonerado ADH") ) / 2 ) - ( ( SUMIFS(AR6:AR46, AY6:AY46, INDIRECT("AE" & ROW()), AP6:AP46, "💲", AS6:AS46, "Exonerado Doctor") + SUMIFS(AR6:AR46, AY6:AY46, INDIRECT("AE" & ROW()), AP6:AP46, "📦", AS6:AS46, "Exonerado Doctor") ) / 2 )} -> 0 | AK52: {=( SUMIFS(AR6:AR46, AY6:AY46, INDIRECT("AE" & ROW()), AP6:AP46, "💲") + SUMIFS(AR6:AR46, AY6:AY46, INDIRECT("AE" & ROW()), AP6:AP46, "📦") ) - ( SUMIFS(AR6:AR46, AY6:AY46, INDIRECT("AE" & ROW()), AP6:AP46, "💲", AS6:AS46, "Familiar") + SUMIFS(AR6:AR46, AY6:AY46, INDIRECT("AE" & ROW()), AP6:AP46, "📦", AS6:AS46, "Familiar") ) - ( SUMIFS(AR6:AR46, AY6:AY46, INDIRECT("AE" & ROW()), AP6:AP46, "💲", AS6:AS46, "Participante") + SUMIFS(AR6:AR46, AY6:AY46, INDIRECT("AE" & ROW()), AP6:AP46, "📦", AS6:AS46, "Participante") ) - ( SUMIFS(AR6:AR46, AY6:AY46, INDIRECT("AE" & ROW()), AP6:AP46, "💲", AS6:AS46, "Empleado") + SUMIFS(AR6:AR46, AY6:AY46, INDIRECT("AE" & ROW()), AP6:AP46, "📦", AS6:AS46, "Empleado") ) - ( SUMIFS(AR6:AR46, AY6:AY46, INDIRECT("AE" & ROW()), AP6:AP46, "💲", AS6:AS46, "Exonerado ADH") + SUMIFS(AR6:AR46, AY6:AY46, INDIRECT("AE" & ROW()), AP6:AP46, "📦", AS6:AS46, "Exonerado ADH") ) - ( ( SUMIFS(AR6:AR46, AY6:AY46, INDIRECT("AE" & ROW()), AP6:AP46, "💲", AS6:AS46, "Exonerado Doctor") + SUMIFS(AR6:AR46, AY6:AY46, INDIRECT("AE" & ROW()), AP6:AP46, "📦", AS6:AS46, "Exonerado Doctor") ) / 2 ) - ( ( SUMIFS(AR6:AR46, AY6:AY46, INDIRECT("AE" & ROW()), AP6:AP46, "💲", AS6:AS46, "") + SUMIFS(AR6:AR46, AY6:AY46, INDIRECT("AE" & ROW()), AP6:AP46, "📦", AS6:AS46, "") ) / 2 )} -> 0 | AL52: {=( SUMIFS(AR6:AR46, AY6:AY46, INDIRECT("AE" & ROW()), AP6:AP46, "💲") + SUMIFS(AR6:AR46, AY6:AY46, INDIRECT("AE" & ROW()), AP6:AP46, "📦") ) - ( ( SUMIFS(AR6:AR46, AY6:AY46, INDIRECT("AE" & ROW()), AP6:AP46, "💲", AS6:AS46, "Familiar") + SUMIFS(AR6:AR46, AY6:AY46, INDIRECT("AE" & ROW()), AP6:AP46, "📦", AS6:AS46, "Familiar") ) / 2 ) - ( ( SUMIFS(AR6:AR46, AY6:AY46, INDIRECT("AE" & ROW()), AP6:AP46, "💲", AS6:AS46, "Participante") + SUMIFS(AR6:AR46, AY6:AY46, INDIRECT("AE" & ROW()), AP6:AP46, "📦", AS6:AS46, "Participante") ) / 2 ) - ( ( SUMIFS(AR6:AR46, AY6:AY46, INDIRECT("AE" & ROW()), AP6:AP46, "💲", AS6:AS46, "Empleado") + SUMIFS(AR6:AR46, AY6:AY46, INDIRECT("AE" & ROW()), AP6:AP46, "📦", AS6:AS46, "Empleado") ) / 2 ) - ( ( SUMIFS(AR6:AR46, AY6:AY46, INDIRECT("AE" & ROW()), AP6:AP46, "💲", AS6:AS46, "Exonerado ADH") + SUMIFS(AR6:AR46, AY6:AY46, INDIRECT("AE" & ROW()), AP6:AP46, "📦", AS6:AS46, "Exonerado ADH") ) / 2 ) - ( SUMIFS(AR6:AR46, AY6:AY46, INDIRECT("AE" & ROW()), AP6:AP46, "💲", AS6:AS46, "Exonerado Doctor") + SUMIFS(AR6:AR46, AY6:AY46, INDIRECT("AE" & ROW()), AP6:AP46, "📦", AS6:AS46, "Exonerado Doctor") ) - ( ( SUMIFS(AR6:AR46, AY6:AY46, INDIRECT("AE" & ROW()), AP6:AP46, "💲", AS6:AS46, "") + SUMIFS(AR6:AR46, AY6:AY46, INDIRECT("AE" & ROW()), AP6:AP46, "📦", AS6:AS46, "") ) / 2 )} -> 0
E53: Doctor: | I53: Doctor: | M53: Doctor: | S53: =IF(OR(S50="Empleado",S50="Familiar"),"Nombre del Empleado","N° Factura") -> N° Factura | W53: =IF(OR(W50="Empleado",W50="Familiar"),"Nombre del Empleado","N° Factura") -> N° Factura | AA53: =IF(OR(AA50="Empleado",AA50="Familiar"),"Nombre del Empleado","N° Factura") -> N° Factura | AE53: Dra. Evelyn Tranchino | AG53: {=COUNTIFS(AP6:AP46, "💲", AY6:AY46, INDIRECT("AE" & ROW())) + COUNTIFS(AP6:AP46, "📦", AY6:AY46, INDIRECT("AE" & ROW())) + COUNTIFS(AP6:AP46, "✅", AY6:AY46, INDIRECT("AE" & ROW()))} -> 0 | AH53: {=COUNTIFS(AP6:AP46, "💲", AY6:AY46, INDIRECT("AE" & ROW())) + COUNTIFS(AP6:AP46, "📦", AY6:AY46, INDIRECT("AE" & ROW()))} -> 0 | AI53: {=SUMIFS(AR6:AR46, AY6:AY46, INDIRECT("AE" & ROW()), AP6:AP46, "💲") + SUMIFS(AR6:AR46, AY6:AY46, INDIRECT("AE" & ROW()), AP6:AP46, "📦")} -> 0 | AJ53: {=( SUMIFS(AR6:AR46, AY6:AY46, INDIRECT("AE" & ROW()), AP6:AP46, "💲") + SUMIFS(AR6:AR46, AY6:AY46, INDIRECT("AE" & ROW()), AP6:AP46, "📦") ) - ( SUMIFS(AR6:AR46, AY6:AY46, INDIRECT("AE" & ROW()), AP6:AP46, "💲", AS6:AS46, "Participante") + SUMIFS(AR6:AR46, AY6:AY46, INDIRECT("AE" & ROW()), AP6:AP46, "📦", AS6:AS46, "Participante") ) - ( SUMIFS(AR6:AR46, AY6:AY46, INDIRECT("AE" & ROW()), AP6:AP46, "💲", AS6:AS46, "Empleado") + SUMIFS(AR6:AR46, AY6:AY46, INDIRECT("AE" & ROW()), AP6:AP46, "📦", AS6:AS46, "Empleado") ) - ( ( SUMIFS(AR6:AR46, AY6:AY46, INDIRECT("AE" & ROW()), AP6:AP46, "💲", AS6:AS46, "Familiar") + SUMIFS(AR6:AR46, AY6:AY46, INDIRECT("AE" & ROW()), AP6:AP46, "📦", AS6:AS46, "Familiar") ) / 2 ) - ( ( SUMIFS(AR6:AR46, AY6:AY46, INDIRECT("AE" & ROW()), AP6:AP46, "💲", AS6:AS46, "Exonerado ADH") + SUMIFS(AR6:AR46, AY6:AY46, INDIRECT("AE" & ROW()), AP6:AP46, "📦", AS6:AS46, "Exonerado ADH") ) / 2 ) - ( ( SUMIFS(AR6:AR46, AY6:AY46, INDIRECT("AE" & ROW()), AP6:AP46, "💲", AS6:AS46, "Exonerado Doctor") + SUMIFS(AR6:AR46, AY6:AY46, INDIRECT("AE" & ROW()), AP6:AP46, "📦", AS6:AS46, "Exonerado Doctor") ) / 2 )} -> 0 | AK53: {=( SUMIFS(AR6:AR46, AY6:AY46, INDIRECT("AE" & ROW()), AP6:AP46, "💲") + SUMIFS(AR6:AR46, AY6:AY46, INDIRECT("AE" & ROW()), AP6:AP46, "📦") ) - ( SUMIFS(AR6:AR46, AY6:AY46, INDIRECT("AE" & ROW()), AP6:AP46, "💲", AS6:AS46, "Familiar") + SUMIFS(AR6:AR46, AY6:AY46, INDIRECT("AE" & ROW()), AP6:AP46, "📦", AS6:AS46, "Familiar") ) - ( SUMIFS(AR6:AR46, AY6:AY46, INDIRECT("AE" & ROW()), AP6:AP46, "💲", AS6:AS46, "Participante") + SUMIFS(AR6:AR46, AY6:AY46, INDIRECT("AE" & ROW()), AP6:AP46, "📦", AS6:AS46, "Participante") ) - ( SUMIFS(AR6:AR46, AY6:AY46, INDIRECT("AE" & ROW()), AP6:AP46, "💲", AS6:AS46, "Empleado") + SUMIFS(AR6:AR46, AY6:AY46, INDIRECT("AE" & ROW()), AP6:AP46, "📦", AS6:AS46, "Empleado") ) - ( SUMIFS(AR6:AR46, AY6:AY46, INDIRECT("AE" & ROW()), AP6:AP46, "💲", AS6:AS46, "Exonerado ADH") + SUMIFS(AR6:AR46, AY6:AY46, INDIRECT("AE" & ROW()), AP6:AP46, "📦", AS6:AS46, "Exonerado ADH") ) - ( ( SUMIFS(AR6:AR46, AY6:AY46, INDIRECT("AE" & ROW()), AP6:AP46, "💲", AS6:AS46, "Exonerado Doctor") + SUMIFS(AR6:AR46, AY6:AY46, INDIRECT("AE" & ROW()), AP6:AP46, "📦", AS6:AS46, "Exonerado Doctor") ) / 2 ) - ( ( SUMIFS(AR6:AR46, AY6:AY46, INDIRECT("AE" & ROW()), AP6:AP46, "💲", AS6:AS46, "") + SUMIFS(AR6:AR46, AY6:AY46, INDIRECT("AE" & ROW()), AP6:AP46, "📦", AS6:AS46, "") ) / 2 )} -> 0 | AL53: {=( SUMIFS(AR6:AR46, AY6:AY46, INDIRECT("AE" & ROW()), AP6:AP46, "💲") + SUMIFS(AR6:AR46, AY6:AY46, INDIRECT("AE" & ROW()), AP6:AP46, "📦") ) - ( ( SUMIFS(AR6:AR46, AY6:AY46, INDIRECT("AE" & ROW()), AP6:AP46, "💲", AS6:AS46, "Familiar") + SUMIFS(AR6:AR46, AY6:AY46, INDIRECT("AE" & ROW()), AP6:AP46, "📦", AS6:AS46, "Familiar") ) / 2 ) - ( ( SUMIFS(AR6:AR46, AY6:AY46, INDIRECT("AE" & ROW()), AP6:AP46, "💲", AS6:AS46, "Participante") + SUMIFS(AR6:AR46, AY6:AY46, INDIRECT("AE" & ROW()), AP6:AP46, "📦", AS6:AS46, "Participante") ) / 2 ) - ( ( SUMIFS(AR6:AR46, AY6:AY46, INDIRECT("AE" & ROW()), AP6:AP46, "💲", AS6:AS46, "Empleado") + SUMIFS(AR6:AR46, AY6:AY46, INDIRECT("AE" & ROW()), AP6:AP46, "📦", AS6:AS46, "Empleado") ) / 2 ) - ( ( SUMIFS(AR6:AR46, AY6:AY46, INDIRECT("AE" & ROW()), AP6:AP46, "💲", AS6:AS46, "Exonerado ADH") + SUMIFS(AR6:AR46, AY6:AY46, INDIRECT("AE" & ROW()), AP6:AP46, "📦", AS6:AS46, "Exonerado ADH") ) / 2 ) - ( SUMIFS(AR6:AR46, AY6:AY46, INDIRECT("AE" & ROW()), AP6:AP46, "💲", AS6:AS46, "Exonerado Doctor") + SUMIFS(AR6:AR46, AY6:AY46, INDIRECT("AE" & ROW()), AP6:AP46, "📦", AS6:AS46, "Exonerado Doctor") ) - ( ( SUMIFS(AR6:AR46, AY6:AY46, INDIRECT("AE" & ROW()), AP6:AP46, "💲", AS6:AS46, "") + SUMIFS(AR6:AR46, AY6:AY46, INDIRECT("AE" & ROW()), AP6:AP46, "📦", AS6:AS46, "") ) / 2 )} -> 0
A54: =A50+$Q$13/1440 -> 0.83333333 | E54: Representante: | F54: =IF(D54<>"", VLOOKUP(D54,'Base de Datos'!$A$2:$D1268,2,FALSE()),"") | I54: Representante: | J54: =IF(H54<>"", VLOOKUP(H54,'Base de Datos'!$A$2:$D1268,2,FALSE()),"") | M54: Representante: | N54: =IF(L54<>"", VLOOKUP(L54,'Base de Datos'!$A$2:$D1268,2,FALSE()),"") | T54: Precio: | X54: Precio: | AB54: Precio: | AE54: Dra. Elisa Villasmil | AG54: {=COUNTIFS(AP6:AP46, "💲", AY6:AY46, INDIRECT("AE" & ROW())) + COUNTIFS(AP6:AP46, "📦", AY6:AY46, INDIRECT("AE" & ROW())) + COUNTIFS(AP6:AP46, "✅", AY6:AY46, INDIRECT("AE" & ROW()))} -> 0 | AH54: {=COUNTIFS(AP6:AP46, "💲", AY6:AY46, INDIRECT("AE" & ROW())) + COUNTIFS(AP6:AP46, "📦", AY6:AY46, INDIRECT("AE" & ROW()))} -> 0 | AI54: {=SUMIFS(AR6:AR46, AY6:AY46, INDIRECT("AE" & ROW()), AP6:AP46, "💲") + SUMIFS(AR6:AR46, AY6:AY46, INDIRECT("AE" & ROW()), AP6:AP46, "📦")} -> 0 | AJ54: {=( SUMIFS(AR6:AR46, AY6:AY46, INDIRECT("AE" & ROW()), AP6:AP46, "💲") + SUMIFS(AR6:AR46, AY6:AY46, INDIRECT("AE" & ROW()), AP6:AP46, "📦") ) - ( SUMIFS(AR6:AR46, AY6:AY46, INDIRECT("AE" & ROW()), AP6:AP46, "💲", AS6:AS46, "Participante") + SUMIFS(AR6:AR46, AY6:AY46, INDIRECT("AE" & ROW()), AP6:AP46, "📦", AS6:AS46, "Participante") ) - ( SUMIFS(AR6:AR46, AY6:AY46, INDIRECT("AE" & ROW()), AP6:AP46, "💲", AS6:AS46, "Empleado") + SUMIFS(AR6:AR46, AY6:AY46, INDIRECT("AE" & ROW()), AP6:AP46, "📦", AS6:AS46, "Empleado") ) - ( ( SUMIFS(AR6:AR46, AY6:AY46, INDIRECT("AE" & ROW()), AP6:AP46, "💲", AS6:AS46, "Familiar") + SUMIFS(AR6:AR46, AY6:AY46, INDIRECT("AE" & ROW()), AP6:AP46, "📦", AS6:AS46, "Familiar") ) / 2 ) - ( ( SUMIFS(AR6:AR46, AY6:AY46, INDIRECT("AE" & ROW()), AP6:AP46, "💲", AS6:AS46, "Exonerado ADH") + SUMIFS(AR6:AR46, AY6:AY46, INDIRECT("AE" & ROW()), AP6:AP46, "📦", AS6:AS46, "Exonerado ADH") ) / 2 ) - ( ( SUMIFS(AR6:AR46, AY6:AY46, INDIRECT("AE" & ROW()), AP6:AP46, "💲", AS6:AS46, "Exonerado Doctor") + SUMIFS(AR6:AR46, AY6:AY46, INDIRECT("AE" & ROW()), AP6:AP46, "📦", AS6:AS46, "Exonerado Doctor") ) / 2 )} -> 0 | AK54: {=( SUMIFS(AR6:AR46, AY6:AY46, INDIRECT("AE" & ROW()), AP6:AP46, "💲") + SUMIFS(AR6:AR46, AY6:AY46, INDIRECT("AE" & ROW()), AP6:AP46, "📦") ) - ( SUMIFS(AR6:AR46, AY6:AY46, INDIRECT("AE" & ROW()), AP6:AP46, "💲", AS6:AS46, "Familiar") + SUMIFS(AR6:AR46, AY6:AY46, INDIRECT("AE" & ROW()), AP6:AP46, "📦", AS6:AS46, "Familiar") ) - ( SUMIFS(AR6:AR46, AY6:AY46, INDIRECT("AE" & ROW()), AP6:AP46, "💲", AS6:AS46, "Participante") + SUMIFS(AR6:AR46, AY6:AY46, INDIRECT("AE" & ROW()), AP6:AP46, "📦", AS6:AS46, "Participante") ) - ( SUMIFS(AR6:AR46, AY6:AY46, INDIRECT("AE" & ROW()), AP6:AP46, "💲", AS6:AS46, "Empleado") + SUMIFS(AR6:AR46, AY6:AY46, INDIRECT("AE" & ROW()), AP6:AP46, "📦", AS6:AS46, "Empleado") ) - ( SUMIFS(AR6:AR46, AY6:AY46, INDIRECT("AE" & ROW()), AP6:AP46, "💲", AS6:AS46, "Exonerado ADH") + SUMIFS(AR6:AR46, AY6:AY46, INDIRECT("AE" & ROW()), AP6:AP46, "📦", AS6:AS46, "Exonerado ADH") ) - ( ( SUMIFS(AR6:AR46, AY6:AY46, INDIRECT("AE" & ROW()), AP6:AP46, "💲", AS6:AS46, "Exonerado Doctor") + SUMIFS(AR6:AR46, AY6:AY46, INDIRECT("AE" & ROW()), AP6:AP46, "📦", AS6:AS46, "Exonerado Doctor") ) / 2 ) - ( ( SUMIFS(AR6:AR46, AY6:AY46, INDIRECT("AE" & ROW()), AP6:AP46, "💲", AS6:AS46, "") + SUMIFS(AR6:AR46, AY6:AY46, INDIRECT("AE" & ROW()), AP6:AP46, "📦", AS6:AS46, "") ) / 2 )} -> 0 | AL54: {=( SUMIFS(AR6:AR46, AY6:AY46, INDIRECT("AE" & ROW()), AP6:AP46, "💲") + SUMIFS(AR6:AR46, AY6:AY46, INDIRECT("AE" & ROW()), AP6:AP46, "📦") ) - ( ( SUMIFS(AR6:AR46, AY6:AY46, INDIRECT("AE" & ROW()), AP6:AP46, "💲", AS6:AS46, "Familiar") + SUMIFS(AR6:AR46, AY6:AY46, INDIRECT("AE" & ROW()), AP6:AP46, "📦", AS6:AS46, "Familiar") ) / 2 ) - ( ( SUMIFS(AR6:AR46, AY6:AY46, INDIRECT("AE" & ROW()), AP6:AP46, "💲", AS6:AS46, "Participante") + SUMIFS(AR6:AR46, AY6:AY46, INDIRECT("AE" & ROW()), AP6:AP46, "📦", AS6:AS46, "Participante") ) / 2 ) - ( ( SUMIFS(AR6:AR46, AY6:AY46, INDIRECT("AE" & ROW()), AP6:AP46, "💲", AS6:AS46, "Empleado") + SUMIFS(AR6:AR46, AY6:AY46, INDIRECT("AE" & ROW()), AP6:AP46, "📦", AS6:AS46, "Empleado") ) / 2 ) - ( ( SUMIFS(AR6:AR46, AY6:AY46, INDIRECT("AE" & ROW()), AP6:AP46, "💲", AS6:AS46, "Exonerado ADH") + SUMIFS(AR6:AR46, AY6:AY46, INDIRECT("AE" & ROW()), AP6:AP46, "📦", AS6:AS46, "Exonerado ADH") ) / 2 ) - ( SUMIFS(AR6:AR46, AY6:AY46, INDIRECT("AE" & ROW()), AP6:AP46, "💲", AS6:AS46, "Exonerado Doctor") + SUMIFS(AR6:AR46, AY6:AY46, INDIRECT("AE" & ROW()), AP6:AP46, "📦", AS6:AS46, "Exonerado Doctor") ) - ( ( SUMIFS(AR6:AR46, AY6:AY46, INDIRECT("AE" & ROW()), AP6:AP46, "💲", AS6:AS46, "") + SUMIFS(AR6:AR46, AY6:AY46, INDIRECT("AE" & ROW()), AP6:AP46, "📦", AS6:AS46, "") ) / 2 )} -> 0
E55: Teléfono: | F55: =IF(D54<>"", VLOOKUP(D54,'Base de Datos'!$A$2:$D1268,3,FALSE()),"") | I55: Teléfono: | J55: =IF(H54<>"", VLOOKUP(H54,'Base de Datos'!$A$2:$D1268,3,FALSE()),"") | M55: Teléfono: | N55: =IF(L54<>"", VLOOKUP(L54,'Base de Datos'!$A$2:$D1268,3,FALSE()),"") | AE55: Dra. Elisa Izquierdo | AG55: {=COUNTIFS(AP6:AP46, "💲", AY6:AY46, INDIRECT("AE" & ROW())) + COUNTIFS(AP6:AP46, "📦", AY6:AY46, INDIRECT("AE" & ROW())) + COUNTIFS(AP6:AP46, "✅", AY6:AY46, INDIRECT("AE" & ROW()))} -> 0 | AH55: {=COUNTIFS(AP6:AP46, "💲", AY6:AY46, INDIRECT("AE" & ROW())) + COUNTIFS(AP6:AP46, "📦", AY6:AY46, INDIRECT("AE" & ROW()))} -> 0 | AI55: {=SUMIFS(AR6:AR46, AY6:AY46, INDIRECT("AE" & ROW()), AP6:AP46, "💲") + SUMIFS(AR6:AR46, AY6:AY46, INDIRECT("AE" & ROW()), AP6:AP46, "📦")} -> 0 | AJ55: {=( SUMIFS(AR6:AR46, AY6:AY46, INDIRECT("AE" & ROW()), AP6:AP46, "💲") + SUMIFS(AR6:AR46, AY6:AY46, INDIRECT("AE" & ROW()), AP6:AP46, "📦") ) - ( SUMIFS(AR6:AR46, AY6:AY46, INDIRECT("AE" & ROW()), AP6:AP46, "💲", AS6:AS46, "Participante") + SUMIFS(AR6:AR46, AY6:AY46, INDIRECT("AE" & ROW()), AP6:AP46, "📦", AS6:AS46, "Participante") ) - ( SUMIFS(AR6:AR46, AY6:AY46, INDIRECT("AE" & ROW()), AP6:AP46, "💲", AS6:AS46, "Empleado") + SUMIFS(AR6:AR46, AY6:AY46, INDIRECT("AE" & ROW()), AP6:AP46, "📦", AS6:AS46, "Empleado") ) - ( ( SUMIFS(AR6:AR46, AY6:AY46, INDIRECT("AE" & ROW()), AP6:AP46, "💲", AS6:AS46, "Familiar") + SUMIFS(AR6:AR46, AY6:AY46, INDIRECT("AE" & ROW()), AP6:AP46, "📦", AS6:AS46, "Familiar") ) / 2 ) - ( ( SUMIFS(AR6:AR46, AY6:AY46, INDIRECT("AE" & ROW()), AP6:AP46, "💲", AS6:AS46, "Exonerado ADH") + SUMIFS(AR6:AR46, AY6:AY46, INDIRECT("AE" & ROW()), AP6:AP46, "📦", AS6:AS46, "Exonerado ADH") ) / 2 ) - ( ( SUMIFS(AR6:AR46, AY6:AY46, INDIRECT("AE" & ROW()), AP6:AP46, "💲", AS6:AS46, "Exonerado Doctor") + SUMIFS(AR6:AR46, AY6:AY46, INDIRECT("AE" & ROW()), AP6:AP46, "📦", AS6:AS46, "Exonerado Doctor") ) / 2 )} -> 0 | AK55: {=( SUMIFS(AR6:AR46, AY6:AY46, INDIRECT("AE" & ROW()), AP6:AP46, "💲") + SUMIFS(AR6:AR46, AY6:AY46, INDIRECT("AE" & ROW()), AP6:AP46, "📦") ) - ( SUMIFS(AR6:AR46, AY6:AY46, INDIRECT("AE" & ROW()), AP6:AP46, "💲", AS6:AS46, "Familiar") + SUMIFS(AR6:AR46, AY6:AY46, INDIRECT("AE" & ROW()), AP6:AP46, "📦", AS6:AS46, "Familiar") ) - ( SUMIFS(AR6:AR46, AY6:AY46, INDIRECT("AE" & ROW()), AP6:AP46, "💲", AS6:AS46, "Participante") + SUMIFS(AR6:AR46, AY6:AY46, INDIRECT("AE" & ROW()), AP6:AP46, "📦", AS6:AS46, "Participante") ) - ( SUMIFS(AR6:AR46, AY6:AY46, INDIRECT("AE" & ROW()), AP6:AP46, "💲", AS6:AS46, "Empleado") + SUMIFS(AR6:AR46, AY6:AY46, INDIRECT("AE" & ROW()), AP6:AP46, "📦", AS6:AS46, "Empleado") ) - ( SUMIFS(AR6:AR46, AY6:AY46, INDIRECT("AE" & ROW()), AP6:AP46, "💲", AS6:AS46, "Exonerado ADH") + SUMIFS(AR6:AR46, AY6:AY46, INDIRECT("AE" & ROW()), AP6:AP46, "📦", AS6:AS46, "Exonerado ADH") ) - ( ( SUMIFS(AR6:AR46, AY6:AY46, INDIRECT("AE" & ROW()), AP6:AP46, "💲", AS6:AS46, "Exonerado Doctor") + SUMIFS(AR6:AR46, AY6:AY46, INDIRECT("AE" & ROW()), AP6:AP46, "📦", AS6:AS46, "Exonerado Doctor") ) / 2 ) - ( ( SUMIFS(AR6:AR46, AY6:AY46, INDIRECT("AE" & ROW()), AP6:AP46, "💲", AS6:AS46, "") + SUMIFS(AR6:AR46, AY6:AY46, INDIRECT("AE" & ROW()), AP6:AP46, "📦", AS6:AS46, "") ) / 2 )} -> 0 | AL55: {=( SUMIFS(AR6:AR46, AY6:AY46, INDIRECT("AE" & ROW()), AP6:AP46, "💲") + SUMIFS(AR6:AR46, AY6:AY46, INDIRECT("AE" & ROW()), AP6:AP46, "📦") ) - ( ( SUMIFS(AR6:AR46, AY6:AY46, INDIRECT("AE" & ROW()), AP6:AP46, "💲", AS6:AS46, "Familiar") + SUMIFS(AR6:AR46, AY6:AY46, INDIRECT("AE" & ROW()), AP6:AP46, "📦", AS6:AS46, "Familiar") ) / 2 ) - ( ( SUMIFS(AR6:AR46, AY6:AY46, INDIRECT("AE" & ROW()), AP6:AP46, "💲", AS6:AS46, "Participante") + SUMIFS(AR6:AR46, AY6:AY46, INDIRECT("AE" & ROW()), AP6:AP46, "📦", AS6:AS46, "Participante") ) / 2 ) - ( ( SUMIFS(AR6:AR46, AY6:AY46, INDIRECT("AE" & ROW()), AP6:AP46, "💲", AS6:AS46, "Empleado") + SUMIFS(AR6:AR46, AY6:AY46, INDIRECT("AE" & ROW()), AP6:AP46, "📦", AS6:AS46, "Empleado") ) / 2 ) - ( ( SUMIFS(AR6:AR46, AY6:AY46, INDIRECT("AE" & ROW()), AP6:AP46, "💲", AS6:AS46, "Exonerado ADH") + SUMIFS(AR6:AR46, AY6:AY46, INDIRECT("AE" & ROW()), AP6:AP46, "📦", AS6:AS46, "Exonerado ADH") ) / 2 ) - ( SUMIFS(AR6:AR46, AY6:AY46, INDIRECT("AE" & ROW()), AP6:AP46, "💲", AS6:AS46, "Exonerado Doctor") + SUMIFS(AR6:AR46, AY6:AY46, INDIRECT("AE" & ROW()), AP6:AP46, "📦", AS6:AS46, "Exonerado Doctor") ) - ( ( SUMIFS(AR6:AR46, AY6:AY46, INDIRECT("AE" & ROW()), AP6:AP46, "💲", AS6:AS46, "") + SUMIFS(AR6:AR46, AY6:AY46, INDIRECT("AE" & ROW()), AP6:AP46, "📦", AS6:AS46, "") ) / 2 )} -> 0
E56: Cedula: | F56: =IF(D54<>"", VLOOKUP(D54,'Base de Datos'!$A$2:$D1268,4,FALSE()),"") | I56: Cedula: | J56: =IF(H54<>"", VLOOKUP(H54,'Base de Datos'!$A$2:$D1268,4,FALSE()),"") | M56: Cedula: | N56: =IF(L54<>"", VLOOKUP(L54,'Base de Datos'!$A$2:$D1268,4,FALSE()),"") | AE56: Dra. Gabriela Berbis | AG56: {=COUNTIFS(AP6:AP46, "💲", AY6:AY46, INDIRECT("AE" & ROW())) + COUNTIFS(AP6:AP46, "📦", AY6:AY46, INDIRECT("AE" & ROW())) + COUNTIFS(AP6:AP46, "✅", AY6:AY46, INDIRECT("AE" & ROW()))} -> 0 | AH56: {=COUNTIFS(AP6:AP46, "💲", AY6:AY46, INDIRECT("AE" & ROW())) + COUNTIFS(AP6:AP46, "📦", AY6:AY46, INDIRECT("AE" & ROW()))} -> 0 | AI56: {=SUMIFS(AR6:AR46, AY6:AY46, INDIRECT("AE" & ROW()), AP6:AP46, "💲") + SUMIFS(AR6:AR46, AY6:AY46, INDIRECT("AE" & ROW()), AP6:AP46, "📦")} -> 0 | AJ56: {=( SUMIFS(AR6:AR46, AY6:AY46, INDIRECT("AE" & ROW()), AP6:AP46, "💲") + SUMIFS(AR6:AR46, AY6:AY46, INDIRECT("AE" & ROW()), AP6:AP46, "📦") ) - ( SUMIFS(AR6:AR46, AY6:AY46, INDIRECT("AE" & ROW()), AP6:AP46, "💲", AS6:AS46, "Participante") + SUMIFS(AR6:AR46, AY6:AY46, INDIRECT("AE" & ROW()), AP6:AP46, "📦", AS6:AS46, "Participante") ) - ( SUMIFS(AR6:AR46, AY6:AY46, INDIRECT("AE" & ROW()), AP6:AP46, "💲", AS6:AS46, "Empleado") + SUMIFS(AR6:AR46, AY6:AY46, INDIRECT("AE" & ROW()), AP6:AP46, "📦", AS6:AS46, "Empleado") ) - ( ( SUMIFS(AR6:AR46, AY6:AY46, INDIRECT("AE" & ROW()), AP6:AP46, "💲", AS6:AS46, "Familiar") + SUMIFS(AR6:AR46, AY6:AY46, INDIRECT("AE" & ROW()), AP6:AP46, "📦", AS6:AS46, "Familiar") ) / 2 ) - ( ( SUMIFS(AR6:AR46, AY6:AY46, INDIRECT("AE" & ROW()), AP6:AP46, "💲", AS6:AS46, "Exonerado ADH") + SUMIFS(AR6:AR46, AY6:AY46, INDIRECT("AE" & ROW()), AP6:AP46, "📦", AS6:AS46, "Exonerado ADH") ) / 2 ) - ( ( SUMIFS(AR6:AR46, AY6:AY46, INDIRECT("AE" & ROW()), AP6:AP46, "💲", AS6:AS46, "Exonerado Doctor") + SUMIFS(AR6:AR46, AY6:AY46, INDIRECT("AE" & ROW()), AP6:AP46, "📦", AS6:AS46, "Exonerado Doctor") ) / 2 )} -> 0 | AK56: {=( SUMIFS(AR6:AR46, AY6:AY46, INDIRECT("AE" & ROW()), AP6:AP46, "💲") + SUMIFS(AR6:AR46, AY6:AY46, INDIRECT("AE" & ROW()), AP6:AP46, "📦") ) - ( SUMIFS(AR6:AR46, AY6:AY46, INDIRECT("AE" & ROW()), AP6:AP46, "💲", AS6:AS46, "Familiar") + SUMIFS(AR6:AR46, AY6:AY46, INDIRECT("AE" & ROW()), AP6:AP46, "📦", AS6:AS46, "Familiar") ) - ( SUMIFS(AR6:AR46, AY6:AY46, INDIRECT("AE" & ROW()), AP6:AP46, "💲", AS6:AS46, "Participante") + SUMIFS(AR6:AR46, AY6:AY46, INDIRECT("AE" & ROW()), AP6:AP46, "📦", AS6:AS46, "Participante") ) - ( SUMIFS(AR6:AR46, AY6:AY46, INDIRECT("AE" & ROW()), AP6:AP46, "💲", AS6:AS46, "Empleado") + SUMIFS(AR6:AR46, AY6:AY46, INDIRECT("AE" & ROW()), AP6:AP46, "📦", AS6:AS46, "Empleado") ) - ( SUMIFS(AR6:AR46, AY6:AY46, INDIRECT("AE" & ROW()), AP6:AP46, "💲", AS6:AS46, "Exonerado ADH") + SUMIFS(AR6:AR46, AY6:AY46, INDIRECT("AE" & ROW()), AP6:AP46, "📦", AS6:AS46, "Exonerado ADH") ) - ( ( SUMIFS(AR6:AR46, AY6:AY46, INDIRECT("AE" & ROW()), AP6:AP46, "💲", AS6:AS46, "Exonerado Doctor") + SUMIFS(AR6:AR46, AY6:AY46, INDIRECT("AE" & ROW()), AP6:AP46, "📦", AS6:AS46, "Exonerado Doctor") ) / 2 ) - ( ( SUMIFS(AR6:AR46, AY6:AY46, INDIRECT("AE" & ROW()), AP6:AP46, "💲", AS6:AS46, "") + SUMIFS(AR6:AR46, AY6:AY46, INDIRECT("AE" & ROW()), AP6:AP46, "📦", AS6:AS46, "") ) / 2 )} -> 0 | AL56: {=( SUMIFS(AR6:AR46, AY6:AY46, INDIRECT("AE" & ROW()), AP6:AP46, "💲") + SUMIFS(AR6:AR46, AY6:AY46, INDIRECT("AE" & ROW()), AP6:AP46, "📦") ) - ( ( SUMIFS(AR6:AR46, AY6:AY46, INDIRECT("AE" & ROW()), AP6:AP46, "💲", AS6:AS46, "Familiar") + SUMIFS(AR6:AR46, AY6:AY46, INDIRECT("AE" & ROW()), AP6:AP46, "📦", AS6:AS46, "Familiar") ) / 2 ) - ( ( SUMIFS(AR6:AR46, AY6:AY46, INDIRECT("AE" & ROW()), AP6:AP46, "💲", AS6:AS46, "Participante") + SUMIFS(AR6:AR46, AY6:AY46, INDIRECT("AE" & ROW()), AP6:AP46, "📦", AS6:AS46, "Participante") ) / 2 ) - ( ( SUMIFS(AR6:AR46, AY6:AY46, INDIRECT("AE" & ROW()), AP6:AP46, "💲", AS6:AS46, "Empleado") + SUMIFS(AR6:AR46, AY6:AY46, INDIRECT("AE" & ROW()), AP6:AP46, "📦", AS6:AS46, "Empleado") ) / 2 ) - ( ( SUMIFS(AR6:AR46, AY6:AY46, INDIRECT("AE" & ROW()), AP6:AP46, "💲", AS6:AS46, "Exonerado ADH") + SUMIFS(AR6:AR46, AY6:AY46, INDIRECT("AE" & ROW()), AP6:AP46, "📦", AS6:AS46, "Exonerado ADH") ) / 2 ) - ( SUMIFS(AR6:AR46, AY6:AY46, INDIRECT("AE" & ROW()), AP6:AP46, "💲", AS6:AS46, "Exonerado Doctor") + SUMIFS(AR6:AR46, AY6:AY46, INDIRECT("AE" & ROW()), AP6:AP46, "📦", AS6:AS46, "Exonerado Doctor") ) - ( ( SUMIFS(AR6:AR46, AY6:AY46, INDIRECT("AE" & ROW()), AP6:AP46, "💲", AS6:AS46, "") + SUMIFS(AR6:AR46, AY6:AY46, INDIRECT("AE" & ROW()), AP6:AP46, "📦", AS6:AS46, "") ) / 2 )} -> 0
E57: Doctor: | I57: Doctor: | M57: Doctor: | S57: =IF(OR(S54="Empleado",S54="Familiar"),"Nombre del Empleado","N° Factura") -> N° Factura | W57: =IF(OR(W54="Empleado",W54="Familiar"),"Nombre del Empleado","N° Factura") -> N° Factura | AA57: =IF(OR(AA54="Empleado",AA54="Familiar"),"Nombre del Empleado","N° Factura") -> N° Factura | AE57: Dra. Gerlly Mendoza | AG57: {=COUNTIFS(AP6:AP46, "💲", AY6:AY46, INDIRECT("AE" & ROW())) + COUNTIFS(AP6:AP46, "📦", AY6:AY46, INDIRECT("AE" & ROW())) + COUNTIFS(AP6:AP46, "✅", AY6:AY46, INDIRECT("AE" & ROW()))} -> 0 | AH57: {=COUNTIFS(AP6:AP46, "💲", AY6:AY46, INDIRECT("AE" & ROW())) + COUNTIFS(AP6:AP46, "📦", AY6:AY46, INDIRECT("AE" & ROW()))} -> 0 | AI57: {=SUMIFS(AR6:AR46, AY6:AY46, INDIRECT("AE" & ROW()), AP6:AP46, "💲") + SUMIFS(AR6:AR46, AY6:AY46, INDIRECT("AE" & ROW()), AP6:AP46, "📦")} -> 0 | AJ57: {=( SUMIFS(AR6:AR46, AY6:AY46, INDIRECT("AE" & ROW()), AP6:AP46, "💲") + SUMIFS(AR6:AR46, AY6:AY46, INDIRECT("AE" & ROW()), AP6:AP46, "📦") ) - ( SUMIFS(AR6:AR46, AY6:AY46, INDIRECT("AE" & ROW()), AP6:AP46, "💲", AS6:AS46, "Participante") + SUMIFS(AR6:AR46, AY6:AY46, INDIRECT("AE" & ROW()), AP6:AP46, "📦", AS6:AS46, "Participante") ) - ( SUMIFS(AR6:AR46, AY6:AY46, INDIRECT("AE" & ROW()), AP6:AP46, "💲", AS6:AS46, "Empleado") + SUMIFS(AR6:AR46, AY6:AY46, INDIRECT("AE" & ROW()), AP6:AP46, "📦", AS6:AS46, "Empleado") ) - ( ( SUMIFS(AR6:AR46, AY6:AY46, INDIRECT("AE" & ROW()), AP6:AP46, "💲", AS6:AS46, "Familiar") + SUMIFS(AR6:AR46, AY6:AY46, INDIRECT("AE" & ROW()), AP6:AP46, "📦", AS6:AS46, "Familiar") ) / 2 ) - ( ( SUMIFS(AR6:AR46, AY6:AY46, INDIRECT("AE" & ROW()), AP6:AP46, "💲", AS6:AS46, "Exonerado ADH") + SUMIFS(AR6:AR46, AY6:AY46, INDIRECT("AE" & ROW()), AP6:AP46, "📦", AS6:AS46, "Exonerado ADH") ) / 2 ) - ( ( SUMIFS(AR6:AR46, AY6:AY46, INDIRECT("AE" & ROW()), AP6:AP46, "💲", AS6:AS46, "Exonerado Doctor") + SUMIFS(AR6:AR46, AY6:AY46, INDIRECT("AE" & ROW()), AP6:AP46, "📦", AS6:AS46, "Exonerado Doctor") ) / 2 )} -> 0 | AK57: {=( SUMIFS(AR6:AR46, AY6:AY46, INDIRECT("AE" & ROW()), AP6:AP46, "💲") + SUMIFS(AR6:AR46, AY6:AY46, INDIRECT("AE" & ROW()), AP6:AP46, "📦") ) - ( SUMIFS(AR6:AR46, AY6:AY46, INDIRECT("AE" & ROW()), AP6:AP46, "💲", AS6:AS46, "Familiar") + SUMIFS(AR6:AR46, AY6:AY46, INDIRECT("AE" & ROW()), AP6:AP46, "📦", AS6:AS46, "Familiar") ) - ( SUMIFS(AR6:AR46, AY6:AY46, INDIRECT("AE" & ROW()), AP6:AP46, "💲", AS6:AS46, "Participante") + SUMIFS(AR6:AR46, AY6:AY46, INDIRECT("AE" & ROW()), AP6:AP46, "📦", AS6:AS46, "Participante") ) - ( SUMIFS(AR6:AR46, AY6:AY46, INDIRECT("AE" & ROW()), AP6:AP46, "💲", AS6:AS46, "Empleado") + SUMIFS(AR6:AR46, AY6:AY46, INDIRECT("AE" & ROW()), AP6:AP46, "📦", AS6:AS46, "Empleado") ) - ( SUMIFS(AR6:AR46, AY6:AY46, INDIRECT("AE" & ROW()), AP6:AP46, "💲", AS6:AS46, "Exonerado ADH") + SUMIFS(AR6:AR46, AY6:AY46, INDIRECT("AE" & ROW()), AP6:AP46, "📦", AS6:AS46, "Exonerado ADH") ) - ( ( SUMIFS(AR6:AR46, AY6:AY46, INDIRECT("AE" & ROW()), AP6:AP46, "💲", AS6:AS46, "Exonerado Doctor") + SUMIFS(AR6:AR46, AY6:AY46, INDIRECT("AE" & ROW()), AP6:AP46, "📦", AS6:AS46, "Exonerado Doctor") ) / 2 ) - ( ( SUMIFS(AR6:AR46, AY6:AY46, INDIRECT("AE" & ROW()), AP6:AP46, "💲", AS6:AS46, "") + SUMIFS(AR6:AR46, AY6:AY46, INDIRECT("AE" & ROW()), AP6:AP46, "📦", AS6:AS46, "") ) / 2 )} -> 0 | AL57: {=( SUMIFS(AR6:AR46, AY6:AY46, INDIRECT("AE" & ROW()), AP6:AP46, "💲") + SUMIFS(AR6:AR46, AY6:AY46, INDIRECT("AE" & ROW()), AP6:AP46, "📦") ) - ( ( SUMIFS(AR6:AR46, AY6:AY46, INDIRECT("AE" & ROW()), AP6:AP46, "💲", AS6:AS46, "Familiar") + SUMIFS(AR6:AR46, AY6:AY46, INDIRECT("AE" & ROW()), AP6:AP46, "📦", AS6:AS46, "Familiar") ) / 2 ) - ( ( SUMIFS(AR6:AR46, AY6:AY46, INDIRECT("AE" & ROW()), AP6:AP46, "💲", AS6:AS46, "Participante") + SUMIFS(AR6:AR46, AY6:AY46, INDIRECT("AE" & ROW()), AP6:AP46, "📦", AS6:AS46, "Participante") ) / 2 ) - ( ( SUMIFS(AR6:AR46, AY6:AY46, INDIRECT("AE" & ROW()), AP6:AP46, "💲", AS6:AS46, "Empleado") + SUMIFS(AR6:AR46, AY6:AY46, INDIRECT("AE" & ROW()), AP6:AP46, "📦", AS6:AS46, "Empleado") ) / 2 ) - ( ( SUMIFS(AR6:AR46, AY6:AY46, INDIRECT("AE" & ROW()), AP6:AP46, "💲", AS6:AS46, "Exonerado ADH") + SUMIFS(AR6:AR46, AY6:AY46, INDIRECT("AE" & ROW()), AP6:AP46, "📦", AS6:AS46, "Exonerado ADH") ) / 2 ) - ( SUMIFS(AR6:AR46, AY6:AY46, INDIRECT("AE" & ROW()), AP6:AP46, "💲", AS6:AS46, "Exonerado Doctor") + SUMIFS(AR6:AR46, AY6:AY46, INDIRECT("AE" & ROW()), AP6:AP46, "📦", AS6:AS46, "Exonerado Doctor") ) - ( ( SUMIFS(AR6:AR46, AY6:AY46, INDIRECT("AE" & ROW()), AP6:AP46, "💲", AS6:AS46, "") + SUMIFS(AR6:AR46, AY6:AY46, INDIRECT("AE" & ROW()), AP6:AP46, "📦", AS6:AS46, "") ) / 2 )} -> 0
AI58: =SUM(AI43:AI56) -> 0 | AJ58: =SUM(AJ43:AJ56) -> 0 | AK58: =SUM(AK43:AK56) -> 0 | AL58: =SUM(AL43:AL56) -> 0
A59: =IF(WEEKDAY(A4)=6, WORKDAY(A4+1, 1), A4+1) -> 46267
A60: Hora | B60: Name | C60: Consultorio N° 1 | G60: Consultorio N° 2 | K60: Consultorio N° 3 | S60: Consultorio N° 1 | W60: Consultorio N° 2 | AA60: Consultorio N° 3 | AN60: Fecha | AO60: Consultorio | AP60: Estado | AQ60: Paciente | AR60: Precio | AS60: Tipo | AT60: Forma 1 | AU60: Monto 1 | AV60: Forma 2 | AW60: Monto 2 | AX60: Empleado | AY60: Doctor
A61: =Q67 -> 0.33333333 | E61: Representante: | F61: =IF(D61<>"", VLOOKUP(D61,'Base de Datos'!$A$2:$D1268,2,FALSE()),"") | I61: Representante: | J61: =IF(H61<>"", VLOOKUP(H61,'Base de Datos'!$A$2:$D1268,2,FALSE()),"") | M61: Representante: | N61: =IF(L61<>"", VLOOKUP(L61,'Base de Datos'!$A$2:$D1268,2,FALSE()),"") | T61: Precio: | X61: Precio: | AB61: Precio: | AN61: =A59 -> 46267 | AO61: =C60 -> Consultorio N° 1 | AP61: =C61 -> 0 | AQ61: =D61 -> 0 | AR61: =U61 -> 0 | AS61: =S61 -> 0 | AT61: =S62 -> 0 | AU61: =U62 -> 0 | AV61: =S63 -> 0 | AW61: =U63 -> 0 | AX61: =U64 -> 0 | AY61: =F64 -> 0
E62: Teléfono: | F62: =IF(D61<>"", VLOOKUP(D61,'Base de Datos'!$A$2:$D1268,3,FALSE()),"") | I62: Teléfono: | J62: =IF(H61<>"", VLOOKUP(H61,'Base de Datos'!$A$2:$D1268,3,FALSE()),"") | M62: Teléfono: | N62: =IF(L61<>"", VLOOKUP(L61,'Base de Datos'!$A$2:$D1268,3,FALSE()),"") | AN62: =A59 -> 46267 | AO62: =C60 -> Consultorio N° 1 | AP62: =C65 -> 0 | AQ62: =D65 -> 0 | AR62: =U65 -> 0 | AS62: =S65 -> 0 | AT62: =S66 -> 0 | AU62: =U66 -> 0 | AV62: =S67 -> 0 | AW62: =U67 -> 0 | AX62: =U68 -> 0 | AY62: =F68 -> 0
E63: Cedula: | F63: =IF(D61<>"", VLOOKUP(D61,'Base de Datos'!$A$2:$D1268,4,FALSE()),"") | I63: Cedula: | J63: =IF(H61<>"", VLOOKUP(H61,'Base de Datos'!$A$2:$D1268,4,FALSE()),"") | M63: Cedula: | N63: =IF(L61<>"", VLOOKUP(L61,'Base de Datos'!$A$2:$D1268,4,FALSE()),"") | AN63: =A59 -> 46267 | AO63: =C60 -> Consultorio N° 1 | AP63: =C69 -> 0 | AQ63: =D69 -> 0 | AR63: =U69 -> 0 | AS63: =S69 -> 0 | AT63: =S70 -> 0 | AU63: =U70 -> 0 | AV63: =S71 -> 0 | AW63: =U71 -> 0 | AX63: =U72 -> 0 | AY63: =F72 -> 0
E64: Doctor: | I64: Doctor: | M64: Doctor: | S64: =IF(OR(S61="Empleado",S61="Familiar"),"Nombre del Empleado","N° Factura") -> N° Factura | W64: =IF(OR(W61="Empleado",W61="Familiar"),"Nombre del Empleado","N° Factura") -> N° Factura | AA64: =IF(OR(AA61="Empleado",AA61="Familiar"),"Nombre del Empleado","N° Factura") -> N° Factura | AN64: =A59 -> 46267 | AO64: =C60 -> Consultorio N° 1 | AP64: =C73 -> 0 | AQ64: =D73 -> 0 | AR64: =U73 -> 0 | AS64: =S73 -> 0 | AT64: =S74 -> 0 | AU64: =U74 -> 0 | AV64: =S75 -> 0 | AW64: =U75 -> 0 | AX64: =U76 -> 0 | AY64: =F76 -> 0
A65: =A61+$Q$13/1440 -> 0.375 | E65: Representante: | F65: =IF(D65<>"", VLOOKUP(D65,'Base de Datos'!$A$2:$D1268,2,FALSE()),"") | I65: Representante: | J65: =IF(H65<>"", VLOOKUP(H65,'Base de Datos'!$A$2:$D1268,2,FALSE()),"") | M65: Representante: | N65: =IF(L65<>"", VLOOKUP(L65,'Base de Datos'!$A$2:$D1268,2,FALSE()),"") | O65: $ USD: | Q65: =$N$2 -> 888.8909 | T65: Precio: | X65: Precio: | AB65: Precio: | AN65: =A59 -> 46267 | AO65: =C60 -> Consultorio N° 1 | AP65: =C77 -> 0 | AQ65: =D77 -> 0 | AR65: =U77 -> 0 | AS65: =S77 -> 0 | AT65: =S78 -> 0 | AU65: =U78 -> 0 | AV65: =S79 -> 0 | AW65: =U79 -> 0 | AX65: =U80 -> 0 | AY65: =F80 -> 0
E66: Teléfono: | F66: =IF(D65<>"", VLOOKUP(D65,'Base de Datos'!$A$2:$D1268,3,FALSE()),"") | I66: Teléfono: | J66: =IF(H65<>"", VLOOKUP(H65,'Base de Datos'!$A$2:$D1268,3,FALSE()),"") | M66: Teléfono: | N66: =IF(L65<>"", VLOOKUP(L65,'Base de Datos'!$A$2:$D1268,3,FALSE()),"") | AN66: =A59 -> 46267 | AO66: =C60 -> Consultorio N° 1 | AP66: =C81 -> 0 | AQ66: =D81 -> 0 | AR66: =U81 -> 0 | AS66: =S81 -> 0 | AT66: =S82 -> 0 | AU66: =U82 -> 0 | AV66: =S83 -> 0 | AW66: =U83 -> 0 | AX66: =U84 -> 0 | AY66: =F84 -> 0
E67: Cedula: | F67: =IF(D65<>"", VLOOKUP(D65,'Base de Datos'!$A$2:$D1268,4,FALSE()),"") | I67: Cedula: | J67: =IF(H65<>"", VLOOKUP(H65,'Base de Datos'!$A$2:$D1268,4,FALSE()),"") | M67: Cedula: | N67: =IF(L65<>"", VLOOKUP(L65,'Base de Datos'!$A$2:$D1268,4,FALSE()),"") | P67: Hora de inicio | Q67: 0.33333333 | AN67: =A59 -> 46267 | AO67: =C60 -> Consultorio N° 1 | AP67: =C85 -> 0 | AQ67: =D85 -> 0 | AR67: =U85 -> 0 | AS67: =S85 -> 0 | AT67: =S86 -> 0 | AU67: =U86 -> 0 | AV67: =S87 -> 0 | AW67: =U87 -> 0 | AX67: =U88 -> 0 | AY67: =F88 -> 0
E68: Doctor: | I68: Doctor: | M68: Doctor: | P68: Intervalo | Q68: 60 | S68: =IF(OR(S65="Empleado",S65="Familiar"),"Nombre del Empleado","N° Factura") -> N° Factura | W68: =IF(OR(W65="Empleado",W65="Familiar"),"Nombre del Empleado","N° Factura") -> N° Factura | AA68: =IF(OR(AA65="Empleado",AA65="Familiar"),"Nombre del Empleado","N° Factura") -> N° Factura | AN68: =A59 -> 46267 | AO68: =C60 -> Consultorio N° 1 | AP68: =C89 -> 0 | AQ68: =D89 -> 0 | AR68: =U89 -> 0 | AS68: =S89 -> 0 | AT68: =S90 -> 0 | AU68: =U90 -> 0 | AV68: =S91 -> 0 | AW68: =U91 -> 0 | AX68: =U92 -> 0 | AY68: =F92 -> 0
A69: =A65+$Q$13/1440 -> 0.41666667 | E69: Representante: | F69: =IF(D69<>"", VLOOKUP(D69,'Base de Datos'!$A$2:$D1268,2,FALSE()),"") | G69: 🚫 | H69: Ivelisse Sosa | I69: Representante: | J69: =IF(H69<>"", VLOOKUP(H69,'Base de Datos'!$A$2:$D1268,2,FALSE()),"") -> Ivelisse Sosa | M69: Representante: | N69: =IF(L69<>"", VLOOKUP(L69,'Base de Datos'!$A$2:$D1268,2,FALSE()),"") | T69: Precio: | X69: Precio: | AB69: Precio: | AN69: =A59 -> 46267 | AO69: =C60 -> Consultorio N° 1 | AP69: =C93 -> 0 | AQ69: =D93 -> 0 | AR69: =U93 -> 0 | AS69: =S93 -> 0 | AT69: =S94 -> 0 | AU69: =U94 -> 0 | AV69: =S95 -> 0 | AW69: =U95 -> 0 | AX69: =U96 -> 0 | AY69: =F96 -> 0
E70: Teléfono: | F70: =IF(D69<>"", VLOOKUP(D69,'Base de Datos'!$A$2:$D1268,3,FALSE()),"") | I70: Teléfono: | J70: =IF(H69<>"", VLOOKUP(H69,'Base de Datos'!$A$2:$D1268,3,FALSE()),"") -> 0 | M70: Teléfono: | N70: =IF(L69<>"", VLOOKUP(L69,'Base de Datos'!$A$2:$D1268,3,FALSE()),"") | P70: LEYENDA | AN70: =A59 -> 46267 | AO70: =C60 -> Consultorio N° 1 | AP70: =C97 -> 0 | AQ70: =D97 -> 0 | AR70: =U97 -> 0 | AS70: =S97 -> 0 | AT70: =S98 -> 0 | AU70: =U98 -> 0 | AV70: =S99 -> 0 | AW70: =U99 -> 0 | AX70: =U100 -> 0 | AY70: =F100 -> 0
E71: Cedula: | F71: =IF(D69<>"", VLOOKUP(D69,'Base de Datos'!$A$2:$D1268,4,FALSE()),"") | I71: Cedula: | J71: =IF(H69<>"", VLOOKUP(H69,'Base de Datos'!$A$2:$D1268,4,FALSE()),"") -> 0 | M71: Cedula: | N71: =IF(L69<>"", VLOOKUP(L69,'Base de Datos'!$A$2:$D1268,4,FALSE()),"") | P71: 📌 | Q71: Agendada | AN71: =A59 -> 46267 | AO71: Consultorio N° 1 | AP71: =C101 -> 0 | AQ71: =D101 -> 0 | AR71: =U101 -> 0 | AS71: =S101 -> 0 | AT71: =S102 -> 0 | AU71: =U102 -> 0 | AV71: =S103 -> 0 | AW71: =U103 -> 0 | AX71: =U104 -> 0 | AY71: =F104 -> 0
E72: Doctor: | I72: Doctor: | J72: Luzmir Fagúndez | M72: Doctor: | P72: 📞 | Q72: Sin confirmar | S72: =IF(OR(S69="Empleado",S69="Familiar"),"Nombre del Empleado","N° Factura") -> N° Factura | W72: =IF(OR(W69="Empleado",W69="Familiar"),"Nombre del Empleado","N° Factura") -> N° Factura | AA72: =IF(OR(AA69="Empleado",AA69="Familiar"),"Nombre del Empleado","N° Factura") -> N° Factura | AN72: =A59 -> 46267 | AO72: Consultorio N° 1 | AP72: =C105 -> 0 | AQ72: =D105 -> 0 | AR72: =U105 -> 0 | AS72: =S105 -> 0 | AT72: =S106 -> 0 | AU72: =U106 -> 0 | AV72: =S107 -> 0 | AW72: =U107 -> 0 | AX72: =U108 -> 0 | AY72: =F108 -> 0
A73: =A69+$Q$13/1440 -> 0.45833333 | E73: Representante: | F73: =IF(D73<>"", VLOOKUP(D73,'Base de Datos'!$A$2:$D1268,2,FALSE()),"") | G73: 🚫 | H73: Geraldine Mendoza | I73: Representante: | J73: =IF(H73<>"", VLOOKUP(H73,'Base de Datos'!$A$2:$D1268,2,FALSE()),"") -> Geraldine Mendoza | M73: Representante: | N73: =IF(L73<>"", VLOOKUP(L73,'Base de Datos'!$A$2:$D1268,2,FALSE()),"") | P73: ✔️ | Q73: Confirmado | T73: Precio: | X73: Precio: | AB73: Precio: | AN73: =A59 -> 46267 | AO73: Consultorio N° 1 | AP73: =C109 -> 0 | AQ73: =D109 -> 0 | AR73: =U109 -> 0 | AS73: =S109 -> 0 | AT73: =S110 -> 0 | AU73: =U110 -> 0 | AV73: =S111 -> 0 | AW73: =U111 -> 0 | AX73: =U112 -> 0 | AY73: =F112 -> 0
E74: Teléfono: | F74: =IF(D73<>"", VLOOKUP(D73,'Base de Datos'!$A$2:$D1268,3,FALSE()),"") | I74: Teléfono: | J74: =IF(H73<>"", VLOOKUP(H73,'Base de Datos'!$A$2:$D1268,3,FALSE()),"") -> 0 | M74: Teléfono: | N74: =IF(L73<>"", VLOOKUP(L73,'Base de Datos'!$A$2:$D1268,3,FALSE()),"") | P74: ✅ | Q74: Completado | AN74: =A59 -> 46267 | AO74: =G60 -> Consultorio N° 2 | AP74: =G61 -> 0 | AQ74: =H61 -> 0 | AR74: =Y61 -> 0 | AS74: =W61 -> 0 | AT74: =W62 -> 0 | AU74: =Y62 -> 0 | AV74: =W63 -> 0 | AW74: =Y63 -> 0 | AX74: =Y64 -> 0 | AY74: =J64 -> 0
E75: Cedula: | F75: =IF(D73<>"", VLOOKUP(D73,'Base de Datos'!$A$2:$D1268,4,FALSE()),"") | I75: Cedula: | J75: =IF(H73<>"", VLOOKUP(H73,'Base de Datos'!$A$2:$D1268,4,FALSE()),"") -> 0 | M75: Cedula: | N75: =IF(L73<>"", VLOOKUP(L73,'Base de Datos'!$A$2:$D1268,4,FALSE()),"") | P75: 🚫 | Q75: No asistio | AN75: =A59 -> 46267 | AO75: =G60 -> Consultorio N° 2 | AP75: =G65 -> 0 | AQ75: =H65 -> 0 | AR75: =Y65 -> 0 | AS75: =W65 -> 0 | AT75: =W66 -> 0 | AU75: =Y66 -> 0 | AV75: =W67 -> 0 | AW75: =Y67 -> 0 | AX75: =Y68 -> 0 | AY75: =J68 -> 0
E76: Doctor: | I76: Doctor: | J76: Luzmir Fagúndez | M76: Doctor: | P76: 💲 | Q76: Pagado | S76: =IF(OR(S73="Empleado",S73="Familiar"),"Nombre del Empleado","N° Factura") -> N° Factura | W76: =IF(OR(W73="Empleado",W73="Familiar"),"Nombre del Empleado","N° Factura") -> N° Factura | AA76: =IF(OR(AA73="Empleado",AA73="Familiar"),"Nombre del Empleado","N° Factura") -> N° Factura | AN76: =A59 -> 46267 | AO76: =G60 -> Consultorio N° 2 | AP76: =G69 -> 🚫 | AQ76: =H69 -> Ivelisse Sosa | AR76: =Y69 -> 0 | AS76: =W69 -> 0 | AT76: =W70 -> 0 | AU76: =Y70 -> 0 | AV76: =W71 -> 0 | AW76: =Y71 -> 0 | AX76: =Y72 -> 0 | AY76: =J72 -> Luzmir Fagúndez
A77: =A73+$Q$13/1440 -> 0.5 | E77: Representante: | F77: =IF(D77<>"", VLOOKUP(D77,'Base de Datos'!$A$2:$D1268,2,FALSE()),"") | G77: 🚫 | H77: Karina Borges | I77: Representante: | J77: =IF(H77<>"", VLOOKUP(H77,'Base de Datos'!$A$2:$D1268,2,FALSE()),"") -> 0 | M77: Representante: | N77: =IF(L77<>"", VLOOKUP(L77,'Base de Datos'!$A$2:$D1268,2,FALSE()),"") | P77: 📦 | Q77: Facturado | T77: Precio: | X77: Precio: | AB77: Precio: | AN77: =A59 -> 46267 | AO77: =G60 -> Consultorio N° 2 | AP77: =G73 -> 🚫 | AQ77: =H73 -> Geraldine Mendoza | AR77: =Y73 -> 0 | AS77: =W73 -> 0 | AT77: =W74 -> 0 | AU77: =Y74 -> 0 | AV77: =W75 -> 0 | AW77: =Y75 -> 0 | AX77: =Y76 -> 0 | AY77: =J76 -> Luzmir Fagúndez
E78: Teléfono: | F78: =IF(D77<>"", VLOOKUP(D77,'Base de Datos'!$A$2:$D1268,3,FALSE()),"") | I78: Teléfono: | J78: =IF(H77<>"", VLOOKUP(H77,'Base de Datos'!$A$2:$D1268,3,FALSE()),"") -> 4142492199 | M78: Teléfono: | N78: =IF(L77<>"", VLOOKUP(L77,'Base de Datos'!$A$2:$D1268,3,FALSE()),"") | AN78: =A59 -> 46267 | AO78: =G60 -> Consultorio N° 2 | AP78: =G77 -> 🚫 | AQ78: =H77 -> Karina Borges | AR78: =Y77 -> 0 | AS78: =W77 -> 0 | AT78: =W78 -> 0 | AU78: =Y78 -> 0 | AV78: =W79 -> 0 | AW78: =Y79 -> 0 | AX78: =Y80 -> 0 | AY78: =J80 -> Luzmir Fagúndez
E79: Cedula: | F79: =IF(D77<>"", VLOOKUP(D77,'Base de Datos'!$A$2:$D1268,4,FALSE()),"") | I79: Cedula: | J79: =IF(H77<>"", VLOOKUP(H77,'Base de Datos'!$A$2:$D1268,4,FALSE()),"") -> V5313199 | M79: Cedula: | N79: =IF(L77<>"", VLOOKUP(L77,'Base de Datos'!$A$2:$D1268,4,FALSE()),"") | AN79: =A59 -> 46267 | AO79: =G60 -> Consultorio N° 2 | AP79: =G81 -> 0 | AQ79: =H81 -> 0 | AR79: =Y81 -> 0 | AS79: =W81 -> 0 | AT79: =W82 -> 0 | AU79: =Y82 -> 0 | AV79: =W83 -> 0 | AW79: =Y83 -> 0 | AX79: =Y84 -> 0 | AY79: =J84 -> 0
E80: Doctor: | I80: Doctor: | J80: Luzmir Fagúndez | M80: Doctor: | S80: =IF(OR(S77="Empleado",S77="Familiar"),"Nombre del Empleado","N° Factura") -> N° Factura | W80: =IF(OR(W77="Empleado",W77="Familiar"),"Nombre del Empleado","N° Factura") -> N° Factura | AA80: =IF(OR(AA77="Empleado",AA77="Familiar"),"Nombre del Empleado","N° Factura") -> N° Factura | AN80: =A59 -> 46267 | AO80: =G60 -> Consultorio N° 2 | AP80: =G85 -> 0 | AQ80: =H85 -> 0 | AR80: =Y85 -> 0 | AS80: =W85 -> 0 | AT80: =W86 -> 0 | AU80: =Y86 -> 0 | AV80: =W87 -> 0 | AW80: =Y87 -> 0 | AX80: =Y88 -> 0 | AY80: =J88 -> 0
A81: =A77+$Q$13/1440 -> 0.54166667 | E81: Representante: | F81: =IF(D81<>"", VLOOKUP(D81,'Base de Datos'!$A$2:$D1268,2,FALSE()),"") | I81: Representante: | J81: =IF(H81<>"", VLOOKUP(H81,'Base de Datos'!$A$2:$D1268,2,FALSE()),"") | M81: Representante: | N81: =IF(L81<>"", VLOOKUP(L81,'Base de Datos'!$A$2:$D1268,2,FALSE()),"") | T81: Precio: | X81: Precio: | AB81: Precio: | AN81: =A59 -> 46267 | AO81: =G60 -> Consultorio N° 2 | AP81: =G89 -> 0 | AQ81: =H89 -> 0 | AR81: =Y89 -> 0 | AS81: =W89 -> 0 | AT81: =W90 -> 0 | AU81: =Y90 -> 0 | AV81: =W91 -> 0 | AW81: =Y91 -> 0 | AX81: =Y92 -> 0 | AY81: =J92 -> 0
E82: Teléfono: | F82: =IF(D81<>"", VLOOKUP(D81,'Base de Datos'!$A$2:$D1268,3,FALSE()),"") | I82: Teléfono: | J82: =IF(H81<>"", VLOOKUP(H81,'Base de Datos'!$A$2:$D1268,3,FALSE()),"") | M82: Teléfono: | N82: =IF(L81<>"", VLOOKUP(L81,'Base de Datos'!$A$2:$D1268,3,FALSE()),"") | AN82: =A59 -> 46267 | AO82: =G60 -> Consultorio N° 2 | AP82: =G93 -> 0 | AQ82: =H93 -> 0 | AR82: =Y93 -> 0 | AS82: =W93 -> 0 | AT82: =W94 -> 0 | AU82: =Y94 -> 0 | AV82: =W95 -> 0 | AW82: =Y95 -> 0 | AX82: =Y96 -> 0 | AY82: =J96 -> 0
E83: Cedula: | F83: =IF(D81<>"", VLOOKUP(D81,'Base de Datos'!$A$2:$D1268,4,FALSE()),"") | I83: Cedula: | J83: =IF(H81<>"", VLOOKUP(H81,'Base de Datos'!$A$2:$D1268,4,FALSE()),"") | M83: Cedula: | N83: =IF(L81<>"", VLOOKUP(L81,'Base de Datos'!$A$2:$D1268,4,FALSE()),"") | AN83: =A59 -> 46267 | AO83: =G60 -> Consultorio N° 2 | AP83: =G97 -> 0 | AQ83: =H97 -> 0 | AR83: =Y97 -> 0 | AS83: =W97 -> 0 | AT83: =W98 -> 0 | AU83: =Y98 -> 0 | AV83: =W99 -> 0 | AW83: =Y99 -> 0 | AX83: =Y100 -> 0 | AY83: =J100 -> 0
E84: Doctor: | I84: Doctor: | M84: Doctor: | S84: =IF(OR(S81="Empleado",S81="Familiar"),"Nombre del Empleado","N° Factura") -> N° Factura | W84: =IF(OR(W81="Empleado",W81="Familiar"),"Nombre del Empleado","N° Factura") -> N° Factura | AA84: =IF(OR(AA81="Empleado",AA81="Familiar"),"Nombre del Empleado","N° Factura") -> N° Factura | AN84: =A59 -> 46267 | AO84: =K60 -> Consultorio N° 3 | AP84: =K61 -> 0 | AQ84: =L61 -> 0 | AR84: =AC61 -> 0 | AS84: =AA61 -> 0 | AT84: =AA62 -> 0 | AU84: =AC62 -> 0 | AV84: =AA63 -> 0 | AW84: =AC63 -> 0 | AX84: =AC64 -> 0 | AY84: =N64 -> 0
A85: =A81+$Q$13/1440 -> 0.58333333 | E85: Representante: | F85: =IF(D85<>"", VLOOKUP(D85,'Base de Datos'!$A$2:$D1268,2,FALSE()),"") | I85: Representante: | J85: =IF(H85<>"", VLOOKUP(H85,'Base de Datos'!$A$2:$D1268,2,FALSE()),"") | M85: Representante: | N85: =IF(L85<>"", VLOOKUP(L85,'Base de Datos'!$A$2:$D1268,2,FALSE()),"") | T85: Precio: | X85: Precio: | AB85: Precio: | AN85: =A59 -> 46267 | AO85: =K60 -> Consultorio N° 3 | AP85: =K65 -> 0 | AQ85: =L65 -> 0 | AR85: =AC65 -> 0 | AS85: =AA65 -> 0 | AT85: =AA66 -> 0 | AU85: =AC66 -> 0 | AV85: =AA67 -> 0 | AW85: =AC67 -> 0 | AX85: =AC68 -> 0 | AY85: =N68 -> 0
E86: Teléfono: | F86: =IF(D85<>"", VLOOKUP(D85,'Base de Datos'!$A$2:$D1268,3,FALSE()),"") | I86: Teléfono: | J86: =IF(H85<>"", VLOOKUP(H85,'Base de Datos'!$A$2:$D1268,3,FALSE()),"") | M86: Teléfono: | N86: =IF(L85<>"", VLOOKUP(L85,'Base de Datos'!$A$2:$D1268,3,FALSE()),"") | AN86: =A59 -> 46267 | AO86: =K60 -> Consultorio N° 3 | AP86: =K69 -> 0 | AQ86: =L69 -> 0 | AR86: =AC69 -> 0 | AS86: =AA69 -> 0 | AT86: =AA70 -> 0 | AU86: =AC70 -> 0 | AV86: =AA71 -> 0 | AW86: =AC71 -> 0 | AX86: =AC72 -> 0 | AY86: =N72 -> 0
E87: Cedula: | F87: =IF(D85<>"", VLOOKUP(D85,'Base de Datos'!$A$2:$D1268,4,FALSE()),"") | I87: Cedula: | J87: =IF(H85<>"", VLOOKUP(H85,'Base de Datos'!$A$2:$D1268,4,FALSE()),"") | M87: Cedula: | N87: =IF(L85<>"", VLOOKUP(L85,'Base de Datos'!$A$2:$D1268,4,FALSE()),"") | AN87: =A59 -> 46267 | AO87: =K60 -> Consultorio N° 3 | AP87: =K73 -> 0 | AQ87: =L73 -> 0 | AR87: =AC73 -> 0 | AS87: =AA73 -> 0 | AT87: =AA74 -> 0 | AU87: =AC74 -> 0 | AV87: =AA75 -> 0 | AW87: =AC75 -> 0 | AX87: =AC76 -> 0 | AY87: =N76 -> 0
E88: Doctor: | I88: Doctor: | M88: Doctor: | S88: =IF(OR(S85="Empleado",S85="Familiar"),"Nombre del Empleado","N° Factura") -> N° Factura | W88: =IF(OR(W85="Empleado",W85="Familiar"),"Nombre del Empleado","N° Factura") -> N° Factura | AA88: =IF(OR(AA85="Empleado",AA85="Familiar"),"Nombre del Empleado","N° Factura") -> N° Factura | AN88: =A59 -> 46267 | AO88: =K60 -> Consultorio N° 3 | AP88: =K77 -> 0 | AQ88: =L77 -> 0 | AR88: =AC77 -> 0 | AS88: =AA77 -> 0 | AT88: =AA78 -> 0 | AU88: =AC78 -> 0 | AV88: =AA79 -> 0 | AW88: =AC79 -> 0 | AX88: =AC80 -> 0 | AY88: =N80 -> 0
A89: =A85+$Q$13/1440 -> 0.625 | E89: Representante: | F89: =IF(D89<>"", VLOOKUP(D89,'Base de Datos'!$A$2:$D1268,2,FALSE()),"") | I89: Representante: | J89: =IF(H89<>"", VLOOKUP(H89,'Base de Datos'!$A$2:$D1268,2,FALSE()),"") | M89: Representante: | N89: =IF(L89<>"", VLOOKUP(L89,'Base de Datos'!$A$2:$D1268,2,FALSE()),"") | T89: Precio: | X89: Precio: | AB89: Precio: | AN89: =A59 -> 46267 | AO89: =K60 -> Consultorio N° 3 | AP89: =K81 -> 0 | AQ89: =L81 -> 0 | AR89: =AC81 -> 0 | AS89: =AA81 -> 0 | AT89: =AA82 -> 0 | AU89: =AC82 -> 0 | AV89: =AA83 -> 0 | AW89: =AC83 -> 0 | AX89: =AC84 -> 0 | AY89: =N84 -> 0
E90: Teléfono: | F90: =IF(D89<>"", VLOOKUP(D89,'Base de Datos'!$A$2:$D1268,3,FALSE()),"") | I90: Teléfono: | J90: =IF(H89<>"", VLOOKUP(H89,'Base de Datos'!$A$2:$D1268,3,FALSE()),"") | M90: Teléfono: | N90: =IF(L89<>"", VLOOKUP(L89,'Base de Datos'!$A$2:$D1268,3,FALSE()),"") | AN90: =A59 -> 46267 | AO90: =K60 -> Consultorio N° 3 | AP90: =K85 -> 0 | AQ90: =L85 -> 0 | AR90: =AC85 -> 0 | AS90: =AA85 -> 0 | AT90: =AA86 -> 0 | AU90: =AC86 -> 0 | AV90: =AA87 -> 0 | AW90: =AC87 -> 0 | AX90: =AC88 -> 0 | AY90: =N88 -> 0
E91: Cedula: | F91: =IF(D89<>"", VLOOKUP(D89,'Base de Datos'!$A$2:$D1268,4,FALSE()),"") | I91: Cedula: | J91: =IF(H89<>"", VLOOKUP(H89,'Base de Datos'!$A$2:$D1268,4,FALSE()),"") | M91: Cedula: | N91: =IF(L89<>"", VLOOKUP(L89,'Base de Datos'!$A$2:$D1268,4,FALSE()),"") | AN91: =A59 -> 46267 | AO91: =K60 -> Consultorio N° 3 | AP91: =K89 -> 0 | AQ91: =L89 -> 0 | AR91: =AC89 -> 0 | AS91: =AA89 -> 0 | AT91: =AA90 -> 0 | AU91: =AC90 -> 0 | AV91: =AA91 -> 0 | AW91: =AC91 -> 0 | AX91: =AC92 -> 0 | AY91: =N92 -> 0
E92: Doctor: | I92: Doctor: | M92: Doctor: | S92: =IF(OR(S89="Empleado",S89="Familiar"),"Nombre del Empleado","N° Factura") -> N° Factura | W92: =IF(OR(W89="Empleado",W89="Familiar"),"Nombre del Empleado","N° Factura") -> N° Factura | AA92: =IF(OR(AA89="Empleado",AA89="Familiar"),"Nombre del Empleado","N° Factura") -> N° Factura | AN92: =A59 -> 46267 | AO92: =K60 -> Consultorio N° 3 | AP92: =K93 -> 0 | AQ92: =L93 -> 0 | AR92: =AC93 -> 0 | AS92: =AA93 -> 0 | AT92: =AA94 -> 0 | AU92: =AC94 -> 0 | AV92: =AA95 -> 0 | AW92: =AC95 -> 0 | AX92: =AC96 -> 0 | AY92: =N96 -> 0
A93: =A89+$Q$13/1440 -> 0.66666667 | E93: Representante: | F93: =IF(D93<>"", VLOOKUP(D93,'Base de Datos'!$A$2:$D1268,2,FALSE()),"") | I93: Representante: | J93: =IF(H93<>"", VLOOKUP(H93,'Base de Datos'!$A$2:$D1268,2,FALSE()),"") | M93: Representante: | N93: =IF(L93<>"", VLOOKUP(L93,'Base de Datos'!$A$2:$D1268,2,FALSE()),"") | T93: Precio: | X93: Precio: | AB93: Precio: | AN93: =A59 -> 46267 | AO93: =K60 -> Consultorio N° 3 | AP93: =K97 -> 0 | AQ93: =L97 -> 0 | AR93: =AC97 -> 0 | AS93: =AA97 -> 0 | AT93: =AA98 -> 0 | AU93: =AC98 -> 0 | AV93: =AA99 -> 0 | AW93: =AC99 -> 0 | AX93: =AC100 -> 0 | AY93: =N100 -> 0
E94: Teléfono: | F94: =IF(D93<>"", VLOOKUP(D93,'Base de Datos'!$A$2:$D1268,3,FALSE()),"") | I94: Teléfono: | J94: =IF(H93<>"", VLOOKUP(H93,'Base de Datos'!$A$2:$D1268,3,FALSE()),"") | M94: Teléfono: | N94: =IF(L93<>"", VLOOKUP(L93,'Base de Datos'!$A$2:$D1268,3,FALSE()),"") | AE94: =A59 -> 46267 | AN94: =A59 -> 46267 | AO94: =K60 -> Consultorio N° 3 | AP94: =K101 -> 0 | AQ94: =L101 -> 0 | AR94: =AC101 -> 0 | AS94: =AA101 -> 0 | AT94: =AA102 -> 0 | AU94: =AC102 -> 0 | AV94: =AA103 -> 0 | AW94: =AC103 -> 0 | AX94: =AC104 -> 0 | AY94: =N104 -> 0
E95: Cedula: | F95: =IF(D93<>"", VLOOKUP(D93,'Base de Datos'!$A$2:$D1268,4,FALSE()),"") | I95: Cedula: | J95: =IF(H93<>"", VLOOKUP(H93,'Base de Datos'!$A$2:$D1268,4,FALSE()),"") | M95: Cedula: | N95: =IF(L93<>"", VLOOKUP(L93,'Base de Datos'!$A$2:$D1268,4,FALSE()),"") | AE95: Doctor | AG95: Cantidad citas | AH95: Citas pagadas | AI95: Total | AJ95: Monto Cobrado | AK95: Monto ADH | AL95: Monto Médico | AN95: =A59 -> 46267 | AO95: =K60 -> Consultorio N° 3 | AP95: =K105 -> 0 | AQ95: =L105 -> 0 | AR95: =AC105 -> 0 | AS95: =AA105 -> 0 | AT95: =AA106 -> 0 | AU95: =AC106 -> 0 | AV95: =AA107 -> 0 | AW95: =AC107 -> 0 | AX95: =AC108 -> 0 | AY95: =N108 -> 0
E96: Doctor: | I96: Doctor: | M96: Doctor: | S96: =IF(OR(S93="Empleado",S93="Familiar"),"Nombre del Empleado","N° Factura") -> N° Factura | W96: =IF(OR(W93="Empleado",W93="Familiar"),"Nombre del Empleado","N° Factura") -> N° Factura | AA96: =IF(OR(AA93="Empleado",AA93="Familiar"),"Nombre del Empleado","N° Factura") -> N° Factura | AE96: Dra. Rosanny García | AG96: {=COUNTIFS(AP61:AP101, "💲", AY61:AY101, INDIRECT("AE" & ROW())) + COUNTIFS(AP61:AP101, "📦", AY61:AY101, INDIRECT("AE" & ROW())) + COUNTIFS(AP61:AP101, "✅", AY61:AY101, INDIRECT("AE" & ROW()))} -> 0 | AH96: {=COUNTIFS(AP61:AP101, "💲", AY61:AY101, INDIRECT("AE" & ROW())) + COUNTIFS(AP61:AP101, "📦", AY61:AY101, INDIRECT("AE" & ROW()))} -> 0 | AI96: {=SUMIFS(AR61:AR101, AY61:AY101, INDIRECT("AE" & ROW()), AP61:AP101, "💲") + SUMIFS(AR61:AR101, AY61:AY101, INDIRECT("AE" & ROW()), AP61:AP101, "📦")} -> 0 | AJ96: {=( SUMIFS(AR61:AR101, AY61:AY101, INDIRECT("AE" & ROW()), AP61:AP101, "💲") + SUMIFS(AR61:AR101, AY61:AY101, INDIRECT("AE" & ROW()), AP61:AP101, "📦") ) - ( SUMIFS(AR61:AR101, AY61:AY101, INDIRECT("AE" & ROW()), AP61:AP101, "💲", AS61:AS101, "Participante") + SUMIFS(AR61:AR101, AY61:AY101, INDIRECT("AE" & ROW()), AP61:AP101, "📦", AS61:AS101, "Participante") ) - ( SUMIFS(AR61:AR101, AY61:AY101, INDIRECT("AE" & ROW()), AP61:AP101, "💲", AS61:AS101, "Empleado") + SUMIFS(AR61:AR101, AY61:AY101, INDIRECT("AE" & ROW()), AP61:AP101, "📦", AS61:AS101, "Empleado") ) - ( ( SUMIFS(AR61:AR101, AY61:AY101, INDIRECT("AE" & ROW()), AP61:AP101, "💲", AS61:AS101, "Familiar") + SUMIFS(AR61:AR101, AY61:AY101, INDIRECT("AE" & ROW()), AP61:AP101, "📦", AS61:AS101, "Familiar") ) / 2 ) - ( ( SUMIFS(AR61:AR101, AY61:AY101, INDIRECT("AE" & ROW()), AP61:AP101, "💲", AS61:AS101, "Exonerado ADH") + SUMIFS(AR61:AR101, AY61:AY101, INDIRECT("AE" & ROW()), AP61:AP101, "📦", AS61:AS101, "Exonerado ADH") ) / 2 ) - ( ( SUMIFS(AR61:AR101, AY61:AY101, INDIRECT("AE" & ROW()), AP61:AP101, "💲", AS61:AS101, "Exonerado Doctor") + SUMIFS(AR61:AR101, AY61:AY101, INDIRECT("AE" & ROW()), AP61:AP101, "📦", AS61:AS101, "Exonerado Doctor") ) / 2 )} -> 0 | AK96: {=( SUMIFS(AR61:AR101, AY61:AY101, INDIRECT("AE" & ROW()), AP61:AP101, "💲") + SUMIFS(AR61:AR101, AY61:AY101, INDIRECT("AE" & ROW()), AP61:AP101, "📦") ) - ( SUMIFS(AR61:AR101, AY61:AY101, INDIRECT("AE" & ROW()), AP61:AP101, "💲", AS61:AS101, "Familiar") + SUMIFS(AR61:AR101, AY61:AY101, INDIRECT("AE" & ROW()), AP61:AP101, "📦", AS61:AS101, "Familiar") ) - ( SUMIFS(AR61:AR101, AY61:AY101, INDIRECT("AE" & ROW()), AP61:AP101, "💲", AS61:AS101, "Participante") + SUMIFS(AR61:AR101, AY61:AY101, INDIRECT("AE" & ROW()), AP61:AP101, "📦", AS61:AS101, "Participante") ) - ( SUMIFS(AR61:AR101, AY61:AY101, INDIRECT("AE" & ROW()), AP61:AP101, "💲", AS61:AS101, "Empleado") + SUMIFS(AR61:AR101, AY61:AY101, INDIRECT("AE" & ROW()), AP61:AP101, "📦", AS61:AS101, "Empleado") ) - ( SUMIFS(AR61:AR101, AY61:AY101, INDIRECT("AE" & ROW()), AP61:AP101, "💲", AS61:AS101, "Exonerado ADH") + SUMIFS(AR61:AR101, AY61:AY101, INDIRECT("AE" & ROW()), AP61:AP101, "📦", AS61:AS101, "Exonerado ADH") ) - ( ( SUMIFS(AR61:AR101, AY61:AY101, INDIRECT("AE" & ROW()), AP61:AP101, "💲", AS61:AS101, "Exonerado Doctor") + SUMIFS(AR61:AR101, AY61:AY101, INDIRECT("AE" & ROW()), AP61:AP101, "📦", AS61:AS101, "Exonerado Doctor") ) / 2 ) - ( ( SUMIFS(AR61:AR101, AY61:AY101, INDIRECT("AE" & ROW()), AP61:AP101, "💲", AS61:AS101, "") + SUMIFS(AR61:AR101, AY61:AY101, INDIRECT("AE" & ROW()), AP61:AP101, "📦", AS61:AS101, "") ) / 2 )} -> 0 | AL96: {=( SUMIFS(AR61:AR101, AY61:AY101, INDIRECT("AE" & ROW()), AP61:AP101, "💲") + SUMIFS(AR61:AR101, AY61:AY101, INDIRECT("AE" & ROW()), AP61:AP101, "📦") ) - ( ( SUMIFS(AR61:AR101, AY61:AY101, INDIRECT("AE" & ROW()), AP61:AP101, "💲", AS61:AS101, "Familiar") + SUMIFS(AR61:AR101, AY61:AY101, INDIRECT("AE" & ROW()), AP61:AP101, "📦", AS61:AS101, "Familiar") ) / 2 ) - ( ( SUMIFS(AR61:AR101, AY61:AY101, INDIRECT("AE" & ROW()), AP61:AP101, "💲", AS61:AS101, "Participante") + SUMIFS(AR61:AR101, AY61:AY101, INDIRECT("AE" & ROW()), AP61:AP101, "📦", AS61:AS101, "Participante") ) / 2 ) - ( ( SUMIFS(AR61:AR101, AY61:AY101, INDIRECT("AE" & ROW()), AP61:AP101, "💲", AS61:AS101, "Empleado") + SUMIFS(AR61:AR101, AY61:AY101, INDIRECT("AE" & ROW()), AP61:AP101, "📦", AS61:AS101, "Empleado") ) / 2 ) - ( ( SUMIFS(AR61:AR101, AY61:AY101, INDIRECT("AE" & ROW()), AP61:AP101, "💲", AS61:AS101, "Exonerado ADH") + SUMIFS(AR61:AR101, AY61:AY101, INDIRECT("AE" & ROW()), AP61:AP101, "📦", AS61:AS101, "Exonerado ADH") ) / 2 ) - ( SUMIFS(AR61:AR101, AY61:AY101, INDIRECT("AE" & ROW()), AP61:AP101, "💲", AS61:AS101, "Exonerado Doctor") + SUMIFS(AR61:AR101, AY61:AY101, INDIRECT("AE" & ROW()), AP61:AP101, "📦", AS61:AS101, "Exonerado Doctor") ) - ( ( SUMIFS(AR61:AR101, AY61:AY101, INDIRECT("AE" & ROW()), AP61:AP101, "💲", AS61:AS101, "") + SUMIFS(AR61:AR101, AY61:AY101, INDIRECT("AE" & ROW()), AP61:AP101, "📦", AS61:AS101, "") ) / 2 )} -> 0 | AN96: =A59 -> 46267 | AO96: =K60 -> Consultorio N° 3 | AP96: =K109 -> 0 | AQ96: =L109 -> 0 | AR96: =AC109 -> 0 | AS96: =AA109 -> 0 | AT96: =AA110 -> 0 | AU96: =AC110 -> 0 | AV96: =AA111 -> 0 | AW96: =AC111 -> 0 | AX96: =AC112 -> 0 | AY96: =N112 -> 0
A97: =A93+$Q$13/1440 -> 0.70833333 | E97: Representante: | F97: =IF(D97<>"", VLOOKUP(D97,'Base de Datos'!$A$2:$D1268,2,FALSE()),"") | I97: Representante: | J97: =IF(H97<>"", VLOOKUP(H97,'Base de Datos'!$A$2:$D1268,2,FALSE()),"") | M97: Representante: | N97: =IF(L97<>"", VLOOKUP(L97,'Base de Datos'!$A$2:$D1268,2,FALSE()),"") | T97: Precio: | X97: Precio: | AB97: Precio: | AE97: Dra. Maribel Guilarte | AG97: {=COUNTIFS(AP61:AP101, "💲", AY61:AY101, INDIRECT("AE" & ROW())) + COUNTIFS(AP61:AP101, "📦", AY61:AY101, INDIRECT("AE" & ROW())) + COUNTIFS(AP61:AP101, "✅", AY61:AY101, INDIRECT("AE" & ROW()))} -> 0 | AH97: {=COUNTIFS(AP61:AP101, "💲", AY61:AY101, INDIRECT("AE" & ROW())) + COUNTIFS(AP61:AP101, "📦", AY61:AY101, INDIRECT("AE" & ROW()))} -> 0 | AI97: {=SUMIFS(AR61:AR101, AY61:AY101, INDIRECT("AE" & ROW()), AP61:AP101, "💲") + SUMIFS(AR61:AR101, AY61:AY101, INDIRECT("AE" & ROW()), AP61:AP101, "📦")} -> 0 | AJ97: {=( SUMIFS(AR61:AR101, AY61:AY101, INDIRECT("AE" & ROW()), AP61:AP101, "💲") + SUMIFS(AR61:AR101, AY61:AY101, INDIRECT("AE" & ROW()), AP61:AP101, "📦") ) - ( SUMIFS(AR61:AR101, AY61:AY101, INDIRECT("AE" & ROW()), AP61:AP101, "💲", AS61:AS101, "Participante") + SUMIFS(AR61:AR101, AY61:AY101, INDIRECT("AE" & ROW()), AP61:AP101, "📦", AS61:AS101, "Participante") ) - ( SUMIFS(AR61:AR101, AY61:AY101, INDIRECT("AE" & ROW()), AP61:AP101, "💲", AS61:AS101, "Empleado") + SUMIFS(AR61:AR101, AY61:AY101, INDIRECT("AE" & ROW()), AP61:AP101, "📦", AS61:AS101, "Empleado") ) - ( ( SUMIFS(AR61:AR101, AY61:AY101, INDIRECT("AE" & ROW()), AP61:AP101, "💲", AS61:AS101, "Familiar") + SUMIFS(AR61:AR101, AY61:AY101, INDIRECT("AE" & ROW()), AP61:AP101, "📦", AS61:AS101, "Familiar") ) / 2 ) - ( ( SUMIFS(AR61:AR101, AY61:AY101, INDIRECT("AE" & ROW()), AP61:AP101, "💲", AS61:AS101, "Exonerado ADH") + SUMIFS(AR61:AR101, AY61:AY101, INDIRECT("AE" & ROW()), AP61:AP101, "📦", AS61:AS101, "Exonerado ADH") ) / 2 ) - ( ( SUMIFS(AR61:AR101, AY61:AY101, INDIRECT("AE" & ROW()), AP61:AP101, "💲", AS61:AS101, "Exonerado Doctor") + SUMIFS(AR61:AR101, AY61:AY101, INDIRECT("AE" & ROW()), AP61:AP101, "📦", AS61:AS101, "Exonerado Doctor") ) / 2 )} -> 0 | AK97: {=( SUMIFS(AR61:AR101, AY61:AY101, INDIRECT("AE" & ROW()), AP61:AP101, "💲") + SUMIFS(AR61:AR101, AY61:AY101, INDIRECT("AE" & ROW()), AP61:AP101, "📦") ) - ( SUMIFS(AR61:AR101, AY61:AY101, INDIRECT("AE" & ROW()), AP61:AP101, "💲", AS61:AS101, "Familiar") + SUMIFS(AR61:AR101, AY61:AY101, INDIRECT("AE" & ROW()), AP61:AP101, "📦", AS61:AS101, "Familiar") ) - ( SUMIFS(AR61:AR101, AY61:AY101, INDIRECT("AE" & ROW()), AP61:AP101, "💲", AS61:AS101, "Participante") + SUMIFS(AR61:AR101, AY61:AY101, INDIRECT("AE" & ROW()), AP61:AP101, "📦", AS61:AS101, "Participante") ) - ( SUMIFS(AR61:AR101, AY61:AY101, INDIRECT("AE" & ROW()), AP61:AP101, "💲", AS61:AS101, "Empleado") + SUMIFS(AR61:AR101, AY61:AY101, INDIRECT("AE" & ROW()), AP61:AP101, "📦", AS61:AS101, "Empleado") ) - ( SUMIFS(AR61:AR101, AY61:AY101, INDIRECT("AE" & ROW()), AP61:AP101, "💲", AS61:AS101, "Exonerado ADH") + SUMIFS(AR61:AR101, AY61:AY101, INDIRECT("AE" & ROW()), AP61:AP101, "📦", AS61:AS101, "Exonerado ADH") ) - ( ( SUMIFS(AR61:AR101, AY61:AY101, INDIRECT("AE" & ROW()), AP61:AP101, "💲", AS61:AS101, "Exonerado Doctor") + SUMIFS(AR61:AR101, AY61:AY101, INDIRECT("AE" & ROW()), AP61:AP101, "📦", AS61:AS101, "Exonerado Doctor") ) / 2 ) - ( ( SUMIFS(AR61:AR101, AY61:AY101, INDIRECT("AE" & ROW()), AP61:AP101, "💲", AS61:AS101, "") + SUMIFS(AR61:AR101, AY61:AY101, INDIRECT("AE" & ROW()), AP61:AP101, "📦", AS61:AS101, "") ) / 2 )} -> 0 | AL97: {=( SUMIFS(AR61:AR101, AY61:AY101, INDIRECT("AE" & ROW()), AP61:AP101, "💲") + SUMIFS(AR61:AR101, AY61:AY101, INDIRECT("AE" & ROW()), AP61:AP101, "📦") ) - ( ( SUMIFS(AR61:AR101, AY61:AY101, INDIRECT("AE" & ROW()), AP61:AP101, "💲", AS61:AS101, "Familiar") + SUMIFS(AR61:AR101, AY61:AY101, INDIRECT("AE" & ROW()), AP61:AP101, "📦", AS61:AS101, "Familiar") ) / 2 ) - ( ( SUMIFS(AR61:AR101, AY61:AY101, INDIRECT("AE" & ROW()), AP61:AP101, "💲", AS61:AS101, "Participante") + SUMIFS(AR61:AR101, AY61:AY101, INDIRECT("AE" & ROW()), AP61:AP101, "📦", AS61:AS101, "Participante") ) / 2 ) - ( ( SUMIFS(AR61:AR101, AY61:AY101, INDIRECT("AE" & ROW()), AP61:AP101, "💲", AS61:AS101, "Empleado") + SUMIFS(AR61:AR101, AY61:AY101, INDIRECT("AE" & ROW()), AP61:AP101, "📦", AS61:AS101, "Empleado") ) / 2 ) - ( ( SUMIFS(AR61:AR101, AY61:AY101, INDIRECT("AE" & ROW()), AP61:AP101, "💲", AS61:AS101, "Exonerado ADH") + SUMIFS(AR61:AR101, AY61:AY101, INDIRECT("AE" & ROW()), AP61:AP101, "📦", AS61:AS101, "Exonerado ADH") ) / 2 ) - ( SUMIFS(AR61:AR101, AY61:AY101, INDIRECT("AE" & ROW()), AP61:AP101, "💲", AS61:AS101, "Exonerado Doctor") + SUMIFS(AR61:AR101, AY61:AY101, INDIRECT("AE" & ROW()), AP61:AP101, "📦", AS61:AS101, "Exonerado Doctor") ) - ( ( SUMIFS(AR61:AR101, AY61:AY101, INDIRECT("AE" & ROW()), AP61:AP101, "💲", AS61:AS101, "") + SUMIFS(AR61:AR101, AY61:AY101, INDIRECT("AE" & ROW()), AP61:AP101, "📦", AS61:AS101, "") ) / 2 )} -> 0 | AQ97: =L105 -> 0 | AY97: =N100 -> 0
